Workbook

Sheet PROTOCOLO
A1: PROTOCOLO EXPERIMENTAL DA DISSERTAÇÃO
A2: Avaliação Experimental de Ferramentas de IA Generativa na Análise de Documentos Financeiros da Administração Pública
A4: 1. IDENTIFICAÇÃO DA PESQUISA
A5: Título da pesquisa | B5: Avaliação Experimental de Ferramentas de IA Generativa na Análise de Documentos Financeiros da Administração Pública
A6: Objetivo geral | B6: Avaliar como diferentes ferramentas de Inteligência Artificial Generativa analisam documentos administrativos públicos.
A7: Objetivo da aplicação experimental | B7: Comparar, sob as mesmas condições possíveis (mesmo documento, mesma pergunta, mesmo contexto de teste), as respostas produzidas por 6 configurações de ferramentas de IA generativa frente a um conjunto padronizado de documentos administrativos e perguntas, contrastando cada resposta com uma resposta de referência (Gold) elaborada pelo pesquisador.
A9: 2. UNIDADE EXPERIMENTAL
A10: Unidade experimental | B10: Documento administrativo + Pergunta/prompt padronizado + Configuração de IA testada.
A11: Entrada (input) | B11: Documento administrativo público + pergunta/prompt padronizado, aplicados à ferramenta de IA.
A12: Saída (output) | B12: Resposta produzida pela ferramenta de Inteligência Artificial para o par documento+pergunta.
A13: Conceito de Gold | B13: Resposta de referência elaborada previamente pelo pesquisador, considerada correta e fundamentada diretamente no documento analisado, com evidência documental explícita (página/seção/trecho).
A14: Comparação realizada | B14: Documento + Pergunta + Gold x Documento + Pergunta + Resposta da IA, para cada uma das 9 configurações.
A16: 3. ESCOPO DO EXPERIMENTO
A17: Documentos analisados | B17: 06 documentos administrativos públicos, organizados em grupo de financeiro
A18: Ferramentas testadas | B18: ChatGPT, Claude e Gemini, cada uma em modalidade Gratuita, Paga 1 e Paga 2.
A19: Número de configurações de IA | B19: 6 (nove) configurações, avaliadas individualmente e sem agrupamento automático.
A20: Banco de perguntas | B20: 33 perguntas gerais (P01-P33)
A22: 4. CRITÉRIOS E CATEGORIAS
A23: Critérios de avaliação | B23: Correção, Completude, Precisão, Consistência, Clareza, Profundidade, Fidelidade Documental, Alucinação, Omissão, Interpretação e Conformidade (ver aba DICIONÁRIO DE DADOS).
A24: Categorias de perguntas | B24: Identificação, Localização, Extração, Organização, Interpretação, Identificação de Inconsistências, Detecção de Erros, Identificação de Omissões, Conformidade Documental, Análise de Risco, Comparação, Síntese, Rastreabilidade da Informação, Análise de Relações entre Informações
A25: Níveis de dificuldade | B25: Nível 1 - Extração Direta; Nível 2 - Localização e Organização; Nível 3 - Interpretação; Nível 4 - Análise; Nível 5 - Raciocínio Documental
A27: 5. REGRAS DE APLICAÇÃO E COMPARAÇÃO
A28: Regras de aplicação | B28: Cada configuração de IA recebe, sempre que possível, o mesmo documento, a mesma pergunta/prompt e o mesmo contexto de teste (nova conversa, sem histórico prévio, salvo quando o parâmetro de continuidade for objeto específico do teste).
A29: Regras de comparação | B29: As 6 configurações são comparadas separadamente entre si (não agrupadas). São admitidas comparações descritivas: por ferramenta . Não é criado ranking, nota prévia ou classificação de melhor/pior ferramenta: os resultados decorrem exclusivamente dos dados obtidos empiricamente.
A30: Controle das condições experimentais | B30: Registrado na aba CONTROLE METODOLÓGICO: mesmo documento, mesma versão, mesma pergunta, mesmo prompt, mesmo idioma, mesmo contexto, mesmo formato de arquivo, tentativas, intervenções humanas, acesso à internet, uso de memória/contexto e validade/comparabilidade de cada teste.
A32: 6. DECLARAÇÃO METODOLÓGICA
A33: Princípio de neutralidade | B33: Esta planilha não estabelece previamente qual ferramenta, modalidade, plano ou modelo é superior. Os resultados devem ser obtidos empiricamente a partir dos testes, e os cálculos de resultado apenas consolidam os dados inseridos pelo pesquisador.
A34: Regra de aplicação padronizada | B34: "Todas as ferramentas deverão receber, sempre que possível, o mesmo documento, a mesma pergunta e o mesmo contexto de teste."

Sheet DOCUMENTOS
A1: ABA 2 - DOCUMENTOS DO EXPERIMENTO (20 documentos / 5 grupos)
A2: ID_Doc | B2: Grupo | C2: Categoria | D2: Tipo Documental | E2: Nome do Documento | F2: Nº/Identificação | G2: Nº SEI | H2: Nº Processo | I2: Data | J2: Setor Responsável | K2: Finalidade | L2: Descrição | M2: Qtd. Páginas | N2: Formato do Arquivo | O2: Tamanho do Arquivo | P2: Observações | Q2: Link/Referência SEI | R2: Situação do Documento | S2: Documento Relacionado | T2: Processo Relacionado
A3: 1 | B3: Grupo 4 - Informação Financeira | C3: Financeiro | D3: Planilha de Custos | E3: Planilha Mapa Comparativo de Preços | F3: Mapa Comparativo de Preços | G3: 0631096 | H3: 23854.007448/2024-94 | Q3: SEI nº 0631096 (processo 23854.007448/2024-94)
A4: 2 | B4: Grupo 4 - Informação Financeira | C4: Financeiro | D4: Pesquisa de Preços | E4: Relatório Pesquisa de Preço - Banco de Preços | F4: Pesquisa de Preço - Banco de Preços | G4: 0631080 | H4: 23854.007448/2024-94 | Q4: SEI nº 0631080 (processo 23854.007448/2024-94)
A5: 3 | B5: Grupo 4 - Informação Financeira | C5: Financeiro | D5: Medição | E5: Boletim de Medição | F5: Boletim de Medição | G5: 0572838 | H5: 23854.003175/2026-71 | Q5: SEI nº 0572838 (processo 23854.003175/2026-71)
A6: 4 | B6: Grupo 4 - Informação Financeira | C6: Financeiro | D6: Nota Fiscal | E6: Nota Fiscal nº 119.235 - Março/26 | F6: NF 119.235 | G6: 0574135 | H6: 23854.003175/2026-71 | Q6: SEI nº 0574135 (processo 23854.003175/2026-71)
A7: 5 | B7: Grupo 4 - Informação Financeira | C7: Financeiro | D7: Nota de Empenho | E7: Empenho 2026NE000070 - Reforço | F7: NE 2026NE000070 | G7: 0601218 | H7: 23854.008489/2024-06 | Q7: SEI nº 0601218 (processo 23854.008489/2024-06)
A8: 6 | B8: Grupo 4 - Informação Financeira | C8: Financeiro | D8: Ordem Bancária | E8: Ordem Bancária 2026OB000456 | F8: OB 2026OB000456 | G8: 0604691 | H8: 23854.003091/2026-37 | Q8: SEI nº 0604691 (processo 23854.003091/2026-37)

Sheet BANCO DE PERGUNTAS
A1: ABA 3 - BANCO DE PERGUNTAS (33 gerais + 20 específicas por tipo documental)
A2: ID_Pergunta | B2: Categoria | C2: Subcategoria | D2: Pergunta | E2: Prompt Completo | F2: Objetivo | G2: Tipo Documental Aplicável | H2: Nível de Dificuldade | I2: Habilidade Avaliada | J2: Informação Esperada | K2: Permite 'Não Consta no Documento'? | L2: Requer Comparação com Outro Documento? | M2: Observação Metodológica
A3: P01 | B3: Identificação | C3: Objeto do documento | D3: Qual é o objeto principal deste documento? | E3: Com base exclusivamente no documento fornecido, responda: Qual é o objeto principal deste documento? Caso a informação não conste no documento, declare explicitamente 'não consta no documento'. | F3: Avaliar a capacidade da ferramenta de identificar informações do tipo 'identificação'. | G3: Geral (todos os tipos) | H3: 1 | I3: Identificar | J3: Ver evidência documental correspondente na aba GOLD. | K3: Não | L3: Não | M3: Pergunta geral, aplicável a qualquer tipo documental do corpus, resguardadas as adaptações de vocabulário indicadas entre colchetes.
A4: P02 | B4: Identificação | C4: Numeração do documento | D4: Qual é o número ou identificação do documento? | E4: Com base exclusivamente no documento fornecido, responda: Qual é o número ou identificação do documento? Caso a informação não conste no documento, declare explicitamente 'não consta no documento'. | F4: Avaliar a capacidade da ferramenta de identificar informações do tipo 'identificação'. | G4: Geral (todos os tipos) | H4: 1 | I4: Identificar | J4: Ver evidência documental correspondente na aba GOLD. | K4: Não | L4: Não | M4: Pergunta geral, aplicável a qualquer tipo documental do corpus, resguardadas as adaptações de vocabulário indicadas entre colchetes.
A5: P03 | B5: Identificação | C5: Processo relacionado | D5: Qual é o número do processo relacionado? | E5: Com base exclusivamente no documento fornecido, responda: Qual é o número do processo relacionado? Caso a informação não conste no documento, declare explicitamente 'não consta no documento'. | F5: Avaliar a capacidade da ferramenta de identificar informações do tipo 'identificação'. | G5: Geral (todos os tipos) | H5: 1 | I5: Identificar | J5: Ver evidência documental correspondente na aba GOLD. | K5: Sim | L5: Não | M5: Pergunta geral, aplicável a qualquer tipo documental do corpus, resguardadas as adaptações de vocabulário indicadas entre colchetes.
A6: P04 | B6: Identificação | C6: Data do documento | D6: Qual é a data do documento? | E6: Com base exclusivamente no documento fornecido, responda: Qual é a data do documento? Caso a informação não conste no documento, declare explicitamente 'não consta no documento'. | F6: Avaliar a capacidade da ferramenta de identificar informações do tipo 'identificação'. | G6: Geral (todos os tipos) | H6: 1 | I6: Identificar | J6: Ver evidência documental correspondente na aba GOLD. | K6: Sim | L6: Não | M6: Pergunta geral, aplicável a qualquer tipo documental do corpus, resguardadas as adaptações de vocabulário indicadas entre colchetes.
A7: P05 | B7: Identificação | C7: Setor responsável | D7: Qual setor ou unidade está relacionado ao documento? | E7: Com base exclusivamente no documento fornecido, responda: Qual setor ou unidade está relacionado ao documento? Caso a informação não conste no documento, declare explicitamente 'não consta no documento'. | F7: Avaliar a capacidade da ferramenta de identificar informações do tipo 'identificação'. | G7: Geral (todos os tipos) | H7: 1 | I7: Identificar | J7: Ver evidência documental correspondente na aba GOLD. | K7: Sim | L7: Não | M7: Pergunta geral, aplicável a qualquer tipo documental do corpus, resguardadas as adaptações de vocabulário indicadas entre colchetes.
A8: P06 | B8: Identificação | C8: Partes envolvidas | D8: Quais são as partes ou instituições mencionadas? | E8: Com base exclusivamente no documento fornecido, responda: Quais são as partes ou instituições mencionadas? Caso a informação não conste no documento, declare explicitamente 'não consta no documento'. | F8: Avaliar a capacidade da ferramenta de identificar/organizar informações do tipo 'identificação'. | G8: Geral (todos os tipos) | H8: 2 | I8: Identificar/Organizar | J8: Ver evidência documental correspondente na aba GOLD. | K8: Sim | L8: Não | M8: Pergunta geral, aplicável a qualquer tipo documental do corpus, resguardadas as adaptações de vocabulário indicadas entre colchetes.
A9: P07 | B9: Localização | C9: Informação em seção específica | D9: Qual informação específica está apresentada na seção 08? | E9: Com base exclusivamente no documento fornecido, responda: Qual informação específica está apresentada na seção 8? Caso a informação não conste no documento, declare explicitamente 'não consta no documento'. | F9: Avaliar a capacidade da ferramenta de localizar informações do tipo 'localização'. | G9: Geral (todos os tipos) | H9: 2 | I9: Localizar | J9: Ver evidência documental correspondente na aba GOLD. | K9: Sim | L9: Não | M9: Pergunta geral, aplicável a qualquer tipo documental do corpus, resguardadas as adaptações de vocabulário indicadas entre colchetes.
A10: P08 | B10: Localização | C10: Localização de informação | D10: Em qual seção do documento está localizada a informação solicitada? | E10: Com base exclusivamente no documento fornecido, responda: Em qual seção do documento está localizada a informação solicitada? Caso a informação não conste no documento, declare explicitamente 'não consta no documento'. | F10: Avaliar a capacidade da ferramenta de localizar informações do tipo 'localização'. | G10: Geral (todos os tipos) | H10: 2 | I10: Localizar | J10: Ver evidência documental correspondente na aba GOLD. | K10: Sim | L10: Não | M10: Pergunta geral, aplicável a qualquer tipo documental do corpus, resguardadas as adaptações de vocabulário indicadas entre colchetes.
A11: P09 | B11: Localização | C11: Valor de item | D11: Qual é o valor indicado para o Valor Total Anual do Objeto licitado? | E11: Com base exclusivamente no documento fornecido, responda: Qual é o valor indicado para [item]? Caso a informação não conste no documento, declare explicitamente 'não consta no documento'. | F11: Avaliar a capacidade da ferramenta de localizar/extrair informações do tipo 'localização'. | G11: Geral (todos os tipos) | H11: 1 | I11: Localizar/Extrair | J11: Ver evidência documental correspondente na aba GOLD. | K11: Sim | L11: Não | M11: Pergunta geral, aplicável a qualquer tipo documental do corpus, resguardadas as adaptações de vocabulário indicadas entre colchetes.
A12: P10 | B12: Localização | C12: Data de evento | D12: Qual é a data indicada para de assinatura de todos os membros da comissão da contratação? | E12: Com base exclusivamente no documento fornecido, responda: Qual é a data indicada para [evento]? Caso a informação não conste no documento, declare explicitamente 'não consta no documento'. | F12: Avaliar a capacidade da ferramenta de localizar/extrair informações do tipo 'localização'. | G12: Geral (todos os tipos) | H12: 1 | I12: Localizar/Extrair | J12: Ver evidência documental correspondente na aba GOLD. | K12: Sim | L12: Não | M12: Pergunta geral, aplicável a qualquer tipo documental do corpus, resguardadas as adaptações de vocabulário indicadas entre colchetes.
A13: P11 | B13: Extração | C13: Dados estruturados | D13: Extraia os principais dados do documento em formato estruturado. | E13: Com base exclusivamente no documento fornecido, responda: Extraia os principais dados do documento em formato estruturado. Caso a informação não conste no documento, declare explicitamente 'não consta no documento'. | F13: Avaliar a capacidade da ferramenta de extrair/organizar informações do tipo 'extração'. | G13: Geral (todos os tipos) | H13: 2 | I13: Extrair/Organizar | J13: Ver evidência documental correspondente na aba GOLD. | K13: Não | L13: Não | M13: Pergunta geral, aplicável a qualquer tipo documental do corpus, resguardadas as adaptações de vocabulário indicadas entre colchetes.
A14: P12 | B14: Extração | C14: Valores financeiros | D14: Liste os valores financeiros presentes no documento. | E14: Com base exclusivamente no documento fornecido, responda: Liste os valores financeiros presentes no documento. Caso a informação não conste no documento, declare explicitamente 'não consta no documento'. | F14: Avaliar a capacidade da ferramenta de extrair informações do tipo 'extração'. | G14: Geral (todos os tipos) | H14: 2 | I14: Extrair | J14: Ver evidência documental correspondente na aba GOLD. | K14: Sim | L14: Não | M14: Pergunta geral, aplicável a qualquer tipo documental do corpus, resguardadas as adaptações de vocabulário indicadas entre colchetes.
... A35: P33 | B35: Síntese | C35: Informações mais relevantes | D35: Quais são as três informações mais importantes para um servidor responsável pela análise? | E35: Com base exclusivamente no documento fornecido, responda: Quais são as três informações mais importantes para um servidor responsável pela análise? Caso a informação não conste no documento, declare explicitamente 'não consta no documento'. | F35: Avaliar a capacidade da ferramenta de sintetizar/avaliar relevância informações do tipo 'síntese'. | G35: Geral (todos os tipos) | H35: 3 | I35: Sintetizar/Avaliar Relevância | J35: Ver evidência documental correspondente na aba GOLD. | K35: Não | L35: Não | M35: Pergunta geral, aplicável a qualquer tipo documental do corpus, resguardadas as adaptações de vocabulário indicadas entre colchetes.

Sheet AVALIAÇÃO
A1: ABA 5 - AVALIAÇÃO (uma linha por Documento+Pergunta; um bloco de critérios por configuração de IA)
A2: ID_Doc | B2: ID_Pergunta | C2: Documento | D2: Pergunta | E2: Categoria | F2: Nível | G2: ChatGPT - teste | U2: ChatGPT - GPT-6 Astra | AI2: ChatGPT - GPT-5.6 Luna | AW2: Claude - teste | BK2: Claude - Sonnet 5 | BY2: Claude - Opus 5 | CM2: Gemini - teste | DA2: Gemini - 3.1 Pro | DO2: Gemini - 3.5 Flash
G3: Resposta | H3: Tempo (s) | I3: Correção | J3: Completude | K3: Precisão | L3: Consistência | M3: Clareza | N3: Profundidade | O3: Fidelidade Documental | P3: Alucinação | Q3: Omissão | R3: Erro | S3: Tipo de Erro | T3: Justificativa | U3: Resposta | V3: Tempo (s) | W3: Correção | X3: Completude | Y3: Precisão | Z3: Consistência | AA3: Clareza | AB3: Profundidade | AC3: Fidelidade Documental | AD3: Alucinação | AE3: Omissão | AF3: Erro | AG3: Tipo de Erro | AH3: Justificativa | AI3: Resposta | AJ3: Tempo (s) | AK3: Correção | AL3: Completude | AM3: Precisão | AN3: Consistência | AO3: Clareza | AP3: Profundidade | AQ3: Fidelidade Documental | AR3: Alucinação | AS3: Omissão | AT3: Erro | AU3: Tipo de Erro | AV3: Justificativa | AW3: Resposta | AX3: Tempo (s) | AY3: Correção | AZ3: Completude | BA3: Precisão | BB3: Consistência | BC3: Clareza | BD3: Profundidade | BE3: Fidelidade Documental | BF3: Alucinação | BG3: Omissão | BH3: Erro | BI3: Tipo de Erro | BJ3: Justificativa | BK3: Resposta | BL3: Tempo (s) | BM3: Correção | BN3: Completude | BO3: Precisão | BP3: Consistência | BQ3: Clareza | BR3: Profundidade | BS3: Fidelidade Documental | BT3: Alucinação | BU3: Omissão | BV3: Erro | BW3: Tipo de Erro | BX3: Justificativa | BY3: Resposta | BZ3: Tempo (s) | CA3: Correção | CB3: Completude | CC3: Precisão | CD3: Consistência | CE3: Clareza | CF3: Profundidade | CG3: Fidelidade Documental | CH3: Alucinação | CI3: Omissão | CJ3: Erro | CK3: Tipo de Erro | CL3: Justificativa | CM3: Resposta | CN3: Tempo (s) | CO3: Correção | CP3: Completude | CQ3: Precisão | CR3: Consistência | CS3: Clareza | CT3: Profundidade | CU3: Fidelidade Documental | CV3: Alucinação | CW3: Omissão | CX3: Erro | CY3: Tipo de Erro | CZ3: Justificativa | DA3: Resposta | DB3: Tempo (s) | DC3: Correção | DD3: Completude | DE3: Precisão | DF3: Consistência | DG3: Clareza | DH3: Profundidade | DI3: Fidelidade Documental | DJ3: Alucinação | DK3: Omissão | DL3: Erro | DM3: Tipo de Erro | DN3: Justificativa | DO3: Resposta | DP3: Tempo (s) | DQ3: Correção | DR3: Completude | DS3: Precisão | DT3: Consistência | DU3: Clareza | DV3: Profundidade | DW3: Fidelidade Documental | DX3: Alucinação | DY3: Omissão | DZ3: Erro | EA3: Tipo de Erro | EB3: Justificativa
A4: 11 | B4: P01 | C4: {=IFERROR(INDEX(DOCUMENTOS!$E:$E,MATCH($A4,DOCUMENTOS!$A:$A,0)),"")} | D4: {=IFERROR(INDEX('BANCO DE PERGUNTAS'!$D:$D,MATCH($B4,'BANCO DE PERGUNTAS'!$A:$A,0)),"")} -> Qual é o objeto principal deste documento? | E4: {=IFERROR(INDEX('BANCO DE PERGUNTAS'!$B:$B,MATCH($B4,'BANCO DE PERGUNTAS'!$A:$A,0)),"")} -> Identificação | F4: {=IFERROR(INDEX('BANCO DE PERGUNTAS'!$H:$H,MATCH($B4,'BANCO DE PERGUNTAS'!$A:$A,0)),"")} -> 1 | U4: Comparar preços para serviços de limpeza e conservação diurna, 44 horas, com materiais sob demanda e equipamentos, na Universidade Federal de Jataí, utilizando o contrato vigente atualizado e pesquisa no Banco de Preços. | W4: 2 | X4: 2 | Y4: 2 | Z4: 2 | AA4: 2 | AB4: 2 | AC4: 2 | AD4: Não | AE4: Não | AF4: Não | AI4: A planilha apresenta o mapa comparativo de preços para a contratação de serviços de limpeza e conservação, incluindo mão de obra, materiais sob demanda e equipamentos. | AK4: 2 | AL4: 2 | AM4: 2 | AN4: 2 | AO4: 2 | AP4: 2 | AQ4: 2 | AR4: Não | AS4: Não | AT4: Não | BK4: Mapa comparativo de preços para subsidiar a análise do valor do contrato de prestação de serviço de limpeza e conservação (diurna, 44h) da Universidade Federal de Jataí, incluindo material sob demanda e equipamentos com BDI. | BM4: 2 | BN4: 2 | BO4: 2 | BP4: 2 | BQ4: 2 | BR4: 2 | BS4: 2 | BT4: Não | BU4: Não | BV4: Não | BY4: Mapa comparativo de preços destinado a estimar o valor da contratação de prestação de serviço de limpeza e conservação (diurna, 44 horas, categoria A) para a Universidade Federal de Jataí, incluindo material sob demanda + BDI e equipamentos + BDI. | CA4: 2 | CB4: 2 | CC4: 2 | CD4: 2 | CE4: 2 | CF4: 2 | CG4: 2 | CH4: Não | CI4: Não | CJ4: Não | DA4: Mapa Comparativo de Preços para contratação de prestação de serviço de limpeza e conservação, fornecimento de material e equipamentos. | DC4: 2 | DD4: 2 | DE4: 2 | DF4: 2 | DG4: 2 | DH4: 2 | DI4: 2 | DJ4: Não | DK4: Não | DL4: Não | DO4: Mapa comparativo de preços para prestação de serviço de limpeza e conservação diurna (44 horas), material sob demanda e equipamentos. | DQ4: 2 | DR4: 2 | DS4: 2 | DT4: 2 | DU4: 2 | DV4: 2 | DW4: 2 | DX4: Não | DY4: Não | DZ4: Não
A5: 11 | B5: P02 | C5: {=IFERROR(INDEX(DOCUMENTOS!$E:$E,MATCH($A5,DOCUMENTOS!$A:$A,0)),"")} | D5: {=IFERROR(INDEX('BANCO DE PERGUNTAS'!$D:$D,MATCH($B5,'BANCO DE PERGUNTAS'!$A:$A,0)),"")} -> Qual é o número ou identificação do documento? | E5: {=IFERROR(INDEX('BANCO DE PERGUNTAS'!$B:$B,MATCH($B5,'BANCO DE PERGUNTAS'!$A:$A,0)),"")} -> Identificação | F5: {=IFERROR(INDEX('BANCO DE PERGUNTAS'!$H:$H,MATCH($B5,'BANCO DE PERGUNTAS'!$A:$A,0)),"")} -> 1 | U5: Identificação no conteúdo: “Planilha - Mapa Comparativo de Preços”. Número próprio do documento: não consta no documento. O identificador 0631096 aparece no nome do arquivo fornecido. | W5: 2 | X5: 2 | Y5: 2 | Z5: 2 | AA5: 2 | AB5: 2 | AC5: 2 | AD5: Não | AE5: Não | AF5: Não | AI5: Não consta no corpo da planilha um número individual do documento. O título é “Mapa Comparativo de Preços”. | AK5: 2 | AL5: 2 | AM5: 2 | AN5: 2 | AO5: 2 | AP5: 2 | AQ5: 2 | AR5: Não | AS5: Não | AT5: Não | BK5: O documento não apresenta um número próprio de identificação (é uma "Planilha - Mapa Comparativo de Preços"). Refere-se ao Contrato nº 113/2024 e ao Termo de Apostilamento nº 01/2026 (0616763). | BM5: 2 | BN5: 2 | BO5: 2 | BP5: 2 | BQ5: 2 | BR5: 2 | BS5: 2 | BT5: Não | BU5: Não | BV5: Não | BY5: O documento se identifica apenas como 'PLANILHA - MAPA COMPARATIVO DE PREÇOS'; o corpo não traz número SEI próprio. O nome do arquivo indica o documento SEI nº 0631096. | CA5: 2 | CB5: 2 | CC5: 2 | CD5: 2 | CE5: 2 | CF5: 2 | CG5: 2 | CH5: Não | CI5: Não | CJ5: Não | DA5: Planilha Mapa Comparativo de Preços (0631096). | DC5: 2 | DD5: 2 | DE5: 2 | DF5: 2 | DG5: 2 | DH5: 2 | DI5: 2 | DJ5: Não | DK5: Não | DL5: Não | DO5: Documento 0631096 (Mapa Comparativo de Preços). | DQ5: 1 | DR5: 2 | DS5: 1 | DT5: 1 | DU5: 2 | DV5: 2 | DW5: 1 | DX5: Não | DY5: Não | DZ5: Sim | EA5: Erro de interpretação
A6: 11 | B6: P03 | C6: {=IFERROR(INDEX(DOCUMENTOS!$E:$E,MATCH($A6,DOCUMENTOS!$A:$A,0)),"")} | D6: {=IFERROR(INDEX('BANCO DE PERGUNTAS'!$D:$D,MATCH($B6,'BANCO DE PERGUNTAS'!$A:$A,0)),"")} -> Qual é o número do processo relacionado? | E6: {=IFERROR(INDEX('BANCO DE PERGUNTAS'!$B:$B,MATCH($B6,'BANCO DE PERGUNTAS'!$A:$A,0)),"")} -> Identificação | F6: {=IFERROR(INDEX('BANCO DE PERGUNTAS'!$H:$H,MATCH($B6,'BANCO DE PERGUNTAS'!$A:$A,0)),"")} -> 1 | U6: Processo administrativo SEI 23854.007448/2024-94. | W6: 2 | X6: 2 | Y6: 2 | Z6: 2 | AA6: 2 | AB6: 2 | AC6: 2 | AD6: Não | AE6: Não | AF6: Não | AI6: 23854.007448/2024-94. | AK6: 2 | AL6: 2 | AM6: 2 | AN6: 2 | AO6: 2 | AP6: 2 | AQ6: 2 | AR6: Não | AS6: Não | AT6: Não | BK6: Processo Administrativo SEI nº 23854.007448/2024-94. | BM6: 2 | BN6: 2 | BO6: 2 | BP6: 2 | BQ6: 2 | BR6: 2 | BS6: 2 | BT6: Não | BU6: Não | BV6: Não | BY6: Processo Administrativo SEI nº 23854.007448/2024-94. | CA6: 2 | CB6: 2 | CC6: 2 | CD6: 2 | CE6: 2 | CF6: 2 | CG6: 2 | CH6: Não | CI6: Não | CJ6: Não | DA6: Processo Administrativo SEI 23854.007448/2024-94. | DC6: 2 | DD6: 2 | DE6: 2 | DF6: 2 | DG6: 2 | DH6: 2 | DI6: 2 | DJ6: Não | DK6: Não | DL6: Não | DO6: Processo Administrativo SEI 23854.007448/2024-94. | DQ6: 2 | DR6: 2 | DS6: 2 | DT6: 2 | DU6: 2 | DV6: 2 | DW6: 2 | DX6: Não | DY6: Não | DZ6: Não
A7: 11 | B7: P04 | C7: {=IFERROR(INDEX(DOCUMENTOS!$E:$E,MATCH($A7,DOCUMENTOS!$A:$A,0)),"")} | D7: {=IFERROR(INDEX('BANCO DE PERGUNTAS'!$D:$D,MATCH($B7,'BANCO DE PERGUNTAS'!$A:$A,0)),"")} -> Qual é a data do documento? | E7: {=IFERROR(INDEX('BANCO DE PERGUNTAS'!$B:$B,MATCH($B7,'BANCO DE PERGUNTAS'!$A:$A,0)),"")} -> Identificação | F7: {=IFERROR(INDEX('BANCO DE PERGUNTAS'!$H:$H,MATCH($B7,'BANCO DE PERGUNTAS'!$A:$A,0)),"")} -> 1 | U7: 24 de agosto de 2026, em Jataí. A representação da assinatura digital indica 24/08/2026, às 10:02:42, fuso -0300. | W7: 2 | X7: 2 | Y7: 2 | Z7: 2 | AA7: 2 | AB7: 2 | AC7: 2 | AD7: Não | AE7: Não | AF7: Não | AI7: Jataí, 24 de agosto de 2026. | AK7: 2 | AL7: 2 | AM7: 2 | AN7: 2 | AO7: 2 | AP7: 2 | AQ7: 2 | AR7: Não | AS7: Não | AT7: Não | BK7: Jataí, 24 de agosto de 2026 (data também confirmada na assinatura digital: 24/08/2026 10:02:42-0300). | BM7: 2 | BN7: 2 | BO7: 2 | BP7: 2 | BQ7: 2 | BR7: 2 | BS7: 2 | BT7: Não | BU7: Não | BV7: Não | BY7: Jataí, 24 de agosto de 2026 (assinatura digital gov.br em 24/08/2026, às 10:02:42, fuso -0300). | CA7: 2 | CB7: 2 | CC7: 2 | CD7: 2 | CE7: 2 | CF7: 2 | CG7: 2 | CH7: Não | CI7: Não | CJ7: Não | DA7: 24 de Agosto de 2026. | DC7: 2 | DD7: 2 | DE7: 2 | DF7: 2 | DG7: 2 | DH7: 2 | DI7: 2 | DJ7: Não | DK7: Não | DL7: Não | DO7: 24 de Agosto de 2026. | DQ7: 2 | DR7: 2 | DS7: 2 | DT7: 2 | DU7: 2 | DV7: 2 | DW7: 2 | DX7: Não | DY7: Não | DZ7: Não
A8: 11 | B8: P05 | C8: {=IFERROR(INDEX(DOCUMENTOS!$E:$E,MATCH($A8,DOCUMENTOS!$A:$A,0)),"")} | D8: {=IFERROR(INDEX('BANCO DE PERGUNTAS'!$D:$D,MATCH($B8,'BANCO DE PERGUNTAS'!$A:$A,0)),"")} -> Qual setor ou unidade está relacionado ao documento? | E8: {=IFERROR(INDEX('BANCO DE PERGUNTAS'!$B:$B,MATCH($B8,'BANCO DE PERGUNTAS'!$A:$A,0)),"")} -> Identificação | F8: {=IFERROR(INDEX('BANCO DE PERGUNTAS'!$H:$H,MATCH($B8,'BANCO DE PERGUNTAS'!$A:$A,0)),"")} -> 1 | U8: Pró-Reitoria de Administração e Finanças da Universidade Federal de Jataí (PROAD/UFJ). | W8: 2 | X8: 2 | Y8: 2 | Z8: 2 | AA8: 2 | AB8: 2 | AC8: 2 | AD8: Não | AE8: Não | AF8: Não | AI8: Universidade Federal de Jataí (UFJ), por meio da Pró-Reitoria de Administração e Finanças (PROAD/UFJ). | AK8: 2 | AL8: 2 | AM8: 2 | AN8: 2 | AO8: 2 | AP8: 2 | AQ8: 2 | AR8: Não | AS8: Não | AT8: Não | BK8: PROAD/UFJ – Pró-Reitoria de Administração e Finanças da Universidade Federal de Jataí (UFJ). | BM8: 2 | BN8: 2 | BO8: 2 | BP8: 2 | BQ8: 2 | BR8: 2 | BS8: 2 | BT8: Não | BU8: Não | BV8: Não | BY8: Pró-Reitoria de Administração e Finanças - PROAD/UFJ, da Universidade Federal de Jataí. | CA8: 2 | CB8: 2 | CC8: 2 | CD8: 2 | CE8: 2 | CF8: 2 | CG8: 2 | CH8: Não | CI8: Não | CJ8: Não | DA8: Pró-Reitoria de Administração e Finanças (PROAD/UFPROAD) da Universidade Federal de Jataí (UFJ). | DC8: 2 | DD8: 2 | DE8: 2 | DF8: 2 | DG8: 2 | DH8: 2 | DI8: 2 | DJ8: Não | DK8: Não | DL8: Não | DO8: Universidade Federal de Jataí (UFJ) - Pró-Reitoria de Administração e Finanças (PROAD/UFPROAD). | DQ8: 2 | DR8: 2 | DS8: 2 | DT8: 2 | DU8: 2 | DV8: 2 | DW8: 2 | DX8: Não | DY8: Não | DZ8: Não
A9: 11 | B9: P06 | C9: {=IFERROR(INDEX(DOCUMENTOS!$E:$E,MATCH($A9,DOCUMENTOS!$A:$A,0)),"")} | D9: {=IFERROR(INDEX('BANCO DE PERGUNTAS'!$D:$D,MATCH($B9,'BANCO DE PERGUNTAS'!$A:$A,0)),"")} -> Quais são as partes ou instituições mencionadas? | E9: {=IFERROR(INDEX('BANCO DE PERGUNTAS'!$B:$B,MATCH($B9,'BANCO DE PERGUNTAS'!$A:$A,0)),"")} -> Identificação | F9: {=IFERROR(INDEX('BANCO DE PERGUNTAS'!$H:$H,MATCH($B9,'BANCO DE PERGUNTAS'!$A:$A,0)),"")} -> 2 | U9: Universidade Federal de Jataí (UFJ); Pró-Reitoria de Administração e Finanças (PROAD/UFJ); Banco de Preços, fonte da pesquisa. Consta como signatário Marcos Paulo Pereira Fagundes. A empresa do contrato nº 113/2024 não é identificada. | W9: 2 | X9: 2 | Y9: 2 | Z9: 2 | AA9: 2 | AB9: 2 | AC9: 2 | AD9: Não | AE9: Não | AF9: Não | AI9: Universidade Federal de Jataí (UFJ); PROAD/UFJ; Banco de Preços; e o Contrato nº 113/2024 da Universidade Federal de Jataí, citado como referência. | AK9: 2 | AL9: 2 | AM9: 2 | AN9: 2 | AO9: 2 | AP9: 2 | AQ9: 2 | AR9: Não | AS9: Não | AT9: Não | BK9: Universidade Federal de Jataí (UFJ); PROAD/UFJ; Banco de Preços (site bancodeprecos.com.br), usado como fonte da pesquisa de mercado (Preço 02). | BM9: 2 | BN9: 2 | BO9: 2 | BP9: 2 | BQ9: 2 | BR9: 2 | BS9: 2 | BT9: Não | BU9: Não | BV9: Não | BY9: Universidade Federal de Jataí (UFJ) e PROAD/UFJ; o site Banco de Preços (www.bancodeprecos.com.br) como fonte de pesquisa; referência ao Contrato nº 113/2024, ao Termo de Apostilamento nº 01/2026 (0616763) e à Convenção Coletiva de Trabalho 2026/2027 (0602942); signatário Marcos Paulo Pereira Fagundes. A empresa contratada não é nominada. | CA9: 2 | CB9: 2 | CC9: 2 | CD9: 2 | CE9: 2 | CF9: 2 | CG9: 2 | CH9: Não | CI9: Não | CJ9: Não | DA9: Universidade Federal de Jataí (UFJ) e Banco de Preços. | DC9: 1 | DD9: 2 | DE9: 1 | DF9: 1 | DG9: 2 | DH9: 2 | DI9: 1 | DJ9: Não | DK9: Não | DL9: Sim | DM9: Erro de interpretação | DO9: Universidade Federal de Jataí (UFJ) e Banco de Preços. | DQ9: 1 | DR9: 2 | DS9: 1 | DT9: 1 | DU9: 2 | DV9: 2 | DW9: 1 | DX9: Não | DY9: Não | DZ9: Sim | EA9: Erro de interpretação
A10: 11 | B10: P07 | C10: {=IFERROR(INDEX(DOCUMENTOS!$E:$E,MATCH($A10,DOCUMENTOS!$A:$A,0)),"")} | D10: {=IFERROR(INDEX('BANCO DE PERGUNTAS'!$D:$D,MATCH($B10,'BANCO DE PERGUNTAS'!$A:$A,0)),"")} -> Qual informação específica está apresentada na seção 08? | E10: {=IFERROR(INDEX('BANCO DE PERGUNTAS'!$B:$B,MATCH($B10,'BANCO DE PERGUNTAS'!$A:$A,0)),"")} -> Localização | F10: {=IFERROR(INDEX('BANCO DE PERGUNTAS'!$H:$H,MATCH($B10,'BANCO DE PERGUNTAS'!$A:$A,0)),"")} -> 2 | U10: não consta no documento. O mapa tem uma página e não apresenta seção 08. | W10: 2 | X10: 2 | Y10: 2 | Z10: 2 | AA10: 2 | AB10: 2 | AC10: 2 | AD10: Não | AE10: Não | AF10: Não | AI10: Não consta no documento. A planilha não contém uma seção numerada 08. | AK10: 2 | AL10: 2 | AM10: 2 | AN10: 2 | AO10: 2 | AP10: 2 | AQ10: 2 | AR10: Não | AS10: Não | AT10: Não | BK10: Não consta "Seção 08" no documento — ele não é estruturado em seções numeradas, apenas em uma tabela única (Grupo/Item) e notas de rodapé (Preço 01 e Preço 02). | BM10: 2 | BN10: 2 | BO10: 2 | BP10: 2 | BQ10: 2 | BR10: 2 | BS10: 2 | BT10: Não | BU10: Não | BV10: Não | BY10: Não há seção 08 no documento. Trata-se de planilha de página única, sem divisão em seções numeradas; a estrutura se limita ao quadro de itens (Grupo 1, itens 1 a 3), ao total e às notas 'Preço 01' e 'Preço 02'. | CA10: 2 | CB10: 2 | CC10: 2 | CD10: 2 | CE10: 2 | CF10: 2 | CG10: 2 | CH10: Não | CI10: Não | CJ10: Não | DA10: Não há seção 08 identificada no documento. | DC10: 2 | DD10: 2 | DE10: 2 | DF10: 2 | DG10: 2 | DH10: 2 | DI10: 2 | DJ10: Não | DK10: Não | DL10: Não | DO10: Não há seção 08 especificada no documento. | DQ10: 2 | DR10: 2 | DS10: 2 | DT10: 2 | DU10: 2 | DV10: 2 | DW10: 2 | DX10: Não | DY10: Não | DZ10: Não
A11: 11 | B11: P08 | C11: {=IFERROR(INDEX(DOCUMENTOS!$E:$E,MATCH($A11,DOCUMENTOS!$A:$A,0)),"")} | D11: {=IFERROR(INDEX('BANCO DE PERGUNTAS'!$D:$D,MATCH($B11,'BANCO DE PERGUNTAS'!$A:$A,0)),"")} -> Em qual seção do documento está localizada a informação solicitada? | E11: {=IFERROR(INDEX('BANCO DE PERGUNTAS'!$B:$B,MATCH($B11,'BANCO DE PERGUNTAS'!$A:$A,0)),"")} -> Localização | F11: {=IFERROR(INDEX('BANCO DE PERGUNTAS'!$H:$H,MATCH($B11,'BANCO DE PERGUNTAS'!$A:$A,0)),"")} -> 2 | U11: A pergunta não especifica qual informação deve ser localizada. O documento não possui seções numeradas: identificação e processo no cabeçalho; itens, preços e total na tabela central; fontes nas notas “Preço 01” e “Preço 02”; data e assinatura na parte inferior, tudo na página 1. | W11: 2 | X11: 2 | Y11: 2 | Z11: 2 | AA11: 2 | AB11: 2 | AC11: 2 | AD11: Não | AE11: Não | AF11: Não | AI11: A planilha não tem seções numeradas. Os preços e quantitativos estão na tabela central; a origem dos preços está nas notas “Preço 01” e “Preço 02” abaixo da tabela. | AK11: 2 | AL11: 2 | AM11: 2 | AN11: 2 | AO11: 2 | AP11: 2 | AQ11: 2 | AR11: Não | AS11: Não | AT11: Não | BK11: Não aplicável: o documento não possui seções numeradas. As informações estão organizadas em uma única tabela comparativa de preços e duas notas explicativas (Preço 01 e Preço 02). | BM11: 2 | BN11: 2 | BO11: 2 | BP11: 2 | BQ11: 2 | BR11: 2 | BS11: 2 | BT11: Não | BU11: Não | BV11: Não | BY11: Não aplicável: o documento não possui seções numeradas. As informações estão distribuídas entre o cabeçalho institucional, o quadro de itens, a linha de total por extenso e as notas explicativas 'Preço 01' e 'Preço 02'. | CA11: 2 | CB11: 2 | CC11: 2 | CD11: 2 | CE11: 2 | CF11: 2 | CG11: 2 | CH11: Não | CI11: Não | CJ11: Não | DA11: Não aplicável, pois não foi encontrada seção 08. | DC11: 2 | DD11: 2 | DE11: 2 | DF11: 2 | DG11: 2 | DH11: 2 | DI11: 2 | DJ11: Não | DK11: Não | DL11: Não | DO11: Não aplicável. | DQ11: 2 | DR11: 2 | DS11: 2 | DT11: 2 | DU11: 2 | DV11: 2 | DW11: 2 | DX11: Não | DY11: Não | DZ11: Não
A12: 11 | B12: P09 | C12: {=IFERROR(INDEX(DOCUMENTOS!$E:$E,MATCH($A12,DOCUMENTOS!$A:$A,0)),"")} | D12: {=IFERROR(INDEX('BANCO DE PERGUNTAS'!$D:$D,MATCH($B12,'BANCO DE PERGUNTAS'!$A:$A,0)),"")} -> Qual é o valor indicado para o Valor Total Anual do Objeto licitado? | E12: {=IFERROR(INDEX('BANCO DE PERGUNTAS'!$B:$B,MATCH($B12,'BANCO DE PERGUNTAS'!$A:$A,0)),"")} -> Localização | F12: {=IFERROR(INDEX('BANCO DE PERGUNTAS'!$H:$H,MATCH($B12,'BANCO DE PERGUNTAS'!$A:$A,0)),"")} -> 1 | U12: Total geral indicado: R$ 2.350.378,54. A denominação “Valor Total Anual do Objeto licitado” não consta no documento. Materiais e equipamentos têm quantidade de 12 meses; a periodicidade da quantidade de 434.000 m² do serviço não está explicitada. | W12: 2 | X12: 2 | Y12: 2 | Z12: 2 | AA12: 2 | AB12: 2 | AC12: 2 | AD12: Não | AE12: Não | AF12: Não | AI12: R$ 2.350.378,54 para os 12 meses indicados na planilha. | AK12: 2 | AL12: 2 | AM12: 2 | AN12: 2 | AO12: 2 | AP12: 2 | AQ12: 2 | AR12: Não | AS12: Não | AT12: Não | BK12: R$ 2.350.378,54 (dois milhões, trezentos e cinquenta mil, trezentos e setenta e oito reais e cinquenta e quatro centavos). | BM12: 2 | BN12: 2 | BO12: 2 | BP12: 2 | BQ12: 2 | BR12: 2 | BS12: 2 | BT12: Não | BU12: Não | BV12: Não | BY12: R$ 2.350.378,54 (dois milhões, trezentos e cinquenta mil, trezentos e setenta e oito reais e cinquenta e quatro centavos). Observação: o documento não emprega a expressão 'anual'; a natureza anual é inferida dos itens 2 e 3, cotados para 12 meses. | CA12: 2 | CB12: 2 | CC12: 2 | CD12: 2 | CE12: 2 | CF12: 2 | CG12: 2 | CH12: Não | CI12: Não | CJ12: Não | DA12: R$ 2.350.378,54. | DC12: 2 | DD12: 2 | DE12: 2 | DF12: 2 | DG12: 2 | DH12: 2 | DI12: 2 | DJ12: Não | DK12: Não | DL12: Não | DO12: R$ 2.350.378,54 (Dois milhões, trezentos e cinquenta mil, trezentos e setenta e oito reais e cinquenta e quatro centavos). | DQ12: 2 | DR12: 2 | DS12: 2 | DT12: 2 | DU12: 2 | DV12: 2 | DW12: 2 | DX12: Não | DY12: Não | DZ12: Não
A13: 11 | B13: P10 | C13: {=IFERROR(INDEX(DOCUMENTOS!$E:$E,MATCH($A13,DOCUMENTOS!$A:$A,0)),"")} | D13: {=IFERROR(INDEX('BANCO DE PERGUNTAS'!$D:$D,MATCH($B13,'BANCO DE PERGUNTAS'!$A:$A,0)),"")} -> Qual é a data indicada para de assinatura de todos os membros da comissão da contratação? | E13: {=IFERROR(INDEX('BANCO DE PERGUNTAS'!$B:$B,MATCH($B13,'BANCO DE PERGUNTAS'!$A:$A,0)),"")} -> Localização | F13: {=IFERROR(INDEX('BANCO DE PERGUNTAS'!$H:$H,MATCH($B13,'BANCO DE PERGUNTAS'!$A:$A,0)),"")} -> 1 | U13: não consta no documento. Há uma representação de assinatura digital de Marcos Paulo Pereira Fagundes em 24/08/2026, às 10:02:42 (-0300), mas não há identificação da comissão nem das assinaturas de todos os seus membros. | W13: 2 | X13: 2 | Y13: 2 | Z13: 2 | AA13: 2 | AB13: 2 | AC13: 2 | AD13: Não | AE13: Não | AF13: Não | AI13: Não consta no documento. Há a data “Jataí, 24 de agosto de 2026”, mas não há data de assinatura de comissão nem identificação de seus membros. | AK13: 2 | AL13: 2 | AM13: 2 | AN13: 2 | AO13: 2 | AP13: 2 | AQ13: 2 | AR13: Não | AS13: Não | AT13: Não | BK13: Não consta no documento. Há apenas uma assinatura digital individual (Marcos Paulo Pereira Fagundes, gov.br) datada de 24/08/2026; não há menção a comissão de contratação nem a assinaturas de outros membros. | BM13: 2 | BN13: 2 | BO13: 2 | BP13: 2 | BQ13: 2 | BR13: 2 | BS13: 2 | BT13: Não | BU13: Não | BV13: Não | BY13: Não consta. O documento traz uma única assinatura digital, de Marcos Paulo Pereira Fagundes, em 24/08/2026; não há identificação nem assinatura de membros de comissão ou de equipe de planejamento da contratação. | CA13: 2 | CB13: 2 | CC13: 2 | CD13: 2 | CE13: 2 | CF13: 2 | CG13: 2 | CH13: Não | CI13: Não | CJ13: Não | DA13: Não há menção a todos os membros. Consta apenas a assinatura de Marcos Paulo Pereira Fagundes em 24/08/2026 às 10:02:42. | DC13: 2 | DD13: 2 | DE13: 2 | DF13: 2 | DG13: 2 | DH13: 2 | DI13: 2 | DJ13: Não | DK13: Não | DL13: Não | DO13: Assinado digitalmente por Marcos Paulo Pereira Fagundes em 24/08/2026 10:02:42-0300 (membro/responsável signatário, sem comissão de contratação listada). | DQ13: 2 | DR13: 2 | DS13: 2 | DT13: 2 | DU13: 2 | DV13: 2 | DW13: 2 | DX13: Não | DY13: Não | DZ13: Não
A14: 11 | B14: P11 | C14: {=IFERROR(INDEX(DOCUMENTOS!$E:$E,MATCH($A14,DOCUMENTOS!$A:$A,0)),"")} | D14: {=IFERROR(INDEX('BANCO DE PERGUNTAS'!$D:$D,MATCH($B14,'BANCO DE PERGUNTAS'!$A:$A,0)),"")} -> Extraia os principais dados do documento em formato estruturado. | E14: {=IFERROR(INDEX('BANCO DE PERGUNTAS'!$B:$B,MATCH($B14,'BANCO DE PERGUNTAS'!$A:$A,0)),"")} -> Extração | F14: {=IFERROR(INDEX('BANCO DE PERGUNTAS'!$H:$H,MATCH($B14,'BANCO DE PERGUNTAS'!$A:$A,0)),"")} -> 2 | U14: Documento: Mapa Comparativo de Preços; órgão: UFJ; unidade: PROAD; processo: 23854.007448/2024-94; data: 24/08/2026; grupo: 1; CATSER dos três itens: 25194; item 1: limpeza e conservação diurna, 44 horas (A), 434.000 m², média R$ 4,84, total R$ 2.100.603,40; item 2: Material Sob Demanda + BDI, 12 meses, média R$ 17.763,49, total R$ 213.161,82; item 3: Equipamentos BDI, 12 meses, média R$ 3.051,11, total R$ 36.613,32; total geral: R$ 2.350.378,54; fontes: contrato nº 113/2024 atualizado e Banco de Preços; signatário visível: Marcos Paulo Pereira Fagundes. | W14: 2 | X14: 2 | Y14: 2 | Z14: 2 | AA14: 2 | AB14: 2 | AC14: 2 | AD14: Não | AE14: Não | AF14: Não | AI14: Processo: 23854.007448/2024-94. Unidade: UFJ/PROAD. Objeto: serviço de limpeza e conservação. Grupo: 1. Item 1: 434.000 m², serviço diurno de 44 horas, média R$ 4,84, total R$ 2.100.603,40. Item 2: 12 meses, material sob demanda + BDI, média R$ 17.763,49, total R$ 213.161,82. Item 3: 12 meses, equipamentos + BDI, média R$ 3.051,11, total R$ 36.613,32. Total: R$ 2.350.378,54. Fontes: contrato UFJ nº 113/2024 atualizado e pesquisa no Banco de Preços. Data: 24/08/2026. | AK14: 2 | AL14: 2 | AM14: 2 | AN14: 2 | AO14: 2 | AP14: 2 | AQ14: 2 | AR14: Não | AS14: Não | AT14: Não | BK14: Processo SEI: 23854.007448/2024-94 | Contrato: 113/2024 (UFJ) | Apostilamento: nº 01/2026 (0616763) | Convenção Coletiva: 2026/2027 (0602942) | Órgão: PROAD/UFJ | Data: 24/08/2026 | Item 1: limpeza/conservação, 434.000 m², média R$4,84, total R$2.100.603,40 | Item 2: material sob demanda+BDI, 12 meses, média R$17.763,49, total R$213.161,82 | Item 3: equipamentos BDI, 12 meses, média R$3.051,11, total R$36.613,32 | Valor total: R$2.350.378,54 | Fonte pesquisa: Banco de Preços. | BM14: 2 | BN14: 2 | BO14: 2 | BP14: 2 | BQ14: 2 | BR14: 2 | BS14: 2 | BT14: Não | BU14: Não | BV14: Não | BY14: Órgão: UFJ - PROAD. Documento: Planilha - Mapa Comparativo de Preços. Processo: SEI 23854.007448/2024-94. Data: 24/08/2026. Grupo 1 - Item 1: CATSER 25194, unidade m², qtd. 434.000, 'Prestação de Serviço de limpeza e conservação - Diurna - 44 horas (A)', Preço 01 R$ 4,71, Preço 02 R$ 4,97, média R$ 4,84, total R$ 2.100.603,40. Item 2: CATSER 25194, unidade Meses, qtd. 12, 'Material Sob Demanda + BDI', R$ 15.295,00 / R$ 20.231,97, média R$ 17.763,49, total R$ 213.161,82. Item 3: CATSER 25194, unidade Meses, qtd. 12, 'Equipamentos BDI', R$ 2.638,75 / R$ 3.463,47, média R$ 3.051,11, total R$ 36.613,32. Total geral: R$ 2.350.378,54. Preço 01 = contrato 113/2024 atualizado pelo Apostilamento 01/2026 (CCT 2026/2027). Preço 02 = média do Banco de Preços. | CA14: 2 | CB14: 2 | CC14: 2 | CD14: 2 | CE14: 2 | CF14: 2 | CG14: 2 | CH14: Não | CI14: Não | CJ14: Não | DA14: Processo: 23854.007448/2024-94 | Objeto: Serviços de limpeza | Valor: R$ 2.350.378,54 | Data: 24/08/2026 | Assinante: Marcos Paulo Pereira Fagundes. | DC14: 2 | DD14: 2 | DE14: 2 | DF14: 2 | DG14: 2 | DH14: 2 | DI14: 2 | DJ14: Não | DK14: Não | DL14: Não | DO14: Tabela com 3 itens: 1) Serviço de limpeza diurna 44h; 2) Material sob demanda; 3) Equipamentos, contendo quantidades, preços unitários (Contrato e Banco de Preços) e totais. | DQ14: 2 | DR14: 2 | DS14: 2 | DT14: 2 | DU14: 2 | DV14: 2 | DW14: 2 | DX14: Não | DY14: Não | DZ14: Não
A15: 11 | B15: P12 | C15: {=IFERROR(INDEX(DOCUMENTOS!$E:$E,MATCH($A15,DOCUMENTOS!$A:$A,0)),"")} | D15: {=IFERROR(INDEX('BANCO DE PERGUNTAS'!$D:$D,MATCH($B15,'BANCO DE PERGUNTAS'!$A:$A,0)),"")} -> Liste os valores financeiros presentes no documento. | E15: {=IFERROR(INDEX('BANCO DE PERGUNTAS'!$B:$B,MATCH($B15,'BANCO DE PERGUNTAS'!$A:$A,0)),"")} -> Extração | F15: {=IFERROR(INDEX('BANCO DE PERGUNTAS'!$H:$H,MATCH($B15,'BANCO DE PERGUNTAS'!$A:$A,0)),"")} -> 2 | U15: Item 1: Preço 01 R$ 4,71; Preço 02 R$ 4,97; média R$ 4,84; total R$ 2.100.603,40. Item 2: Preço 01 R$ 15.295,00; Preço 02 R$ 20.231,97; média R$ 17.763,49; total R$ 213.161,82. Item 3: Preço 01 R$ 2.638,75; Preço 02 R$ 3.463,47; média R$ 3.051,11; total R$ 36.613,32. Total geral: R$ 2.350.378,54, também escrito por extenso. | W15: 2 | X15: 2 | Y15: 2 | Z15: 2 | AA15: 2 | AB15: 2 | AC15: 2 | AD15: Não | AE15: Não | AF15: Não | AI15: Item 1: R$ 4,71; R$ 4,97; média R$ 4,84; total R$ 2.100.603,40. Item 2: R$ 15.295,00; R$ 20.231,97; média R$ 17.763,49; total R$ 213.161,82. Item 3: R$ 2.638,75; R$ 3.463,47; média R$ 3.051,11; total R$ 36.613,32. Total geral: R$ 2.350.378,54. | AK15: 2 | AL15: 2 | AM15: 2 | AN15: 2 | AO15: 2 | AP15: 2 | AQ15: 2 | AR15: Não | AS15: Não | AT15: Não | BK15: Item 1: R$4,71 (Preço01) / R$4,97 (Preço02) / R$4,84 (média) / R$2.100.603,40 (total). Item 2: R$15.295,00 / R$20.231,97 / R$17.763,49 / R$213.161,82. Item 3: R$2.638,75 / R$3.463,47 / R$3.051,11 / R$36.613,32. Total geral: R$2.350.378,54. | BM15: 2 | BN15: 2 | BO15: 2 | BP15: 2 | BQ15: 2 | BR15: 2 | BS15: 2 | BT15: Não | BU15: Não | BV15: Não | BY15: Item 1: R$ 4,71; R$ 4,97; média R$ 4,84; total R$ 2.100.603,40. Item 2: R$ 15.295,00; R$ 20.231,97; média R$ 17.763,49; total R$ 213.161,82. Item 3: R$ 2.638,75; R$ 3.463,47; média R$ 3.051,11; total R$ 36.613,32. Total geral: R$ 2.350.378,54. | CA15: 2 | CB15: 2 | CC15: 2 | CD15: 2 | CE15: 2 | CF15: 2 | CG15: 2 | CH15: Não | CI15: Não | CJ15: Não | DA15: Preços unitários: R$ 4,71; R$ 4,97; R$ 4,84; R$ 15.295,00; R$ 20.231,97; R$ 17.763,42; R$ 2.638,75; R$ 3.463,47; R$ 3.051,11. Subtotais: R$ 2.100.603,40; R$ 213.161,82; R$ 36.613,32. Total Geral: R$ 2.350.378,54. | DC15: 2 | DD15: 2 | DE15: 2 | DF15: 2 | DG15: 2 | DH15: 2 | DI15: 2 | DJ15: Não | DK15: Não | DL15: Não | DO15: R$ 4,71; R$ 4,97; R$ 4,84; R$ 2.100.603,40; R$ 15.295,00; R$ 20.231,97; R$ 17.763,42; R$ 213.161,82; R$ 2.638,75; R$ 3.463,47; R$ 3.051,11; R$ 36.613,32; R$ 2.350.378,54. | DQ15: 2 | DR15: 2 | DS15: 2 | DT15: 2 | DU15: 2 | DV15: 2 | DW15: 2 | DX15: Não | DY15: Não | DZ15: Não
A16: 11 | B16: P13 | C16: {=IFERROR(INDEX(DOCUMENTOS!$E:$E,MATCH($A16,DOCUMENTOS!$A:$A,0)),"")} | D16: {=IFERROR(INDEX('BANCO DE PERGUNTAS'!$D:$D,MATCH($B16,'BANCO DE PERGUNTAS'!$A:$A,0)),"")} -> Liste as obrigações ou responsabilidades estabelecidas. | E16: {=IFERROR(INDEX('BANCO DE PERGUNTAS'!$B:$B,MATCH($B16,'BANCO DE PERGUNTAS'!$A:$A,0)),"")} -> Extração | F16: {=IFERROR(INDEX('BANCO DE PERGUNTAS'!$H:$H,MATCH($B16,'BANCO DE PERGUNTAS'!$A:$A,0)),"")} -> 2 | U16: Obrigações ou responsabilidades expressamente atribuídas às partes: não consta no documento. O mapa apenas descreve os componentes de custo: limpeza e conservação diurna, 44 horas, materiais sob demanda com BDI e equipamentos BDI. | W16: 2 | X16: 2 | Y16: 2 | Z16: 2 | AA16: 2 | AB16: 2 | AC16: 2 | AD16: Não | AE16: Não | AF16: Não | AI16: Não há obrigações contratuais estabelecidas. A planilha registra critérios e fontes de pesquisa de preços, sem impor responsabilidades ou prazos a partes. | AK16: 2 | AL16: 2 | AM16: 2 | AN16: 2 | AO16: 2 | AP16: 2 | AQ16: 2 | AR16: Não | AS16: Não | AT16: Não | BK16: O documento não estabelece obrigações ou responsabilidades contratuais — é uma planilha comparativa de preços, não um contrato ou termo de referência. Nenhuma obrigação é fixada no texto. | BM16: 2 | BN16: 2 | BO16: 2 | BP16: 2 | BQ16: 2 | BR16: 2 | BS16: 2 | BT16: Não | BU16: Não | BV16: Não | BY16: O documento não estabelece obrigações ou responsabilidades. É peça meramente instrutória/estimativa da fase preparatória; obrigações contratuais devem ser buscadas no Termo de Referência, no edital e no contrato correspondentes. | CA16: 2 | CB16: 2 | CC16: 2 | CD16: 2 | CE16: 2 | CF16: 2 | CG16: 2 | CH16: Não | CI16: Não | CJ16: Não | DA16: Prestação de Serviço de limpeza e conservação Diurna 44 horas, além de Material Sob Demanda e Equipamentos (com BDI). | DC16: 1 | DD16: 1 | DE16: 1 | DF16: 2 | DG16: 2 | DH16: 1 | DI16: 2 | DJ16: Não | DK16: Sim | DL16: Sim | DM16: Erro de interpretação | DO16: Prestação de serviço contínuo de limpeza e conservação diurna, fornecimento de materiais sob demanda e disponibilização de equipamentos. | DQ16: 2 | DR16: 2 | DS16: 2 | DT16: 2 | DU16: 2 | DV16: 2 | DW16: 2 | DX16: Não | DY16: Não | DZ16: Não | EA16: Erro de interpretação
A17: 11 | B17: P14 | C17: {=IFERROR(INDEX(DOCUMENTOS!$E:$E,MATCH($A17,DOCUMENTOS!$A:$A,0)),"")} | D17: {=IFERROR(INDEX('BANCO DE PERGUNTAS'!$D:$D,MATCH($B17,'BANCO DE PERGUNTAS'!$A:$A,0)),"")} -> Explique o significado da cláusula/seção 4.1.4.. | E17: {=IFERROR(INDEX('BANCO DE PERGUNTAS'!$B:$B,MATCH($B17,'BANCO DE PERGUNTAS'!$A:$A,0)),"")} -> Interpretação | F17: {=IFERROR(INDEX('BANCO DE PERGUNTAS'!$H:$H,MATCH($B17,'BANCO DE PERGUNTAS'!$A:$A,0)),"")} -> 3 | U17: não consta no documento. Não há cláusula ou seção 4.1.4. | W17: 2 | X17: 2 | Y17: 2 | Z17: 2 | AA17: 2 | AB17: 2 | AC17: 2 | AD17: Não | AE17: Não | AF17: Não | AI17: Não consta no documento. Não há cláusula ou seção 4.1.4. | AK17: 2 | AL17: 2 | AM17: 2 | AN17: 2 | AO17: 2 | AP17: 2 | AQ17: 2 | AR17: Não | AS17: Não | AT17: Não | BK17: Não consta cláusula ou seção "4.1.4" neste documento; ele não possui numeração de cláusulas. | BM17: 2 | BN17: 2 | BO17: 2 | BP17: 2 | BQ17: 2 | BR17: 2 | BS17: 2 | BT17: Não | BU17: Não | BV17: Não | BY17: Não existe cláusula ou seção 4.1.4 neste documento. A planilha não é estruturada em cláusulas numeradas; a referência provavelmente pertence a outra peça do processo (Termo de Referência, edital ou contrato). | CA17: 2 | CB17: 2 | CC17: 2 | CD17: 2 | CE17: 2 | CF17: 2 | CG17: 2 | CH17: Não | CI17: Não | CJ17: Não | DA17: Não há cláusula ou seção 4.1.4 no documento. | DC17: 2 | DD17: 2 | DE17: 2 | DF17: 2 | DG17: 2 | DH17: 2 | DI17: 2 | DJ17: Não | DK17: Não | DL17: Não | DO17: Não consta cláusula ou seção 4.1.4 no documento. | DQ17: 2 | DR17: 2 | DS17: 2 | DT17: 2 | DU17: 2 | DV17: 2 | DW17: 2 | DX17: Não | DY17: Não | DZ17: Não
A18: 11 | B18: P15 | C18: {=IFERROR(INDEX(DOCUMENTOS!$E:$E,MATCH($A18,DOCUMENTOS!$A:$A,0)),"")} | D18: {=IFERROR(INDEX('BANCO DE PERGUNTAS'!$D:$D,MATCH($B18,'BANCO DE PERGUNTAS'!$A:$A,0)),"")} -> Qual é a finalidade administrativa deste documento? | E18: {=IFERROR(INDEX('BANCO DE PERGUNTAS'!$B:$B,MATCH($B18,'BANCO DE PERGUNTAS'!$A:$A,0)),"")} -> Interpretação | F18: {=IFERROR(INDEX('BANCO DE PERGUNTAS'!$H:$H,MATCH($B18,'BANCO DE PERGUNTAS'!$A:$A,0)),"")} -> 3 | U18: Subsidiar a estimativa de custos da contratação no processo 23854.007448/2024-94, mediante comparação entre valores atualizados do contrato nº 113/2024 e valores pesquisados no Banco de Preços; finalidade inferida do título e da tabela. | W18: 2 | X18: 2 | Y18: 2 | Z18: 2 | AA18: 2 | AB18: 2 | AC18: 2 | AD18: Não | AE18: Não | AF18: Não | AI18: Apoiar o planejamento da contratação, comparando referências de preços e apresentando uma estimativa para o serviço de limpeza e conservação. | AK18: 2 | AL18: 2 | AM18: 2 | AN18: 2 | AO18: 2 | AP18: 2 | AQ18: 2 | AR18: Não | AS18: Não | AT18: Não | BK18: Comparar o valor atualizado do contrato vigente (Preço 01) com a média de preços de mercado obtida no Banco de Preços (Preço 02), para subsidiar decisões administrativas relacionadas ao reajuste/repactuação do Processo SEI 23854.007448/2024-94. | BM18: 2 | BN18: 2 | BO18: 2 | BP18: 2 | BQ18: 2 | BR18: 2 | BS18: 2 | BT18: Não | BU18: Não | BV18: Não | BY18: Documentar a pesquisa de preços e fixar a estimativa do valor da contratação, instruindo a fase preparatória do procedimento (art. 23 da Lei nº 14.133/2021 e IN SEGES/ME nº 65/2021), de modo a subsidiar a autorização da despesa, a reserva orçamentária e o julgamento de propostas. | CA18: 2 | CB18: 2 | CC18: 2 | CD18: 2 | CE18: 2 | CF18: 2 | CG18: 2 | CH18: Não | CI18: Não | CJ18: Não | DA18: Comparar valores e estipular um preço médio estimado entre o contrato atual vigente e pesquisas no Banco de Preços. | DC18: 2 | DD18: 2 | DE18: 2 | DF18: 2 | DG18: 2 | DH18: 2 | DI18: 2 | DJ18: Não | DK18: Não | DL18: Não | DO18: Apresentar o comparativo de preços entre o contrato atual atualizado e a média do Banco de Preços para a contratação/manutenção dos serviços. | DQ18: 2 | DR18: 2 | DS18: 2 | DT18: 2 | DU18: 2 | DV18: 2 | DW18: 2 | DX18: Não | DY18: Não | DZ18: Não
A19: 11 | B19: P16 | C19: {=IFERROR(INDEX(DOCUMENTOS!$E:$E,MATCH($A19,DOCUMENTOS!$A:$A,0)),"")} | D19: {=IFERROR(INDEX('BANCO DE PERGUNTAS'!$D:$D,MATCH($B19,'BANCO DE PERGUNTAS'!$A:$A,0)),"")} -> Qual consequência decorre da informação estabelecida em 4.11? | E19: {=IFERROR(INDEX('BANCO DE PERGUNTAS'!$B:$B,MATCH($B19,'BANCO DE PERGUNTAS'!$A:$A,0)),"")} -> Interpretação | F19: {=IFERROR(INDEX('BANCO DE PERGUNTAS'!$H:$H,MATCH($B19,'BANCO DE PERGUNTAS'!$A:$A,0)),"")} -> 3 | U19: não consta no documento. Não há seção 4.11 da qual se possa extrair uma consequência. | W19: 2 | X19: 2 | Y19: 2 | Z19: 2 | AA19: 2 | AB19: 2 | AC19: 2 | AD19: Não | AE19: Não | AF19: Não | AI19: Não consta no documento. Não há item ou seção 4.11. | AK19: 2 | AL19: 2 | AM19: 2 | AN19: 2 | AO19: 2 | AP19: 2 | AQ19: 2 | AR19: Não | AS19: Não | AT19: Não | BK19: Não consta item "4.11" no documento; não é possível identificar tal consequência. | BM19: 2 | BN19: 2 | BO19: 2 | BP19: 2 | BQ19: 2 | BR19: 2 | BS19: 2 | BT19: Não | BU19: Não | BV19: Não | BY19: Não há item 4.11 no documento, razão pela qual nenhuma consequência pode ser extraída dele. A verificação deve ser feita na peça do processo que contenha essa numeração. | CA19: 2 | CB19: 2 | CC19: 2 | CD19: 2 | CE19: 2 | CF19: 2 | CG19: 2 | CH19: Não | CI19: Não | CJ19: Não | DA19: Não há item 4.11 no documento. | DC19: 2 | DD19: 2 | DE19: 2 | DF19: 2 | DG19: 2 | DH19: 2 | DI19: 2 | DJ19: Não | DK19: Não | DL19: Não | DO19: Não consta item 4.11 no documento. | DQ19: 2 | DR19: 2 | DS19: 2 | DT19: 2 | DU19: 2 | DV19: 2 | DW19: 2 | DX19: Não | DY19: Não | DZ19: Não
A20: 11 | B20: P17 | C20: {=IFERROR(INDEX(DOCUMENTOS!$E:$E,MATCH($A20,DOCUMENTOS!$A:$A,0)),"")} | D20: {=IFERROR(INDEX('BANCO DE PERGUNTAS'!$D:$D,MATCH($B20,'BANCO DE PERGUNTAS'!$A:$A,0)),"")} -> Existem informações aparentemente inconsistentes dentro do documento? | E20: {=IFERROR(INDEX('BANCO DE PERGUNTAS'!$B:$B,MATCH($B20,'BANCO DE PERGUNTAS'!$A:$A,0)),"")} -> Identificação de Inconsistências | F20: {=IFERROR(INDEX('BANCO DE PERGUNTAS'!$H:$H,MATCH($B20,'BANCO DE PERGUNTAS'!$A:$A,0)),"")} -> 4 | U20: Sim, há diferenças aritméticas aparentes nos valores exibidos. Item 1: 434.000 × R$ 4,84 = R$ 2.100.560,00, mas o total informado é R$ 2.100.603,40, diferença de R$ 43,40. Item 2: 12 × R$ 17.763,49 = R$ 213.161,88, mas o total informado é R$ 213.161,82, diferença de R$ 0,06. Casas decimais não exibidas podem explicar as diferenças; a memória de cálculo não consta no documento. | W20: 2 | X20: 2 | Y20: 2 | Z20: 2 | AA20: 2 | AB20: 2 | AC20: 2 | AD20: Não | AE20: Não | AF20: Não | AI20: Sim. Há possíveis divergências aritméticas: R$ 4,84 × 434.000 m² = R$ 2.100.560,00, enquanto a tabela informa R$ 2.100.603,40 (diferença de R$ 43,40). Também R$ 17.763,49 × 12 = R$ 213.161,88, enquanto a tabela informa R$ 213.161,82 (diferença de R$ 0,06). A segunda diferença pode decorrer de arredondamento de valores não exibidos; ambas devem ser conferidas com os dados de cálculo originais. | AK20: 2 | AL20: 2 | AM20: 2 | AN20: 2 | AO20: 2 | AP20: 2 | AQ20: 2 | AR20: Não | AS20: Não | AT20: Não | BK20: Sim, uma pequena inconsistência de arredondamento: no Item 1, a média exibida (R$4,84) x 434.000 m² resulta em R$2.100.560,00, mas o total informado é R$2.100.603,40 (diferença de R$43,40), sugerindo que o cálculo usou um valor não arredondado (~R$4,8403) diferente do exibido. | BM20: 2 | BN20: 2 | BO20: 2 | BP20: 2 | BQ20: 2 | BR20: 2 | BS20: 2 | BT20: Não | BU20: Não | BV20: Não | BY20: Sim. (a) No item 1, 434.000 m² x R$ 4,84 = R$ 2.100.560,00, mas o total informado é R$ 2.100.603,40 - diferença de R$ 43,40, indicando que o cálculo usou valor não arredondado (R$ 4,8401), enquanto a coluna exibe R$ 4,84. (b) O processo é de 2024 e o documento é de agosto de 2026, sem esclarecimento sobre o intervalo. (c) Os três itens usam o mesmo código CATSER 25194, embora se refiram a serviço, material e equipamentos. Os itens 2 e 3 e o somatório geral estão aritmeticamente corretos. | CA20: 2 | CB20: 2 | CC20: 2 | CD20: 2 | CE20: 2 | CF20: 2 | CG20: 2 | CH20: Não | CI20: Não | CJ20: Não | DA20: Sim, o 'Termo de Apostilamento n 01/2028' faz menção ao ano de 2028, futuro em relação à data do documento (agosto de 2026). | DC20: 1 | DD20: 1 | DE20: 1 | DF20: 2 | DG20: 2 | DH20: 1 | DI20: 2 | DJ20: Sim | DK20: Sim | DL20: Sim | DM20: Erro de interpretação | DO20: Sim, há menção ao 'Termo de Apostilamento n 01/2028' em um documento datado de 2026, o que indica um provável erro material de digitação no ano. | DQ20: 1 | DR20: 1 | DS20: 1 | DT20: 2 | DU20: 2 | DV20: 1 | DW20: 2 | DX20: Sim | DY20: Sim | DZ20: Sim | EA20: Erro de interpretação
A21: 11 | B21: P18 | C21: {=IFERROR(INDEX(DOCUMENTOS!$E:$E,MATCH($A21,DOCUMENTOS!$A:$A,0)),"")} | D21: {=IFERROR(INDEX('BANCO DE PERGUNTAS'!$D:$D,MATCH($B21,'BANCO DE PERGUNTAS'!$A:$A,0)),"")} -> Existem valores, datas, números ou informações aparentemente incompatíveis? | E21: {=IFERROR(INDEX('BANCO DE PERGUNTAS'!$B:$B,MATCH($B21,'BANCO DE PERGUNTAS'!$A:$A,0)),"")} -> Identificação de Inconsistências | F21: {=IFERROR(INDEX('BANCO DE PERGUNTAS'!$H:$H,MATCH($B21,'BANCO DE PERGUNTAS'!$A:$A,0)),"")} -> 4 | U21: Os itens 1 e 2 apresentam diferenças entre quantidade × média exibida e total informado. No item 2, a média não arredondada de R$ 15.295,00 e R$ 20.231,97 é R$ 17.763,485 e, multiplicada por 12, corresponde ao total R$ 213.161,82. O item 3 confere: 12 × R$ 3.051,11 = R$ 36.613,32. A soma dos três totais informados é R$ 2.350.378,54 e coincide com o valor por extenso. Não se identificou incompatibilidade interna entre as datas apresentadas. | W21: 1 | X21: 2 | Y21: 1 | Z21: 2 | AA21: 2 | AB21: 1 | AC21: 2 | AD21: Não | AE21: Não | AF21: Sim | AG21: Confusão de valores | AI21: Há aparentes diferenças entre o preço médio vezes a quantidade e os totais dos itens 1 e 2, conforme detalhado acima. As datas visíveis (Contrato nº 113/2024, apostilamento nº 01/2026 e mapa de 24/08/2026) não são, por si só, incompatíveis. | AK21: 2 | AL21: 2 | AM21: 2 | AN21: 2 | AO21: 2 | AP21: 2 | AQ21: 2 | AR21: Não | AS21: Não | AT21: Não | BK21: A mesma discrepância do Item 1 (média x quantidade não bate exatamente com o total apresentado, diferença de R$43,40). Os demais itens e o total geral conferem matematicamente. | BM21: 2 | BN21: 2 | BO21: 2 | BP21: 2 | BQ21: 2 | BR21: 2 | BS21: 2 | BT21: Não | BU21: Não | BV21: Não | BY21: Sim. Além da diferença de R$ 43,40 no item 1, a quantidade de 434.000 m² não indica se é área mensal ou acumulada em 12 meses (434.000/12 = 36.166,67 m²/mês), o que é essencial para conferir o total. A unidade 'Meses' nos itens 2 e 3 também não deixa claro se os valores de R$ 15.295,00 e R$ 2.638,75 são mensais. | CA21: 2 | CB21: 2 | CC21: 2 | CD21: 2 | CE21: 2 | CF21: 2 | CG21: 2 | CH21: Não | CI21: Não | CJ21: Não | DA21: Sim, a data de emissão/assinatura é 2026, mas há referência a um termo de apostilamento com ano 2028. | DC21: 1 | DD21: 1 | DE21: 1 | DF21: 2 | DG21: 2 | DH21: 1 | DI21: 2 | DJ21: Sim | DK21: Sim | DL21: Sim | DM21: Erro de interpretação | DO21: Sim, o ano 2028 no termo de apostilamento em contraste com o ano de emissão 2026. | DQ21: 1 | DR21: 1 | DS21: 1 | DT21: 2 | DU21: 2 | DV21: 1 | DW21: 2 | DX21: Sim | DY21: Sim | DZ21: Sim | EA21: Erro de interpretação
A22: 11 | B22: P19 | C22: {=IFERROR(INDEX(DOCUMENTOS!$E:$E,MATCH($A22,DOCUMENTOS!$A:$A,0)),"")} | D22: {=IFERROR(INDEX('BANCO DE PERGUNTAS'!$D:$D,MATCH($B22,'BANCO DE PERGUNTAS'!$A:$A,0)),"")} -> Existem informações relevantes ausentes? | E22: {=IFERROR(INDEX('BANCO DE PERGUNTAS'!$B:$B,MATCH($B22,'BANCO DE PERGUNTAS'!$A:$A,0)),"")} -> Identificação de Omissões | F22: {=IFERROR(INDEX('BANCO DE PERGUNTAS'!$H:$H,MATCH($B22,'BANCO DE PERGUNTAS'!$A:$A,0)),"")} -> 4 | U22: Para reproduzir integralmente a estimativa, faltam a memória de cálculo com precisão completa, a composição dos 434.000 m² e sua periodicidade, o detalhamento das cotações do Banco de Preços e a composição/percentual do BDI. Detalhamento dessas informações: não consta no documento. | W22: 2 | X22: 2 | Y22: 2 | Z22: 2 | AA22: 2 | AB22: 2 | AC22: 2 | AD22: Não | AE22: Não | AF22: Não | AI22: Sim. Não aparecem os registros detalhados da pesquisa no Banco de Preços, as cotações que formaram a média, a memória de cálculo, a identificação de quem elaborou/conferiu/aprovou a planilha, nem a assinatura dos responsáveis. A planilha também não explicita se os totais foram calculados com valores unitários não arredondados. | AK22: 2 | AL22: 2 | AM22: 2 | AN22: 2 | AO22: 2 | AP22: 2 | AQ22: 2 | AR22: Não | AS22: Não | AT22: Não | BK22: Sim: vigência contratual (datas de início/fim), dados/CNPJ da empresa contratada, identificação de quem realizou a pesquisa no Banco de Preços, número do edital/licitação de origem, e assinaturas de comissão (há apenas uma assinatura digital individual). | BM22: 2 | BN22: 2 | BO22: 2 | BP22: 2 | BQ22: 2 | BR22: 2 | BS22: 2 | BT22: Não | BU22: Não | BV22: Não | BY22: Sim: data e período de coleta dos preços no Banco de Preços; identificação das contratações similares utilizadas como parâmetro; memória de cálculo do item 1; percentual e composição do BDI; número de postos, produtividade e locais de execução; justificativa da metodologia (média simples) e do uso de apenas duas fontes; cargo/função do signatário; e indicação da dotação orçamentária. | CA22: 2 | CB22: 2 | CC22: 2 | CD22: 2 | CE22: 2 | CF22: 2 | CG22: 2 | CH22: Não | CI22: Não | CJ22: Não | DA22: O documento é apenas um mapa comparativo, faltando as memórias de cálculo detalhadas do BDI e relatórios gerados pelo Banco de Preços. | DC22: 2 | DD22: 2 | DE22: 2 | DF22: 2 | DG22: 2 | DH22: 2 | DI22: 2 | DJ22: Não | DK22: Não | DL22: Não | DO22: Detalhamento completo do cálculo analítico de BDI e encargos sociais. | DQ22: 2 | DR22: 2 | DS22: 2 | DT22: 2 | DU22: 2 | DV22: 2 | DW22: 2 | DX22: Não | DY22: Não | DZ22: Não
A23: 11 | B23: P20 | C23: {=IFERROR(INDEX(DOCUMENTOS!$E:$E,MATCH($A23,DOCUMENTOS!$A:$A,0)),"")} | D23: {=IFERROR(INDEX('BANCO DE PERGUNTAS'!$D:$D,MATCH($B23,'BANCO DE PERGUNTAS'!$A:$A,0)),"")} -> Identifique possíveis erros materiais no documento. | E23: {=IFERROR(INDEX('BANCO DE PERGUNTAS'!$B:$B,MATCH($B23,'BANCO DE PERGUNTAS'!$A:$A,0)),"")} -> Detecção de Erros | F23: {=IFERROR(INDEX('BANCO DE PERGUNTAS'!$H:$H,MATCH($B23,'BANCO DE PERGUNTAS'!$A:$A,0)),"")} -> 4 | U23: Possível erro material ou efeito de precisão não exibida no total do item 1, que excede em R$ 43,40 o produto da quantidade pela média mostrada. No item 2, a diferença de R$ 0,06 é compatível com o uso da média antes do arredondamento. Não é possível confirmar erro de digitação sem a memória de cálculo. | W23: 2 | X23: 2 | Y23: 2 | Z23: 2 | AA23: 2 | AB23: 2 | AC23: 2 | AD23: Não | AE23: Não | AF23: Não | AI23: Possíveis erros materiais a conferir: total do item 1 não corresponde ao produto da quantidade pela média unitária exibida; total do item 2 difere em R$ 0,06 do produto da média mensal exibida por 12. Sem a memória de cálculo, não é possível afirmar que sejam erros definitivos. | AK23: 2 | AL23: 2 | AM23: 2 | AN23: 2 | AO23: 2 | AP23: 2 | AQ23: 2 | AR23: Não | AS23: Não | AT23: Não | BK23: Possível erro de arredondamento no total do Item 1: a média informada (R$4,84) multiplicada por 434.000 m² não reproduz exatamente o total de R$2.100.603,40 (diferença de R$43,40), indicando que o valor unitário efetivamente usado no cálculo foi diferente do arredondamento exibido. | BM23: 2 | BN23: 2 | BO23: 2 | BP23: 2 | BQ23: 2 | BR23: 2 | BS23: 2 | BT23: Não | BU23: Não | BV23: Não | BY23: (1) Divergência de R$ 43,40 entre o preço médio exibido e o total do item 1. (2) Uso do mesmo CATSER 25194 para serviço, material e equipamentos. (3) Ausência de unidade clara (mensal ou anual) para o item 1. (4) Descrição do item 3 como 'Equipamentos BDI', provavelmente 'Equipamentos + BDI', conforme o padrão do item 2. (5) Rótulos 'Preço 01' e 'Preço 02' sem identificação de data-base, o que dificulta a conferência. | CA23: 2 | CB23: 2 | CC23: 2 | CD23: 2 | CE23: 2 | CF23: 2 | CG23: 2 | CH23: Não | CI23: Não | CJ23: Não | DA23: O ano de '2028' referenciado no Termo de Apostilamento é provável erro de digitação. | DC23: 1 | DD23: 1 | DE23: 1 | DF23: 2 | DG23: 2 | DH23: 1 | DI23: 2 | DJ23: Sim | DK23: Sim | DL23: Sim | DM23: Erro de interpretação | DO23: O ano do Termo de Apostilamento citado como 2028 (provável incorreção, devendo ser 2026). | DQ23: 1 | DR23: 1 | DS23: 1 | DT23: 2 | DU23: 2 | DV23: 1 | DW23: 2 | DX23: Sim | DY23: Sim | DZ23: Sim | EA23: Erro de interpretação
A24: 11 | B24: P21 | C24: {=IFERROR(INDEX(DOCUMENTOS!$E:$E,MATCH($A24,DOCUMENTOS!$A:$A,0)),"")} | D24: {=IFERROR(INDEX('BANCO DE PERGUNTAS'!$D:$D,MATCH($B24,'BANCO DE PERGUNTAS'!$A:$A,0)),"")} -> Existem informações que deveriam ser verificadas por um servidor antes da utilização do documento? | E24: {=IFERROR(INDEX('BANCO DE PERGUNTAS'!$B:$B,MATCH($B24,'BANCO DE PERGUNTAS'!$A:$A,0)),"")} -> Análise de Risco | F24: {=IFERROR(INDEX('BANCO DE PERGUNTAS'!$H:$H,MATCH($B24,'BANCO DE PERGUNTAS'!$A:$A,0)),"")} -> 4 | U24: Sim. Conferir a precisão dos preços e os totais dos itens 1 e 2; a base e periodicidade dos 434.000 m²; as cotações que compõem o Preço 02; a atualização do contrato nº 113/2024 pelo apostilamento nº 01/2026; a composição do BDI e a autenticidade da assinatura digital. | W24: 2 | X24: 2 | Y24: 2 | Z24: 2 | AA24: 2 | AB24: 2 | AC24: 2 | AD24: Não | AE24: Não | AF24: Não | AI24: Sim. Conferir as fórmulas e valores não arredondados dos itens 1 e 2; a quantidade de 434.000 m² e sua base de cálculo; os registros da pesquisa no Banco de Preços; a atualização do Contrato nº 113/2024 pelo Termo de Apostilamento nº 01/2026; e a inclusão dos valores de materiais/equipamentos e BDI. | AK24: 2 | AL24: 2 | AM24: 2 | AN24: 2 | AO24: 2 | AP24: 2 | AQ24: 2 | AR24: Não | AS24: Não | AT24: Não | BK24: Sim: (a) a precisão do valor unitário real usado no cálculo do Item 1; (b) a data/validade da pesquisa no Banco de Preços; (c) a autenticidade da assinatura digital (verificável em validar.iti.gov.br); (d) a vigência atual do Termo de Apostilamento nº 01/2026. | BM24: 2 | BN24: 2 | BO24: 2 | BP24: 2 | BQ24: 2 | BR24: 2 | BS24: 2 | BT24: Não | BU24: Não | BV24: Não | BY24: Sim: refazer o cálculo do item 1 e registrar a memória correspondente; confirmar a vigência e os valores do Termo de Apostilamento nº 01/2026 e da CCT 2026/2027; verificar se os preços extraídos do Banco de Preços são de contratações similares e recentes (últimos 12 meses); confirmar a metragem contratada; e checar a compatibilidade do valor com a disponibilidade orçamentária. | CA24: 2 | CB24: 2 | CC24: 2 | CD24: 2 | CE24: 2 | CF24: 2 | CG24: 2 | CH24: Não | CI24: Não | CJ24: Não | DA24: O servidor deve checar a exatidão do 'Termo de Apostilamento n 01/2028' e a validade das cotações realizadas no Banco de Preços. | DC24: 1 | DD24: 1 | DE24: 1 | DF24: 2 | DG24: 2 | DH24: 1 | DI24: 2 | DJ24: Sim | DK24: Sim | DL24: Sim | DM24: Erro de interpretação | DO24: Sim, a verificação do ano correto do Termo de Apostilamento e da vigência da Convenção Coletiva de Trabalho. | DQ24: 1 | DR24: 1 | DS24: 1 | DT24: 2 | DU24: 2 | DV24: 1 | DW24: 2 | DX24: Sim | DY24: Sim | DZ24: Sim | EA24: Erro de interpretação
A25: 11 | B25: P22 | C25: {=IFERROR(INDEX(DOCUMENTOS!$E:$E,MATCH($A25,DOCUMENTOS!$A:$A,0)),"")} | D25: {=IFERROR(INDEX('BANCO DE PERGUNTAS'!$D:$D,MATCH($B25,'BANCO DE PERGUNTAS'!$A:$A,0)),"")} -> Existem elementos que indiquem possível desconformidade com os próprios requisitos apresentados no documento? | E25: {=IFERROR(INDEX('BANCO DE PERGUNTAS'!$B:$B,MATCH($B25,'BANCO DE PERGUNTAS'!$A:$A,0)),"")} -> Conformidade Documental | F25: {=IFERROR(INDEX('BANCO DE PERGUNTAS'!$H:$H,MATCH($B25,'BANCO DE PERGUNTAS'!$A:$A,0)),"")} -> 4 | U25: Há divergência aparente na relação entre quantidade, média exibida e total dos itens 1 e 2. Isso indica necessidade de conferir a precisão dos cálculos, mas não comprova descumprimento de requisito. Regras expressas de arredondamento e critérios detalhados de validação da pesquisa: não consta no documento. | W25: 1 | X25: 2 | Y25: 1 | Z25: 2 | AA25: 2 | AB25: 1 | AC25: 2 | AD25: Não | AE25: Não | AF25: Sim | AG25: Erro de interpretação | AI25: Não há desconformidade interna expressamente indicada; as divergências aritméticas aparentes devem ser verificadas antes do uso. | AK25: 1 | AL25: 2 | AM25: 1 | AN25: 2 | AO25: 2 | AP25: 1 | AQ25: 2 | AR25: Não | AS25: Não | AT25: Sim | AU25: Erro de interpretação | BK25: Não foram identificados requisitos formais explícitos no documento para comparar; não é possível apontar desconformidade além da inconsistência de arredondamento já mencionada. | BM25: 1 | BN25: 2 | BO25: 1 | BP25: 2 | BQ25: 2 | BR25: 1 | BS25: 2 | BT25: Não | BU25: Não | BV25: Sim | BW25: Erro de interpretação | BY25: Sim, em caráter de alerta: o documento afirma que a pesquisa foi 'realizada em conjunto com o Banco de Preços', mas apresenta apenas dois parâmetros (contrato vigente e média do Banco de Preços), sem os documentos comprobatórios da coleta nem justificativa para o número reduzido de fontes, o que tende a exigir complementação à luz da IN SEGES/ME nº 65/2021. Também não há análise crítica dos valores nem justificativa para a adoção da média simples em vez da mediana ou do menor preço. | CA25: 2 | CB25: 2 | CC25: 2 | CD25: 2 | CE25: 2 | CF25: 2 | CG25: 2 | CH25: Não | CI25: Não | CJ25: Não | DA25: A princípio não, à exceção do potencial erro no ano do termo de apostilamento citado. | DC25: 1 | DD25: 1 | DE25: 1 | DF25: 2 | DG25: 2 | DH25: 1 | DI25: 2 | DJ25: Não | DK25: Sim | DL25: Sim | DM25: Erro de interpretação | DO25: A divergência temporal no ano do apostilamento (2028). | DQ25: 1 | DR25: 1 | DS25: 1 | DT25: 2 | DU25: 2 | DV25: 1 | DW25: 2 | DX25: Não | DY25: Sim | DZ25: Sim | EA25: Erro de interpretação
A26: 11 | B26: P23 | C26: {=IFERROR(INDEX(DOCUMENTOS!$E:$E,MATCH($A26,DOCUMENTOS!$A:$A,0)),"")} | D26: {=IFERROR(INDEX('BANCO DE PERGUNTAS'!$D:$D,MATCH($B26,'BANCO DE PERGUNTAS'!$A:$A,0)),"")} -> Quais requisitos estão explicitamente presentes? | E26: {=IFERROR(INDEX('BANCO DE PERGUNTAS'!$B:$B,MATCH($B26,'BANCO DE PERGUNTAS'!$A:$A,0)),"")} -> Conformidade Documental | F26: {=IFERROR(INDEX('BANCO DE PERGUNTAS'!$H:$H,MATCH($B26,'BANCO DE PERGUNTAS'!$A:$A,0)),"")} -> 2 | U26: Estão explicitados: grupo 1; CATSER 25194 nos três itens; limpeza e conservação diurna, 44 horas (A), com quantidade de 434.000 m²; material sob demanda + BDI por 12 meses; equipamentos BDI por 12 meses; comparação entre contrato atualizado e Banco de Preços; apresentação de médias e totais. Não há cláusulas detalhadas de habilitação ou execução. | W26: 2 | X26: 2 | Y26: 2 | Z26: 2 | AA26: 2 | AB26: 2 | AC26: 2 | AD26: Não | AE26: Não | AF26: Não | AI26: A planilha explicita objeto, itens, unidades, quantidades, especificações, duas referências de preço, médias, totais, fontes gerais de pesquisa, processo administrativo e data. Ela não apresenta requisitos de habilitação ou regras do certame. | AK26: 2 | AL26: 2 | AM26: 2 | AN26: 2 | AO26: 2 | AP26: 2 | AQ26: 2 | AR26: Não | AS26: Não | AT26: Não | BK26: Apenas as especificações dos itens: (1) serviço de limpeza e conservação diurna 44h, 434.000 m²; (2) material sob demanda + BDI, 12 meses; (3) equipamentos BDI, 12 meses — com respectivos valores comparativos (contrato atual x pesquisa de mercado). | BM26: 2 | BN26: 2 | BO26: 2 | BP26: 2 | BQ26: 2 | BR26: 2 | BS26: 2 | BT26: Não | BU26: Não | BV26: Não | BY26: Objeto (limpeza e conservação, diurna, 44 horas, categoria A); classificação CATSER 25194; unidades (m² e Meses); quantidades (434.000 e 12 meses); estrutura em Grupo 1 com três itens; duas fontes de preço identificadas nas notas; total por extenso; local, data e assinatura digital. | CA26: 2 | CB26: 2 | CC26: 2 | CD26: 2 | CE26: 2 | CF26: 2 | CG26: 2 | CH26: Não | CI26: Não | CJ26: Não | DA26: Exigência de média de preços baseada no valor atualizado do Contrato 113/2024 e média do sistema Banco de Preços. | DC26: 2 | DD26: 2 | DE26: 2 | DF26: 2 | DG26: 2 | DH26: 2 | DI26: 2 | DJ26: Não | DK26: Não | DL26: Não | DO26: Convenção Coletiva de Trabalho 2026/2027 e parâmetros de pesquisa no Banco de Preços. | DQ26: 2 | DR26: 2 | DS26: 2 | DT26: 2 | DU26: 2 | DV26: 2 | DW26: 2 | DX26: Não | DY26: Não | DZ26: Não
A27: 11 | B27: P24 | C27: {=IFERROR(INDEX(DOCUMENTOS!$E:$E,MATCH($A27,DOCUMENTOS!$A:$A,0)),"")} | D27: {=IFERROR(INDEX('BANCO DE PERGUNTAS'!$D:$D,MATCH($B27,'BANCO DE PERGUNTAS'!$A:$A,0)),"")} -> Quais informações necessárias parecem estar ausentes? | E27: {=IFERROR(INDEX('BANCO DE PERGUNTAS'!$B:$B,MATCH($B27,'BANCO DE PERGUNTAS'!$A:$A,0)),"")} -> Identificação de Omissões | F27: {=IFERROR(INDEX('BANCO DE PERGUNTAS'!$H:$H,MATCH($B27,'BANCO DE PERGUNTAS'!$A:$A,0)),"")} -> 4 | U27: Para conferir os resultados apresentados, seriam necessárias a memória dos cálculos, as casas decimais efetivamente utilizadas, o detalhamento das cotações e os critérios de seleção da amostra, a composição do BDI e a explicação da quantidade/periodicidade do serviço. Detalhamento dessas informações: não consta no documento. | W27: 2 | X27: 2 | Y27: 2 | Z27: 2 | AA27: 2 | AB27: 2 | AC27: 2 | AD27: Não | AE27: Não | AF27: Não | AI27: Parecem ausentes a memória detalhada de cálculo, os registros/cotações que sustentam os preços do Banco de Preços, os valores não arredondados usados nas fórmulas, a identificação dos responsáveis pela elaboração e aprovação e assinaturas. | AK27: 2 | AL27: 2 | AM27: 2 | AN27: 2 | AO27: 2 | AP27: 2 | AQ27: 2 | AR27: Não | AS27: Não | AT27: Não | BK27: Vigência do contrato, dados da empresa contratada, composição/memória de cálculo detalhada do BDI, identificação da comissão responsável pela pesquisa, e o número do edital/licitação originário. | BM27: 2 | BN27: 2 | BO27: 2 | BP27: 2 | BQ27: 2 | BR27: 2 | BS27: 2 | BT27: Não | BU27: Não | BV27: Não | BY27: Locais e edificações atendidas; produtividade e número de postos por categoria; periodicidade das atividades; percentual de BDI; data-base da pesquisa; critério de julgamento (por grupo ou por item); planilha de custos e formação de preços; e fundamentação legal expressa da metodologia adotada. | CA27: 2 | CB27: 2 | CC27: 2 | CD27: 2 | CE27: 2 | CF27: 2 | CG27: 2 | CH27: Não | CI27: Não | CJ27: Não | DA27: A porcentagem das alíquotas de BDI aplicadas sobre material e equipamentos. | DC27: 1 | DD27: 1 | DE27: 1 | DF27: 2 | DG27: 2 | DH27: 1 | DI27: 2 | DJ27: Não | DK27: Sim | DL27: Sim | DM27: Erro de interpretação | DO27: Composição detalhada dos custos unitários além dos totais consolidados. | DQ27: 1 | DR27: 1 | DS27: 1 | DT27: 2 | DU27: 2 | DV27: 1 | DW27: 2 | DX27: Não | DY27: Sim | DZ27: Sim | EA27: Erro de interpretação
A28: 11 | B28: P25 | C28: {=IFERROR(INDEX(DOCUMENTOS!$E:$E,MATCH($A28,DOCUMENTOS!$A:$A,0)),"")} | D28: {=IFERROR(INDEX('BANCO DE PERGUNTAS'!$D:$D,MATCH($B28,'BANCO DE PERGUNTAS'!$A:$A,0)),"")} -> Existem informações conflitantes com outro documento relacionado? | E28: {=IFERROR(INDEX('BANCO DE PERGUNTAS'!$B:$B,MATCH($B28,'BANCO DE PERGUNTAS'!$A:$A,0)),"")} -> Comparação | F28: {=IFERROR(INDEX('BANCO DE PERGUNTAS'!$H:$H,MATCH($B28,'BANCO DE PERGUNTAS'!$A:$A,0)),"")} -> 5 | U28: não consta no documento. O mapa cita contrato nº 113/2024, Termo de Apostilamento nº 01/2026 (0616763) e Convenção Coletiva de Trabalho 2026/2027 (0602942), mas seus conteúdos integrais não estão no arquivo fornecido; não é possível verificar conflitos entre documentos. | W28: 2 | X28: 2 | Y28: 2 | Z28: 2 | AA28: 2 | AB28: 2 | AC28: 2 | AD28: Não | AE28: Não | AF28: Não | AI28: Não consta no documento uma identificação de outro documento usado para confronto. Assim, não é possível confirmar conflito documental com base apenas nesta planilha. | AK28: 2 | AL28: 2 | AM28: 2 | AN28: 2 | AO28: 2 | AP28: 2 | AQ28: 2 | AR28: Não | AS28: Não | AT28: Não | BK28: Não é possível avaliar, pois apenas este documento foi fornecido para análise; nenhum outro documento foi apresentado para comparação. | BM28: 2 | BN28: 2 | BO28: 2 | BP28: 2 | BQ28: 2 | BR28: 2 | BS28: 2 | BT28: Não | BU28: Não | BV28: Não | BY28: Não é possível afirmar: apenas este arquivo foi disponibilizado. A verificação depende do cotejo com o Contrato nº 113/2024, o Termo de Apostilamento nº 01/2026 (0616763), a CCT 2026/2027 (0602942) e o Termo de Referência do processo. | CA28: 2 | CB28: 2 | CC28: 2 | CD28: 2 | CE28: 2 | CF28: 2 | CG28: 2 | CH28: Não | CI28: Não | CJ28: Não | DA28: Impossível analisar, visto que apenas este arquivo foi fornecido. | DC28: 2 | DD28: 2 | DE28: 2 | DF28: 2 | DG28: 2 | DH28: 2 | DI28: 2 | DJ28: Não | DK28: Não | DL28: Não | DO28: Não há acesso a outros documentos, mas há inconsistência interna de ano. | DQ28: 2 | DR28: 2 | DS28: 2 | DT28: 2 | DU28: 2 | DV28: 2 | DW28: 2 | DX28: Não | DY28: Não | DZ28: Não
A29: 11 | B29: P26 | C29: {=IFERROR(INDEX(DOCUMENTOS!$E:$E,MATCH($A29,DOCUMENTOS!$A:$A,0)),"")} | D29: {=IFERROR(INDEX('BANCO DE PERGUNTAS'!$D:$D,MATCH($B29,'BANCO DE PERGUNTAS'!$A:$A,0)),"")} -> Quais diferenças existem entre os documentos? | E29: {=IFERROR(INDEX('BANCO DE PERGUNTAS'!$B:$B,MATCH($B29,'BANCO DE PERGUNTAS'!$A:$A,0)),"")} -> Comparação | F29: {=IFERROR(INDEX('BANCO DE PERGUNTAS'!$H:$H,MATCH($B29,'BANCO DE PERGUNTAS'!$A:$A,0)),"")} -> 5 | U29: não consta no documento. Foi fornecido apenas o mapa comparativo; as diferenças entre ele e os documentos relacionados não podem ser apuradas. As colunas Preço 01 e Preço 02 comparam fontes de preços, não versões de um documento. | W29: 2 | X29: 2 | Y29: 2 | Z29: 2 | AA29: 2 | AB29: 2 | AC29: 2 | AD29: Não | AE29: Não | AF29: Não | AI29: Não é possível determinar: a planilha não identifica outro documento para comparação. | AK29: 2 | AL29: 2 | AM29: 2 | AN29: 2 | AO29: 2 | AP29: 2 | AQ29: 2 | AR29: Não | AS29: Não | AT29: Não | BK29: Não aplicável — apenas um documento foi enviado, não havendo outro para comparação. | BM29: 2 | BN29: 2 | BO29: 2 | BP29: 2 | BQ29: 2 | BR29: 2 | BS29: 2 | BT29: Não | BU29: Não | BV29: Não | BY29: Não avaliável com o material disponível, pois somente esta planilha foi enviada. Recomenda-se comparar o valor unitário de R$ 4,71 com o valor efetivamente apostilado e a metragem com a prevista no contrato vigente. | CA29: 2 | CB29: 2 | CC29: 2 | CD29: 2 | CE29: 2 | CF29: 2 | CG29: 2 | CH29: Não | CI29: Não | CJ29: Não | DA29: Não aplicável, pois há apenas um documento. | DC29: 2 | DD29: 2 | DE29: 2 | DF29: 2 | DG29: 2 | DH29: 2 | DI29: 2 | DJ29: Não | DK29: Não | DL29: Não | DO29: Não aplicável (documento único analisado). | DQ29: 2 | DR29: 2 | DS29: 2 | DT29: 2 | DU29: 2 | DV29: 2 | DW29: 2 | DX29: Não | DY29: Não | DZ29: Não
A30: 11 | B30: P27 | C30: {=IFERROR(INDEX(DOCUMENTOS!$E:$E,MATCH($A30,DOCUMENTOS!$A:$A,0)),"")} | D30: {=IFERROR(INDEX('BANCO DE PERGUNTAS'!$D:$D,MATCH($B30,'BANCO DE PERGUNTAS'!$A:$A,0)),"")} -> Quais informações foram alteradas? | E30: {=IFERROR(INDEX('BANCO DE PERGUNTAS'!$B:$B,MATCH($B30,'BANCO DE PERGUNTAS'!$A:$A,0)),"")} -> Análise de Relações entre Informações | F30: {=IFERROR(INDEX('BANCO DE PERGUNTAS'!$H:$H,MATCH($B30,'BANCO DE PERGUNTAS'!$A:$A,0)),"")} -> 5 | U30: O mapa informa que o valor do contrato nº 113/2024 foi atualizado pelo Termo de Apostilamento nº 01/2026 (0616763), em razão de reajustes dos itens envolvendo a folha de salários, com base na Convenção Coletiva de Trabalho 2026/2027 (0602942). Detalhamento dos valores anteriores e das alterações: não consta no documento. | W30: 2 | X30: 2 | Y30: 2 | Z30: 2 | AA30: 2 | AB30: 2 | AC30: 2 | AD30: Não | AE30: Não | AF30: Não | AI30: Não é possível determinar sem um documento anterior ou de referência e seu histórico de versões. | AK30: 2 | AL30: 2 | AM30: 2 | AN30: 2 | AO30: 2 | AP30: 2 | AQ30: 2 | AR30: Não | AS30: Não | AT30: Não | BK30: Não é possível determinar sem uma versão anterior para comparação. O próprio documento menciona que o valor do contrato foi atualizado pelo Termo de Apostilamento nº 01/2026, em razão de reajustes da folha salarial conforme a Convenção Coletiva 2026/2027, mas a versão anterior não foi fornecida. | BM30: 2 | BN30: 2 | BO30: 2 | BP30: 2 | BQ30: 2 | BR30: 2 | BS30: 2 | BT30: Não | BU30: Não | BV30: Não | BY30: O documento registra que o valor do Contrato nº 113/2024 foi atualizado por meio do Termo de Apostilamento nº 01/2026, em razão de reajustes de itens da folha de salários com base na CCT 2026/2027. Os valores anteriores ao reajuste não são apresentados, o que impede identificar a variação. | CA30: 2 | CB30: 2 | CC30: 2 | CD30: 2 | CE30: 2 | CF30: 2 | CG30: 2 | CH30: Não | CI30: Não | CJ30: Não | DA30: O Preço 01 foi atualizado por termo de apostilamento, em virtude do reajuste da folha salarial pela Convenção Coletiva de Trabalho (CCT) 2026/2027. | DC30: 1 | DD30: 1 | DE30: 1 | DF30: 2 | DG30: 2 | DH30: 1 | DI30: 2 | DJ30: Não | DK30: Sim | DL30: Sim | DM30: Erro de interpretação | DO30: Valores atualizados do contrato decorrentes do Termo de Apostilamento e reajustes da folha de salários. | DQ30: 1 | DR30: 1 | DS30: 1 | DT30: 2 | DU30: 2 | DV30: 1 | DW30: 2 | DX30: Não | DY30: Sim | DZ30: Sim | EA30: Erro de interpretação
A31: 11 | B31: P28 | C31: {=IFERROR(INDEX(DOCUMENTOS!$E:$E,MATCH($A31,DOCUMENTOS!$A:$A,0)),"")} | D31: {=IFERROR(INDEX('BANCO DE PERGUNTAS'!$D:$D,MATCH($B31,'BANCO DE PERGUNTAS'!$A:$A,0)),"")} -> Identifique possíveis pontos de atenção administrativa. | E31: {=IFERROR(INDEX('BANCO DE PERGUNTAS'!$B:$B,MATCH($B31,'BANCO DE PERGUNTAS'!$A:$A,0)),"")} -> Análise de Risco | F31: {=IFERROR(INDEX('BANCO DE PERGUNTAS'!$H:$H,MATCH($B31,'BANCO DE PERGUNTAS'!$A:$A,0)),"")} -> 4 | U31: Pontos de atenção derivados da leitura: diferenças entre médias exibidas e totais dos itens 1 e 2; ausência de memória de cálculo; falta de explicação da periodicidade dos 434.000 m²; composição das cotações do Banco de Preços e do BDI não detalhada; necessidade de conferir os documentos citados e a assinatura. | W31: 2 | X31: 2 | Y31: 2 | Z31: 2 | AA31: 2 | AB31: 2 | AC31: 2 | AD31: Não | AE31: Não | AF31: Não | AI31: Pontos de atenção: validar os totais dos itens 1 e 2; confirmar quantitativos, período de 12 meses e inclusão do BDI; guardar evidências da pesquisa no Banco de Preços; conferir a atualização do contrato usado como referência; e obter registro de elaboração/conferência/aprovação. | AK31: 2 | AL31: 2 | AM31: 2 | AN31: 2 | AO31: 2 | AP31: 2 | AQ31: 2 | AR31: Não | AS31: Não | AT31: Não | BK31: (1) Discrepância de arredondamento no total do Item 1; (2) ausência de dados de vigência contratual; (3) fundamentação do reajuste baseada em convenção coletiva 2026/2027 vigente a partir de data futura/próxima, cuja aplicabilidade deve ser confirmada; (4) ausência de identificação de comissão responsável. | BM31: 2 | BN31: 2 | BO31: 2 | BP31: 2 | BQ31: 2 | BR31: 2 | BS31: 2 | BT31: Não | BU31: Não | BV31: Não | BY31: Pesquisa apoiada em apenas duas fontes; média simples que eleva a estimativa acima do preço do contrato vigente (R$ 4,84 contra R$ 4,71); divergência de R$ 43,40 no item 1; ausência de memória de cálculo e de data da coleta; assinatura única, sem manifestação de equipe de planejamento; intervalo entre a autuação do processo (2024) e a data da planilha (2026); e ausência de definição sobre o caráter mensal ou anual das quantidades. | CA31: 2 | CB31: 2 | CC31: 2 | CD31: 2 | CE31: 2 | CF31: 2 | CG31: 2 | CH31: Não | CI31: Não | CJ31: Não | DA31: A divergência de preço entre o contrato atual e o Banco de Preços (especialmente para os materiais) e o erro na data do apostilamento. | DC31: 2 | DD31: 2 | DE31: 2 | DF31: 2 | DG31: 2 | DH31: 2 | DI31: 2 | DJ31: Não | DK31: Não | DL31: Não | DO31: Checagem rigorosa da data/ano do Termo de Apostilamento e conformidade com a Convenção Coletiva 2026/2027. | DQ31: 1 | DR31: 1 | DS31: 1 | DT31: 2 | DU31: 2 | DV31: 1 | DW31: 2 | DX31: Não | DY31: Sim | DZ31: Sim | EA31: Erro de interpretação
A32: 11 | B32: P29 | C32: {=IFERROR(INDEX(DOCUMENTOS!$E:$E,MATCH($A32,DOCUMENTOS!$A:$A,0)),"")} | D32: {=IFERROR(INDEX('BANCO DE PERGUNTAS'!$D:$D,MATCH($B32,'BANCO DE PERGUNTAS'!$A:$A,0)),"")} -> Quais informações deveriam ser verificadas antes de uma decisão administrativa? | E32: {=IFERROR(INDEX('BANCO DE PERGUNTAS'!$B:$B,MATCH($B32,'BANCO DE PERGUNTAS'!$A:$A,0)),"")} -> Análise de Risco | F32: {=IFERROR(INDEX('BANCO DE PERGUNTAS'!$H:$H,MATCH($B32,'BANCO DE PERGUNTAS'!$A:$A,0)),"")} -> 4 | U32: Conferir os cálculos e o critério de arredondamento; confirmar a quantidade e o período abrangido pelo serviço; verificar a comparabilidade dos preços do contrato atualizado e da pesquisa; conferir o apostilamento e a convenção coletiva citados; verificar a composição do BDI e a autenticidade/autoria da assinatura. | W32: 2 | X32: 2 | Y32: 2 | Z32: 2 | AA32: 2 | AB32: 2 | AC32: 2 | AD32: Não | AE32: Não | AF32: Não | AI32: Antes da decisão, verificar a memória de cálculo e as divergências de R$ 43,40 e R$ 0,06; a documentação da pesquisa de mercado; a validade e comparabilidade do Contrato nº 113/2024 atualizado; e a coerência dos quantitativos e do prazo de 12 meses. | AK32: 2 | AL32: 2 | AM32: 2 | AN32: 2 | AO32: 2 | AP32: 2 | AQ32: 2 | AR32: Não | AS32: Não | AT32: Não | BK32: A exatidão do cálculo do Item 1, a atualidade e metodologia da pesquisa no Banco de Preços, a validade jurídica do Termo de Apostilamento nº 01/2026 e a autenticidade da assinatura digital do documento. | BM32: 2 | BN32: 2 | BO32: 2 | BP32: 2 | BQ32: 2 | BR32: 2 | BS32: 2 | BT32: Não | BU32: Não | BV32: Não | BY32: Exatidão dos cálculos e da metragem; atualidade e similaridade dos preços do Banco de Preços; conformidade da metodologia com a IN SEGES/ME nº 65/2021; compatibilidade com os valores apostilados e com a CCT vigente; existência de dotação orçamentária suficiente; e juntada dos comprovantes da pesquisa aos autos. | CA32: 2 | CB32: 2 | CC32: 2 | CD32: 2 | CE32: 2 | CF32: 2 | CG32: 2 | CH32: Não | CI32: Não | CJ32: Não | DA32: Os comprovantes originais da pesquisa no Banco de Preços, a correta aplicação da Convenção Coletiva 2026/2027 e a data do Termo de Apostilamento. | DC32: 2 | DD32: 2 | DE32: 2 | DF32: 2 | DG32: 2 | DH32: 2 | DI32: 2 | DJ32: Não | DK32: Não | DL32: Não | DO32: Validade jurídica do termo de apostilamento e exatidão dos valores reajustados. | DQ32: 2 | DR32: 2 | DS32: 2 | DT32: 2 | DU32: 2 | DV32: 2 | DW32: 2 | DX32: Não | DY32: Não | DZ32: Não
A33: 11 | B33: P30 | C33: {=IFERROR(INDEX(DOCUMENTOS!$E:$E,MATCH($A33,DOCUMENTOS!$A:$A,0)),"")} | D33: {=IFERROR(INDEX('BANCO DE PERGUNTAS'!$D:$D,MATCH($B33,'BANCO DE PERGUNTAS'!$A:$A,0)),"")} -> Identifique situações que possam representar risco administrativo. | E33: {=IFERROR(INDEX('BANCO DE PERGUNTAS'!$B:$B,MATCH($B33,'BANCO DE PERGUNTAS'!$A:$A,0)),"")} -> Análise de Risco | F33: {=IFERROR(INDEX('BANCO DE PERGUNTAS'!$H:$H,MATCH($B33,'BANCO DE PERGUNTAS'!$A:$A,0)),"")} -> 4 | U33: Riscos potenciais inferidos do mapa: adotar estimativa sem reproduzir seus cálculos; interpretar incorretamente a quantidade ou a periodicidade do serviço; comparar preços com escopos ou composições diferentes sem detalhamento suficiente; utilizar atualização contratual ou BDI sem conferir sua composição. O documento isolado não comprova dano ou irregularidade. | W33: 2 | X33: 2 | Y33: 2 | Z33: 2 | AA33: 2 | AB33: 2 | AC33: 2 | AD33: Não | AE33: Não | AF33: Não | AI33: Há risco de estimativa incorreta do valor da contratação se as divergências aritméticas ou os dados de pesquisa estiverem errados; risco de baixa rastreabilidade se as cotações e memórias de cálculo não estiverem juntadas; e risco de aprovação sem validação formal dos responsáveis. | AK33: 2 | AL33: 2 | AM33: 2 | AN33: 2 | AO33: 2 | AP33: 2 | AQ33: 2 | AR33: Não | AS33: Não | AT33: Não | BK33: Uso de fonte única (Banco de Preços) para a pesquisa de mercado, sem outras cotações comparativas; discrepância de arredondamento no valor total do Item 1; ausência de documentação de comissão formal na assinatura do mapa comparativo. | BM33: 2 | BN33: 2 | BO33: 2 | BP33: 2 | BQ33: 2 | BR33: 2 | BS33: 2 | BT33: Não | BU33: Não | BV33: Não | BY33: Risco de superestimativa da despesa, uma vez que a média eleva o valor acima do contrato em execução; risco de impugnação ou de apontamento em auditoria pela fragilidade da cesta de preços (duas fontes, sem comprovantes); risco de erro material replicado ao edital em razão da divergência do item 1; risco de defasagem dos preços se a coleta for antiga; e risco de responsabilização por ausência de análise crítica formalizada. | CA33: 2 | CB33: 2 | CC33: 2 | CD33: 2 | CE33: 2 | CF33: 2 | CG33: 2 | CH33: Não | CI33: Não | CJ33: Não | DA33: Aprovação do termo com erros materiais em referência legal (Apostilamento 2028) ou aprovação sem a devida juntada dos relatórios do Banco de Preços ao processo. | DC33: 2 | DD33: 2 | DE33: 2 | DF33: 2 | DG33: 2 | DH33: 2 | DI33: 2 | DJ33: Não | DK33: Não | DL33: Não | DO33: Inconsistências de datas (ano 2028) que possam gerar questionamentos em auditorias ou órgãos de controle. | DQ33: 1 | DR33: 1 | DS33: 1 | DT33: 2 | DU33: 2 | DV33: 1 | DW33: 2 | DX33: Não | DY33: Sim | DZ33: Sim | EA33: Erro de interpretação
A34: 11 | B34: P31 | C34: {=IFERROR(INDEX(DOCUMENTOS!$E:$E,MATCH($A34,DOCUMENTOS!$A:$A,0)),"")} | D34: {=IFERROR(INDEX('BANCO DE PERGUNTAS'!$D:$D,MATCH($B34,'BANCO DE PERGUNTAS'!$A:$A,0)),"")} -> Resuma o documento em até cinco pontos objetivos. | E34: {=IFERROR(INDEX('BANCO DE PERGUNTAS'!$B:$B,MATCH($B34,'BANCO DE PERGUNTAS'!$A:$A,0)),"")} -> Síntese | F34: {=IFERROR(INDEX('BANCO DE PERGUNTAS'!$H:$H,MATCH($B34,'BANCO DE PERGUNTAS'!$A:$A,0)),"")} -> 3 | U34: 1) Mapa comparativo de preços da PROAD/UFJ, datado de 24/08/2026, processo 23854.007448/2024-94; 2) Abrange limpeza e conservação diurna, 44 horas, materiais sob demanda e equipamentos; 3) Compara contrato nº 113/2024 atualizado e pesquisa no Banco de Preços; 4) Apresenta total de R$ 2.350.378,54; 5) As médias exibidas e os totais dos itens 1 e 2 exigem conferência da precisão dos cálculos. | W34: 2 | X34: 2 | Y34: 2 | Z34: 2 | AA34: 2 | AB34: 2 | AC34: 2 | AD34: Não | AE34: Não | AF34: Não | AI34: 1. O documento é um mapa comparativo para serviço de limpeza e conservação da UFJ. 2. O processo indicado é 23854.007448/2024-94. 3. A estimativa total para 12 meses é R$ 2.350.378,54. 4. As referências são o Contrato nº 113/2024 atualizado e pesquisa no Banco de Preços. 5. Os totais dos itens 1 e 2 devem ser conferidos, pois não coincidem exatamente com preços médios e quantidades exibidos. | AK34: 2 | AL34: 2 | AM34: 2 | AN34: 2 | AO34: 2 | AP34: 2 | AQ34: 2 | AR34: Não | AS34: Não | AT34: Não | BK34: 1) Mapa comparativo de preços do Processo SEI 23854.007448/2024-94 (UFJ/PROAD). 2) Compara o valor atualizado do Contrato 113/2024 com a média de mercado do Banco de Preços. 3) Objeto: limpeza/conservação (434.000 m²), material sob demanda e equipamentos, todos com BDI. 4) Valor total anual: R$2.350.378,54. 5) Documento datado de 24/08/2026 e assinado digitalmente por Marcos Paulo Pereira Fagundes. | BM34: 2 | BN34: 2 | BO34: 2 | BP34: 2 | BQ34: 2 | BR34: 2 | BS34: 2 | BT34: Não | BU34: Não | BV34: Não | BY34: 1) Mapa comparativo de preços da UFJ/PROAD, processo SEI 23854.007448/2024-94, datado de 24/08/2026. 2) Estima a contratação de limpeza e conservação diurna (44h, categoria A), com material sob demanda e equipamentos, ambos acrescidos de BDI. 3) Compara duas fontes: o contrato 113/2024 atualizado por apostilamento e a média do Banco de Preços. 4) Adota a média aritmética entre elas, chegando a R$ 2.350.378,54. 5) Não apresenta memória de cálculo, data da coleta nem justificativa metodológica, e contém pequena divergência de arredondamento no item 1. | CA34: 2 | CB34: 2 | CC34: 2 | CD34: 2 | CE34: 2 | CF34: 2 | CG34: 2 | CH34: Não | CI34: Não | CJ34: Não | DA34: 1) Mapa Comparativo de Preços. 2) Serviço de Limpeza (UFJ). 3) Compara Contrato 113/2024 x Banco de Preços. 4) Processo: 23854.007448/2024-94. 5) Valor total estimado: R$ 2.350.378,54. | DC34: 2 | DD34: 2 | DE34: 2 | DF34: 2 | DG34: 2 | DH34: 2 | DI34: 2 | DJ34: Não | DK34: Não | DL34: Não | DO34: 1. Mapa comparativo de preços da UFJ; 2. Abrange limpeza diurna 44h, materiais e equipamentos; 3. Valor total anual de R$ 2.350.378,54; 4. Compara contrato atual com média do Banco de Preços; 5. Assinado em 24/08/2026 por Marcos Paulo Pereira Fagundes. | DQ34: 2 | DR34: 2 | DS34: 2 | DT34: 2 | DU34: 2 | DV34: 2 | DW34: 2 | DX34: Não | DY34: Não | DZ34: Não
A35: 11 | B35: P32 | C35: {=IFERROR(INDEX(DOCUMENTOS!$E:$E,MATCH($A35,DOCUMENTOS!$A:$A,0)),"")} | D35: {=IFERROR(INDEX('BANCO DE PERGUNTAS'!$D:$D,MATCH($B35,'BANCO DE PERGUNTAS'!$A:$A,0)),"")} -> Qual é a principal finalidade do documento? | E35: {=IFERROR(INDEX('BANCO DE PERGUNTAS'!$B:$B,MATCH($B35,'BANCO DE PERGUNTAS'!$A:$A,0)),"")} -> Síntese | F35: {=IFERROR(INDEX('BANCO DE PERGUNTAS'!$H:$H,MATCH($B35,'BANCO DE PERGUNTAS'!$A:$A,0)),"")} -> 2 | U35: Apresentar comparação de preços e estimativa de custo para os serviços de limpeza e conservação e seus componentes na UFJ, subsidiando a instrução do processo administrativo. | W35: 2 | X35: 2 | Y35: 2 | Z35: 2 | AA35: 2 | AB35: 2 | AC35: 2 | AD35: Não | AE35: Não | AF35: Não | AI35: A principal finalidade é comparar referências de preços e apoiar a estimativa da contratação de limpeza e conservação. | AK35: 2 | AL35: 2 | AM35: 2 | AN35: 2 | AO35: 2 | AP35: 2 | AQ35: 2 | AR35: Não | AS35: Não | AT35: Não | BK35: Demonstrar, de forma comparativa, que o valor atualizado do contrato vigente está compatível com a média de preços praticados no mercado, subsidiando a decisão administrativa sobre o reajuste/repactuação contratual. | BM35: 2 | BN35: 2 | BO35: 2 | BP35: 2 | BQ35: 2 | BR35: 2 | BS35: 2 | BT35: Não | BU35: Não | BV35: Não | BY35: Fixar e documentar a estimativa do valor da contratação de serviços de limpeza e conservação, servindo de base para a instrução do processo, a autorização da despesa e a futura análise de propostas. | CA35: 2 | CB35: 2 | CC35: 2 | CD35: 2 | CE35: 2 | CF35: 2 | CG35: 2 | CH35: Não | CI35: Não | CJ35: Não | DA35: Apurar a estimativa de custos para a contratação, demonstrando a média entre os valores contratados e a cotação de mercado. | DC35: 2 | DD35: 2 | DE35: 2 | DF35: 2 | DG35: 2 | DH35: 2 | DI35: 2 | DJ35: Não | DK35: Não | DL35: Não | DO35: Subsidiariar a administração da UFJ com o comparativo de preços de mercado e contratuais para serviços de limpeza e conservação. | DQ35: 2 | DR35: 2 | DS35: 2 | DT35: 2 | DU35: 2 | DV35: 2 | DW35: 2 | DX35: Não | DY35: Não | DZ35: Não
A36: 11 | B36: P33 | C36: {=IFERROR(INDEX(DOCUMENTOS!$E:$E,MATCH($A36,DOCUMENTOS!$A:$A,0)),"")} | D36: {=IFERROR(INDEX('BANCO DE PERGUNTAS'!$D:$D,MATCH($B36,'BANCO DE PERGUNTAS'!$A:$A,0)),"")} -> Quais são as três informações mais importantes para um servidor responsável pela análise? | E36: {=IFERROR(INDEX('BANCO DE PERGUNTAS'!$B:$B,MATCH($B36,'BANCO DE PERGUNTAS'!$A:$A,0)),"")} -> Síntese | F36: {=IFERROR(INDEX('BANCO DE PERGUNTAS'!$H:$H,MATCH($B36,'BANCO DE PERGUNTAS'!$A:$A,0)),"")} -> 3 | U36: 1) Vinculação ao processo 23854.007448/2024-94 e objeto composto por limpeza/conservação, materiais e equipamentos; 2) Total informado de R$ 2.350.378,54, com diferenças aparentes nos cálculos dos itens 1 e 2 a conferir; 3) Fontes: contrato nº 113/2024 atualizado pelo apostilamento nº 01/2026 e Banco de Preços, com referência à Convenção Coletiva 2026/2027. | W36: 2 | X36: 2 | Y36: 2 | Z36: 2 | AA36: 2 | AB36: 2 | AC36: 2 | AD36: Não | AE36: Não | AF36: Não | AI36: As três informações prioritárias são: o valor estimado de R$ 2.350.378,54 para 12 meses; a base das duas referências de preço (contrato atualizado e Banco de Preços); e as divergências aritméticas aparentes nos totais dos itens 1 e 2, que precisam de conferência. | AK36: 2 | AL36: 2 | AM36: 2 | AN36: 2 | AO36: 2 | AP36: 2 | AQ36: 2 | AR36: Não | AS36: Não | AT36: Não | BK36: 1) O valor total anual do objeto: R$2.350.378,54. 2) A comparação entre o preço contratual atualizado (Preço 01) e a média de mercado (Preço 02), que baliza a razoabilidade do valor. 3) O fundamento do reajuste: Termo de Apostilamento nº 01/2026, motivado pela Convenção Coletiva de Trabalho 2026/2027. | BM36: 2 | BN36: 2 | BO36: 2 | BP36: 2 | BQ36: 2 | BR36: 2 | BS36: 2 | BT36: Não | BU36: Não | BV36: Não | BY36: 1) O valor estimado total de R$ 2.350.378,54, calculado pela média entre o contrato vigente e a média do Banco de Preços. 2) A metodologia utilizada apoia-se em apenas duas fontes, sem comprovantes, data de coleta ou análise crítica, o que exige complementação. 3) Há divergência de R$ 43,40 no total do item 1 em relação ao preço médio exibido, além da indefinição sobre o caráter mensal ou anual dos 434.000 m². | CA36: 2 | CB36: 2 | CC36: 2 | CD36: 2 | CE36: 2 | CF36: 2 | CG36: 2 | CH36: Não | CI36: Não | CJ36: Não | DA36: 1) Valor Total do Objeto (R$ 2.350.378,54); 2) As fontes de composição da média (Contrato atual vs Banco de Preços); 3) Número do processo (23854.007448/2024-94). | DC36: 1 | DD36: 1 | DE36: 1 | DF36: 2 | DG36: 2 | DH36: 1 | DI36: 2 | DJ36: Não | DK36: Sim | DL36: Sim | DM36: Erro de interpretação | DO36: 1. Valor Total Anual (R$ 2.350.378,54); 2. Objeto e quantitativos dos serviços; 3. Ponto de atenção sobre o erro material no ano do Termo de Apostilamento (2028). | DQ36: 1 | DR36: 1 | DS36: 1 | DT36: 2 | DU36: 2 | DV36: 1 | DW36: 2 | DX36: Não | DY36: Sim | DZ36: Sim | EA36: Erro de interpretação
A37: 12 | B37: P01 | C37: {=IFERROR(INDEX(DOCUMENTOS!$E:$E,MATCH($A37,DOCUMENTOS!$A:$A,0)),"")} | D37: {=IFERROR(INDEX('BANCO DE PERGUNTAS'!$D:$D,MATCH($B37,'BANCO DE PERGUNTAS'!$A:$A,0)),"")} -> Qual é o objeto principal deste documento? | E37: {=IFERROR(INDEX('BANCO DE PERGUNTAS'!$B:$B,MATCH($B37,'BANCO DE PERGUNTAS'!$A:$A,0)),"")} -> Identificação | F37: {=IFERROR(INDEX('BANCO DE PERGUNTAS'!$H:$H,MATCH($B37,'BANCO DE PERGUNTAS'!$A:$A,0)),"")} -> 1 | U37: Pesquisar preços para a contratação de empresa remanescente especializada em serviços continuados de limpeza, conservação e asseio da Universidade Federal de Jataí, com mão de obra, insumos, máquinas e equipamentos. A cotação abrange serviços de limpeza, material sob demanda + BDI e equipamentos BDI. (PDF, pp. 1 e 3.) | W37: 2 | X37: 2 | Y37: 2 | Z37: 2 | AA37: 2 | AB37: 2 | AC37: 2 | AD37: Não | AE37: Não | AF37: Não | AI37: Relatório de pesquisa de preços para estimar valores de referência de três itens ligados à limpeza e conservação: serviço de limpeza, materiais sob demanda + BDI e equipamentos + BDI. | AK37: 2 | AL37: 2 | AM37: 2 | AN37: 2 | AO37: 2 | AP37: 2 | AQ37: 2 | AR37: Não | AS37: Não | AT37: Não | BK37: Relatório de Pesquisa de Preço (cotação de mercado) elaborado pela Diretoria de Compras e Licitações da Universidade Federal de Jataí (UFJ), identificado internamente no sistema como "EMPRESA PRISMA 2026". Abrange 3 itens: 1) Prestação de Serviço de limpeza e conservação; 2) Material Sob Demanda + BDI; 3) Equipamentos BDI. Elaborado em conformidade com a IN SEGES/ME nº 65/2021 (Lei nº 14.133/2021), método da Média Aritmética dos preços obtidos. | BM37: 2 | BN37: 2 | BO37: 2 | BP37: 2 | BQ37: 2 | BR37: 2 | BS37: 2 | BT37: Não | BU37: Não | BV37: Não | BY37: Relatório de Pesquisa de Preço extraído da ferramenta Banco de Preços, sob o título de cotação "EMPRESA PRISMA 2026", destinado a formar o preço estimado da contratação de empresa remanescente para prestação de serviços continuados de limpeza, conservação e asseio na Universidade Federal de Jataí (UFJ), com fornecimento de mão de obra, insumos, máquinas e equipamentos. A cotação abrange 3 itens: (1) Prestação de serviço de limpeza e conservação (m²); (2) Material sob demanda + BDI; (3) Equipamentos + BDI. | CA37: 2 | CB37: 2 | CC37: 2 | CD37: 2 | CE37: 2 | CF37: 2 | CG37: 2 | CH37: Não | CI37: Não | CJ37: Não | DA37: Trata-se de um Relatório de Pesquisa/Cotação de Preço para a contratação de empresa especializada na prestação de serviços continuados de limpeza, conservação e asseio, incluindo fornecimento de material sob demanda e equipamentos. | DC37: 2 | DD37: 2 | DE37: 2 | DF37: 2 | DG37: 2 | DH37: 2 | DI37: 2 | DJ37: Não | DK37: Não | DL37: Não | DO37: Relatório de Pesquisa de Preços com base na Instrução Normativa nº 65/2021 (Lei nº 14.133/2021) para contratação de serviços de limpeza, conservação e fornecimento de materiais e equipamentos. | DQ37: 2 | DR37: 2 | DS37: 2 | DT37: 2 | DU37: 2 | DV37: 2 | DW37: 2 | DX37: Não | DY37: Não | DZ37: Não
A38: 12 | B38: P02 | C38: {=IFERROR(INDEX(DOCUMENTOS!$E:$E,MATCH($A38,DOCUMENTOS!$A:$A,0)),"")} | D38: {=IFERROR(INDEX('BANCO DE PERGUNTAS'!$D:$D,MATCH($B38,'BANCO DE PERGUNTAS'!$A:$A,0)),"")} -> Qual é o número ou identificação do documento? | E38: {=IFERROR(INDEX('BANCO DE PERGUNTAS'!$B:$B,MATCH($B38,'BANCO DE PERGUNTAS'!$A:$A,0)),"")} -> Identificação | F38: {=IFERROR(INDEX('BANCO DE PERGUNTAS'!$H:$H,MATCH($B38,'BANCO DE PERGUNTAS'!$A:$A,0)),"")} -> 1 | U38: Relatório Resumido de Cotação e Relatório de Cotação: EMPRESA PRISMA 2026. A identificação 0631080 consta no nome do arquivo fornecido; no corpo, há códigos de validação dos relatórios, sem número administrativo próprio explicitado. (PDF, pp. 1–2.) | W38: 2 | X38: 2 | Y38: 2 | Z38: 2 | AA38: 2 | AB38: 2 | AC38: 2 | AD38: Não | AE38: Não | AF38: Não | AI38: Relatório de Cotação “EMPRESA PRISMA 2026”; o arquivo não informa número SEI ou outro número formal do relatório. | AK38: 2 | AL38: 2 | AM38: 2 | AN38: 2 | AO38: 2 | AP38: 2 | AQ38: 2 | AR38: Não | AS38: Não | AT38: Não | BK38: O documento não traz um número de identificação/protocolo formal (tipo SEI) em seu conteúdo. Cada página exibe apenas um "Código Validação" (hash), diferente entre o relatório resumido e o relatório detalhado, usado só para autenticação online — não é um número de documento administrativo. (Obs.: o nome do arquivo enviado contém "0631080", possível nº de protocolo/SEI, mas esse número não aparece no corpo do PDF.) | BM38: 1 | BN38: 2 | BO38: 1 | BP38: 2 | BQ38: 2 | BR38: 1 | BS38: 2 | BT38: Não | BU38: Não | BV38: Sim | BW38: Omissão | BY38: O relatório não possui número próprio impresso no corpo do texto. A identificação disponível é: (a) o número do documento SEI constante do nome do arquivo — 0631080; (b) os Códigos de Validação/token do Banco de Preços, que são distintos para cada relatório: relatório resumido = abrUypjvPRgclBvPbBa6v6YDcE8oOpWgE2HfKlRB3IAqHU8nPtm6WA%3d%3d; relatório detalhado = abrUypjvPRgclBvPbBa6v6YDcE8oOpWgsBHzEjXJCXcqHU8nPtm6WA%3d%3d, ambos verificáveis em bancodeprecos.com.br/CertificadoAutenticidade. | CA38: 0 | CB38: 2 | CC38: 1 | CD38: 2 | CE38: 2 | CF38: 1 | CG38: 1 | CH38: Não | CI38: Sim | CJ38: Sim | CK38: Omissão | DA38: Relatório Pesquisa de Preço - Banco de Preços (0631080).pdf, com códigos de validação de autenticidade (ex: abrUypjvPRgclBvPbBa6v6YDcE8oOpWg...). | DC38: 2 | DD38: 2 | DE38: 1 | DF38: 2 | DG38: 2 | DH38: 2 | DI38: 2 | DJ38: Não | DK38: Não | DL38: Não | DO38: Relatório Resumido de Cotação: EMPRESA PRISMA 2026 / ID de Validação: abrUypjvPRgclBvPbBa6v6YDcE8oOpWgE2HfKIRB31AqHU8nPtm6WA%3d%3d | DQ38: 2 | DR38: 2 | DS38: 2 | DT38: 2 | DU38: 2 | DV38: 2 | DW38: 2 | DX38: Não | DY38: Não | DZ38: Não
A39: 12 | B39: P03 | C39: {=IFERROR(INDEX(DOCUMENTOS!$E:$E,MATCH($A39,DOCUMENTOS!$A:$A,0)),"")} | D39: {=IFERROR(INDEX('BANCO DE PERGUNTAS'!$D:$D,MATCH($B39,'BANCO DE PERGUNTAS'!$A:$A,0)),"")} -> Qual é o número do processo relacionado? | E39: {=IFERROR(INDEX('BANCO DE PERGUNTAS'!$B:$B,MATCH($B39,'BANCO DE PERGUNTAS'!$A:$A,0)),"")} -> Identificação | F39: {=IFERROR(INDEX('BANCO DE PERGUNTAS'!$H:$H,MATCH($B39,'BANCO DE PERGUNTAS'!$A:$A,0)),"")} -> 1 | U39: O número do processo da contratação da UFJ não consta no documento. Os anexos mencionam processos das contratações usadas como referência: 05800032468202617 (Pregão 90006/2026), 25115000123202541 (Pregão 90009/2026) e 642580043212025 (Pregão 90001/2026). Esses números não identificam o processo da UFJ. | W39: 2 | X39: 2 | Y39: 2 | Z39: 2 | AA39: 2 | AB39: 2 | AC39: 2 | AD39: Não | AE39: Não | AF39: Não | AI39: Não consta no relatório. O mapa comparativo relacionado identifica o processo SEI nº 23854.007448/2024-94. | AK39: 2 | AL39: 2 | AM39: 2 | AN39: 2 | AO39: 2 | AP39: 2 | AQ39: 2 | AR39: Não | AS39: Não | AT39: Não | BK39: Não consta, no corpo do relatório, um número de processo administrativo da UFJ vinculado a esta pesquisa. Os números de processo/pregão que aparecem (ex.: Processo nº 05800032468202617, nº 25115000123202541, nº 642580043212025) pertencem a OUTROS órgãos e são apenas as fontes de preço utilizadas como referência — não o processo da UFJ. | BM39: 2 | BN39: 2 | BO39: 2 | BP39: 2 | BQ39: 2 | BR39: 2 | BS39: 2 | BT39: Não | BU39: Não | BV39: Não | BY39: NÃO CONSTA. O relatório não indica o número do processo administrativo da UFJ. Os únicos números de processo citados são os das licitações utilizadas como fonte de preço, pertencentes a outros órgãos: Processo nº 05800032468202617 (Pregão 90006/2026 – SSP/SP, Delegacia Seccional de Marília); Processo nº 25115000123202541 (Pregão 90009/2026 – Funasa/MS); Processo nº 642580043212025 (Pregão 90001/2026 – Colégio Militar do Rio de Janeiro). O processo da UFJ deve ser obtido no SEI. | CA39: 2 | CB39: 2 | CC39: 2 | CD39: 2 | CE39: 2 | CF39: 2 | CG39: 2 | CH39: Não | CI39: Não | CJ39: Não | DA39: O relatório principal da UFJ não menciona um número de processo. Os documentos anexos de referência indicam Processo nº 05800032468202617 (Pregão 90006/2026) e Processo nº 25115000123202541 (Pregão 90009/2026). | DC39: 2 | DD39: 2 | DE39: 2 | DF39: 2 | DG39: 2 | DH39: 2 | DI39: 2 | DJ39: Não | DK39: Não | DL39: Não | DO39: Não aplicável / Não especificado no documento principal (menciona processos específicos nos pregões anexos, ex: Processo nº 05800032468202617 e nº 25115000123202541). | DQ39: 2 | DR39: 2 | DS39: 2 | DT39: 2 | DU39: 2 | DV39: 2 | DW39: 2 | DX39: Não | DY39: Não | DZ39: Não
A40: 12 | B40: P04 | C40: {=IFERROR(INDEX(DOCUMENTOS!$E:$E,MATCH($A40,DOCUMENTOS!$A:$A,0)),"")} | D40: {=IFERROR(INDEX('BANCO DE PERGUNTAS'!$D:$D,MATCH($B40,'BANCO DE PERGUNTAS'!$A:$A,0)),"")} -> Qual é a data do documento? | E40: {=IFERROR(INDEX('BANCO DE PERGUNTAS'!$B:$B,MATCH($B40,'BANCO DE PERGUNTAS'!$A:$A,0)),"")} -> Identificação | F40: {=IFERROR(INDEX('BANCO DE PERGUNTAS'!$H:$H,MATCH($B40,'BANCO DE PERGUNTAS'!$A:$A,0)),"")} -> 1 | U40: 24/08/2026. Pesquisa realizada das 07:41:13 às 09:00:20; relatório detalhado gerado às 09:23:33 e relatório resumido às 09:25:10. As atas anexas possuem datas próprias. (PDF, pp. 1–2.) | W40: 2 | X40: 2 | Y40: 2 | Z40: 2 | AA40: 2 | AB40: 2 | AC40: 2 | AD40: Não | AE40: Não | AF40: Não | AI40: 24/08/2026. A pesquisa ocorreu das 07h41min13s às 09h00min20s. O resumo registra geração às 09h25min10s e o relatório detalhado às 09h23min33s. | AK40: 2 | AL40: 2 | AM40: 2 | AN40: 2 | AO40: 2 | AP40: 2 | AQ40: 2 | AR40: Não | AS40: Não | AT40: Não | BK40: Pesquisa realizada entre 24/08/2026 07:41:13 e 24/08/2026 09:00:20. Relatório resumido gerado em 24/08/2026 09:25:10; relatório detalhado gerado em 24/08/2026 09:23:33 (IP 200.137.253.160). | BM40: 2 | BN40: 2 | BO40: 2 | BP40: 2 | BQ40: 2 | BR40: 2 | BS40: 2 | BT40: Não | BU40: Não | BV40: Não | BY40: Pesquisa realizada em 24/08/2026, entre 07:41:13 e 09:00:20. Relatório de Cotação (detalhado) gerado em 24/08/2026 às 09:23:33 e Relatório Resumido gerado em 24/08/2026 às 09:25:10, ambos a partir do IP 200.137.253.160. Não há data de assinatura ou de aprovação. | CA40: 2 | CB40: 2 | CC40: 2 | CD40: 2 | CE40: 2 | CF40: 2 | CG40: 2 | CH40: Não | CI40: Não | CJ40: Não | DA40: O relatório principal foi gerado no dia 24/08/2026, com a pesquisa realizada no mesmo dia. | DC40: 2 | DD40: 2 | DE40: 2 | DF40: 2 | DG40: 2 | DH40: 2 | DI40: 2 | DJ40: Não | DK40: Não | DL40: Não | DO40: 24/08/2026 (Data da geração do relatório entre 07:41:13 e 09:25:10). | DQ40: 2 | DR40: 2 | DS40: 2 | DT40: 2 | DU40: 2 | DV40: 2 | DW40: 2 | DX40: Não | DY40: Não | DZ40: Não
A41: 12 | B41: P05 | C41: {=IFERROR(INDEX(DOCUMENTOS!$E:$E,MATCH($A41,DOCUMENTOS!$A:$A,0)),"")} | D41: {=IFERROR(INDEX('BANCO DE PERGUNTAS'!$D:$D,MATCH($B41,'BANCO DE PERGUNTAS'!$A:$A,0)),"")} -> Qual setor ou unidade está relacionado ao documento? | E41: {=IFERROR(INDEX('BANCO DE PERGUNTAS'!$B:$B,MATCH($B41,'BANCO DE PERGUNTAS'!$A:$A,0)),"")} -> Identificação | F41: {=IFERROR(INDEX('BANCO DE PERGUNTAS'!$H:$H,MATCH($B41,'BANCO DE PERGUNTAS'!$A:$A,0)),"")} -> 1 | U41: Universidade Federal de Jataí (UFJ), Pró-Reitoria de Administração e Finanças, Diretoria de Compras e Licitações, vinculada ao Ministério da Educação. CNPJ da UFJ: 35.840.659/0001-30. (PDF, pp. 1–2.) | W41: 2 | X41: 2 | Y41: 2 | Z41: 2 | AA41: 2 | AB41: 2 | AC41: 2 | AD41: Não | AE41: Não | AF41: Não | AI41: Universidade Federal de Jataí (UFJ), Pró-Reitoria de Administração e Finanças (PROAD), Diretoria de Compras e Licitações. | AK41: 2 | AL41: 2 | AM41: 2 | AN41: 2 | AO41: 2 | AP41: 2 | AQ41: 2 | AR41: Não | AS41: Não | AT41: Não | BK41: Ministério da Educação – Universidade Federal de Jataí (UFJ) – Pró-Reitoria de Administração e Finanças – Diretoria de Compras e Licitações (CNPJ 35.840.659/0001-30). | BM41: 2 | BN41: 2 | BO41: 2 | BP41: 2 | BQ41: 2 | BR41: 2 | BS41: 2 | BT41: Não | BU41: Não | BV41: Não | BY41: Ministério da Educação – Universidade Federal de Jataí (UFJ), Pró-Reitoria de Administração e Finanças, Diretoria de Compras e Licitações, CNPJ 35.840.659/0001-30 (conforme cabeçalho de todas as páginas do relatório). | CA41: 2 | CB41: 2 | CC41: 2 | CD41: 2 | CE41: 2 | CF41: 2 | CG41: 2 | CH41: Não | CI41: Não | CJ41: Não | DA41: Ministério da Educação, Universidade Federal de Jataí (UFJ) - DCL UFJ Pró Reitoria de Administração e Finanças, Diretoria de Compras e Licitações. | DC41: 2 | DD41: 2 | DE41: 2 | DF41: 2 | DG41: 2 | DH41: 2 | DI41: 2 | DJ41: Não | DK41: Não | DL41: Não | DO41: Diretoria de Compras e Licitações (DCL) da Pró-Reitoria de Administração e Finanças da Universidade Federal de Jataí (UFJ). | DQ41: 2 | DR41: 2 | DS41: 2 | DT41: 2 | DU41: 2 | DV41: 2 | DW41: 2 | DX41: Não | DY41: Não | DZ41: Não
A42: 12 | B42: P06 | C42: {=IFERROR(INDEX(DOCUMENTOS!$E:$E,MATCH($A42,DOCUMENTOS!$A:$A,0)),"")} | D42: {=IFERROR(INDEX('BANCO DE PERGUNTAS'!$D:$D,MATCH($B42,'BANCO DE PERGUNTAS'!$A:$A,0)),"")} -> Quais são as partes ou instituições mencionadas? | E42: {=IFERROR(INDEX('BANCO DE PERGUNTAS'!$B:$B,MATCH($B42,'BANCO DE PERGUNTAS'!$A:$A,0)),"")} -> Identificação | F42: {=IFERROR(INDEX('BANCO DE PERGUNTAS'!$H:$H,MATCH($B42,'BANCO DE PERGUNTAS'!$A:$A,0)),"")} -> 2 | U42: Instituição demandante: UFJ/MEC. EMPRESA PRISMA 2026 aparece no título, sem qualificação contratual. Fontes e órgãos pesquisados: IFPB/Campus João Pessoa, IFCE, Governo de São Paulo/SSP/Delegacia Seccional de Marília, Município de São José do Rio Pardo, Ministério da Saúde/Funasa, municípios de Darcinópolis e Caldas Novas, Ministério da Defesa/Exército/Colégio Militar do Rio de Janeiro; PNCP, Compras.gov.br e Banco de Preços. O mapa identifica ZELO, A1 Serviços, ROSCH, COMDERP, 51.722.124 Carla Alessandra Barbosa Perez, D G de Sousa, JL E Sousa Produtos Químicos e BRASIDAS; os anexos incluem outros participantes. (PDF, pp. 3–23.) | W42: 2 | X42: 2 | Y42: 2 | Z42: 2 | AA42: 2 | AB42: 2 | AC42: 2 | AD42: Não | AE42: Não | AF42: Não | AI42: Instituição responsável: Universidade Federal de Jataí (UFJ), vinculada ao Ministério da Educação (MEC). O relatório também menciona o Banco de Preços e órgãos públicos e fornecedores usados como fontes de comparação; há diversas entidades nos registros detalhados. | AK42: 2 | AL42: 2 | AM42: 2 | AN42: 2 | AO42: 2 | AP42: 2 | AQ42: 2 | AR42: Não | AS42: Não | AT42: Não | BK42: UFJ (solicitante). Como fontes das cotações: Instituto Federal da Paraíba, Instituto Federal do Ceará, Governo do Estado de São Paulo/Secretaria de Segurança Pública, Município de São José do Rio Pardo, Município de Darcinópolis, entre outros órgãos; e dezenas de empresas fornecedoras citadas nas propostas/atas anexadas (ex.: Zelo Locação de Mão de Obra, A1 Serviços, DR Soluções, Embraed Empreendimentos, EBCS, Fortline Serviços, Brasidas Ltda, entre muitas outras ao longo das 259 páginas). | BM42: 2 | BN42: 2 | BO42: 2 | BP42: 2 | BQ42: 2 | BR42: 2 | BS42: 2 | BT42: Não | BU42: Não | BV42: Não | BY42: Órgão demandante: UFJ/MEC. Ferramenta/meio: Banco de Preços (bancodeprecos.com.br). Fontes: Compras.gov.br e Portal Nacional de Contratações Públicas (PNCP). Órgãos cujas licitações foram usadas como paradigma: IFPB (Campus João Pessoa), IFCE, Governo do Estado de SP / SSP / Delegacia Seccional de Marília, Município de São José do Rio Pardo/SP, Fundação Nacional de Saúde – Funasa/MS, Município de Darcinópolis/TO, Município de Caldas Novas/GO e Colégio Militar do Rio de Janeiro (Comando do Exército / Ministério da Defesa). Fornecedores citados: dezenas, entre os quais Zelo Locação de Mão de Obra, A1 Serviços, Rosch Serviços Terceirizados, GRN Distribuidora, Comderp, Carla Alessandra Barbosa Perez (CNPJ 51.722.124/0001-11), D G de Sousa, JL e Sousa Produtos Químicos e Brasidas Ltda. | CA42: 2 | CB42: 2 | CC42: 2 | CD42: 2 | CE42: 2 | CF42: 2 | CG42: 2 | CH42: Não | CI42: Não | CJ42: Não | DA42: Universidade Federal de Jataí (solicitante), Banco de Preços (sistema), além de instituições utilizadas como fontes de cotação (ex: IFPB, IFCE, Governo de SP, Funasa) e diversas empresas licitantes (ex: Empresa Prisma 2026, Rosch, Unicca). | DC42: 2 | DD42: 2 | DE42: 2 | DF42: 2 | DG42: 2 | DH42: 2 | DI42: 2 | DJ42: Não | DK42: Não | DL42: Não | DO42: Universidade Federal de Jataí (UFJ), Ministério da Educação, além de diversos órgãos públicos e fornecedores participantes das cotações. | DQ42: 2 | DR42: 2 | DS42: 1 | DT42: 2 | DU42: 2 | DV42: 2 | DW42: 2 | DX42: Não | DY42: Não | DZ42: Não
A43: 12 | B43: P07 | C43: {=IFERROR(INDEX(DOCUMENTOS!$E:$E,MATCH($A43,DOCUMENTOS!$A:$A,0)),"")} | D43: {=IFERROR(INDEX('BANCO DE PERGUNTAS'!$D:$D,MATCH($B43,'BANCO DE PERGUNTAS'!$A:$A,0)),"")} -> Qual informação específica está apresentada na seção 08? | E43: {=IFERROR(INDEX('BANCO DE PERGUNTAS'!$B:$B,MATCH($B43,'BANCO DE PERGUNTAS'!$A:$A,0)),"")} -> Localização | F43: {=IFERROR(INDEX('BANCO DE PERGUNTAS'!$H:$H,MATCH($B43,'BANCO DE PERGUNTAS'!$A:$A,0)),"")} -> 2 | U43: não consta no documento uma seção intitulada 08. A página interna 8/22 do relatório detalhado, correspondente à página 9 do PDF, trata do Item 2: Material Sob Demanda + BDI, estimado em R$ 20.231,97; página e seção não são equivalentes. | W43: 2 | X43: 2 | Y43: 2 | Z43: 2 | AA43: 2 | AB43: 2 | AC43: 2 | AD43: Não | AE43: Não | AF43: Não | AI43: Não consta seção 08 numerada no relatório. O documento apresenta pesquisa de preços, método de cálculo e referências de mercado. | AK43: 2 | AL43: 2 | AM43: 2 | AN43: 2 | AO43: 2 | AP43: 2 | AQ43: 2 | AR43: Não | AS43: Não | AT43: Não | BK43: Não consta — o documento não possui uma "Seção 08" ou numeração de seções nesse formato; sua estrutura é: capa/resumo, detalhamento por item e anexos com as fontes de cada cotação. | BM43: 2 | BN43: 2 | BO43: 2 | BP43: 2 | BQ43: 2 | BR43: 2 | BS43: 2 | BT43: Não | BU43: Não | BV43: Não | BY43: NÃO APLICÁVEL. O documento não é organizado em seções numeradas, portanto não existe "seção 08". Se a referência for à página 8 do Relatório de Cotação (numeração 8/22), essa página inicia o detalhamento do Item 2 – Material Sob Demanda + BDI, com o preço estimado de R$ 20.231,97 e o primeiro preço-fonte (Município de São José do Rio Pardo/SP, Dispensa, R$ 17.590,22). | CA43: 2 | CB43: 2 | CC43: 2 | CD43: 2 | CE43: 2 | CF43: 2 | CG43: 2 | CH43: Não | CI43: Não | CJ43: Não | DA43: Não há uma "seção 08" estruturada no relatório principal. Contudo, no histórico de chat do Pregão 90006/2026, o "Item 8 do Edital" é citado como o referente à fase de envio de documentos de habilitação. | DC43: 2 | DD43: 2 | DE43: 2 | DF43: 2 | DG43: 2 | DH43: 2 | DI43: 2 | DJ43: Não | DK43: Não | DL43: Não | DO43: O documento apresenta o detalhamento do item 2 (Material Sob Demanda + BDI) e cotações específicas de órgãos governamentais nas páginas correspondentes. | DQ43: 1 | DR43: 1 | DS43: 1 | DT43: 2 | DU43: 2 | DV43: 1 | DW43: 2 | DX43: Não | DY43: Sim | DZ43: Sim | EA43: Erro de interpretação
A44: 12 | B44: P08 | C44: {=IFERROR(INDEX(DOCUMENTOS!$E:$E,MATCH($A44,DOCUMENTOS!$A:$A,0)),"")} | D44: {=IFERROR(INDEX('BANCO DE PERGUNTAS'!$D:$D,MATCH($B44,'BANCO DE PERGUNTAS'!$A:$A,0)),"")} -> Em qual seção do documento está localizada a informação solicitada? | E44: {=IFERROR(INDEX('BANCO DE PERGUNTAS'!$B:$B,MATCH($B44,'BANCO DE PERGUNTAS'!$A:$A,0)),"")} -> Localização | F44: {=IFERROR(INDEX('BANCO DE PERGUNTAS'!$H:$H,MATCH($B44,'BANCO DE PERGUNTAS'!$A:$A,0)),"")} -> 2 | U44: A informação solicitada não foi especificada na pergunta. Localização dos principais dados: identificação e datas nas pp. 1–2; Detalhamento dos Itens nas pp. 3–20; Mapa Comparativo de Preços nas pp. 21–22; Extrato de fontes na p. 23; Anexo 1 — Memorial de Cálculo nas pp. 24–27. Referências à paginação física do PDF. | W44: 2 | X44: 2 | Y44: 2 | Z44: 2 | AA44: 2 | AB44: 2 | AC44: 2 | AD44: Não | AE44: Não | AF44: Não | AI44: O relatório não tem seção 08 numerada. Os preços consolidados estão no “Relatório Resumido de Cotação”, página 1; os registros e preços de referência aparecem no detalhamento dos itens, a partir da página 2 do relatório de cotação. | AK44: 2 | AL44: 2 | AM44: 2 | AN44: 2 | AO44: 2 | AP44: 2 | AQ44: 2 | AR44: Não | AS44: Não | AT44: Não | BK44: Não aplicável — a pergunta pressupõe uma seção numerada que não existe neste documento. | BM44: 2 | BN44: 2 | BO44: 2 | BP44: 2 | BQ44: 2 | BR44: 2 | BS44: 2 | BT44: Não | BU44: Não | BV44: Não | BY44: NÃO APLICÁVEL – não há seções numeradas. A estrutura efetiva do documento (259 páginas no total) é: (i) Relatório Resumido de Cotação – 1 página; (ii) Relatório de Cotação, com "Detalhamento dos Itens" – 22 páginas, incluindo ao final o "Extrato de fontes utilizadas neste relatório"; (iii) Anexo 1 – Memorial de Cálculo – 4 páginas; (iv) anexos com 4 Termos de Homologação das licitações-fonte (46 + 89 + 89 + 8 páginas). | CA44: 2 | CB44: 2 | CC44: 2 | CD44: 2 | CE44: 2 | CF44: 2 | CG44: 2 | CH44: Não | CI44: Não | CJ44: Não | DA44: A citação ao item 8 do edital encontra-se na transcrição do chat do Pregão 90006/2026 (Mensagem do Sistema às 14:02:09). | DC44: 1 | DD44: 1 | DE44: 1 | DF44: 2 | DG44: 2 | DH44: 1 | DI44: 2 | DJ44: Não | DK44: Sim | DL44: Sim | DM44: Erro de interpretação | DO44: Seção de detalhamento dos itens e Mapa Comparativo de Preços. | DQ44: 1 | DR44: 1 | DS44: 1 | DT44: 2 | DU44: 2 | DV44: 1 | DW44: 2 | DX44: Não | DY44: Sim | DZ44: Sim | EA44: Erro de interpretação
A45: 12 | B45: P09 | C45: {=IFERROR(INDEX(DOCUMENTOS!$E:$E,MATCH($A45,DOCUMENTOS!$A:$A,0)),"")} | D45: {=IFERROR(INDEX('BANCO DE PERGUNTAS'!$D:$D,MATCH($B45,'BANCO DE PERGUNTAS'!$A:$A,0)),"")} -> Qual é o valor indicado para o Valor Total Anual do Objeto licitado? | E45: {=IFERROR(INDEX('BANCO DE PERGUNTAS'!$B:$B,MATCH($B45,'BANCO DE PERGUNTAS'!$A:$A,0)),"")} -> Localização | F45: {=IFERROR(INDEX('BANCO DE PERGUNTAS'!$H:$H,MATCH($B45,'BANCO DE PERGUNTAS'!$A:$A,0)),"")} -> 1 | U45: não consta no documento o Valor Total Anual do Objeto licitado. Consta Valor Global de R$ 23.700,41, composto por R$ 4,97 + R$ 20.231,97 + R$ 3.463,47, com quantidade 1 em cada item; o relatório não o qualifica como anual. (PDF, p. 1.) | W45: 2 | X45: 2 | Y45: 2 | Z45: 2 | AA45: 2 | AB45: 2 | AC45: 2 | AD45: Não | AE45: Não | AF45: Não | AI45: Não consta valor total anual no relatório. O valor global nele apresentado é R$ 23.700,41, calculado para quantidade 1 de cada item; não deve ser interpretado como total anual. | AK45: 2 | AL45: 2 | AM45: 2 | AN45: 2 | AO45: 2 | AP45: 2 | AQ45: 2 | AR45: Não | AS45: Não | AT45: Não | BK45: Não há um campo rotulado "Valor Total Anual do Objeto licitado". O relatório indica apenas o "Valor Global" da pesquisa: R$ 23.700,41 (soma dos 3 itens: R$ 4,97 + R$ 20.231,97 + R$ 3.463,47). | BM45: 2 | BN45: 2 | BO45: 2 | BP45: 2 | BQ45: 2 | BR45: 2 | BS45: 2 | BT45: Não | BU45: Não | BV45: Não | BY45: NÃO CONSTA. O documento não apresenta "Valor Total Anual do Objeto licitado". O único valor consolidado é o Valor Global de R$ 23.700,41, que corresponde à soma dos preços unitários estimados dos 3 itens (R$ 4,97 + R$ 20.231,97 + R$ 3.463,47), considerando quantidade 1 para cada item. Esse valor NÃO representa o custo anual do contrato e não deve ser utilizado como tal. | CA45: 2 | CB45: 2 | CC45: 2 | CD45: 2 | CE45: 2 | CF45: 2 | CG45: 2 | CH45: Não | CI45: Não | CJ45: Não | DA45: O documento indica o "Valor Global" estimado da contratação em R$ 23.700,41. Não especifica se é um valor anual. | DC45: 1 | DD45: 1 | DE45: 1 | DF45: 2 | DG45: 2 | DH45: 1 | DI45: 2 | DJ45: Não | DK45: Sim | DL45: Sim | DM45: Erro de interpretação | DO45: Valor Global de R$ 23.700,41. | DQ45: 1 | DR45: 1 | DS45: 1 | DT45: 2 | DU45: 2 | DV45: 1 | DW45: 2 | DX45: Não | DY45: Sim | DZ45: Sim | EA45: Erro de interpretação
A46: 12 | B46: P10 | C46: {=IFERROR(INDEX(DOCUMENTOS!$E:$E,MATCH($A46,DOCUMENTOS!$A:$A,0)),"")} | D46: {=IFERROR(INDEX('BANCO DE PERGUNTAS'!$D:$D,MATCH($B46,'BANCO DE PERGUNTAS'!$A:$A,0)),"")} -> Qual é a data indicada para de assinatura de todos os membros da comissão da contratação? | E46: {=IFERROR(INDEX('BANCO DE PERGUNTAS'!$B:$B,MATCH($B46,'BANCO DE PERGUNTAS'!$A:$A,0)),"")} -> Localização | F46: {=IFERROR(INDEX('BANCO DE PERGUNTAS'!$H:$H,MATCH($B46,'BANCO DE PERGUNTAS'!$A:$A,0)),"")} -> 1 | U46: não consta no documento a data de assinatura de todos os membros da comissão de contratação da UFJ. As datas de geração dos relatórios e de homologação das atas anexas não correspondem a essa assinatura. | W46: 2 | X46: 2 | Y46: 2 | Z46: 2 | AA46: 2 | AB46: 2 | AC46: 2 | AD46: Não | AE46: Não | AF46: Não | AI46: Não consta no relatório data de assinatura nem identificação ou assinatura dos membros da comissão de contratação. | AK46: 2 | AL46: 2 | AM46: 2 | AN46: 2 | AO46: 2 | AP46: 2 | AQ46: 2 | AR46: Não | AS46: Não | AT46: Não | BK46: Não consta — este relatório não é um documento de comissão de contratação e não possui página de assinaturas; é gerado automaticamente pelo sistema Banco de Preços. | BM46: 2 | BN46: 2 | BO46: 2 | BP46: 2 | BQ46: 2 | BR46: 2 | BS46: 2 | BT46: Não | BU46: Não | BV46: Não | BY46: NÃO CONSTA. O documento não contém assinaturas — nem de membros de comissão de contratação, nem de agente de contratação, nem do responsável pela pesquisa. A autenticidade é atestada apenas por código de validação eletrônico do Banco de Preços. Eventual assinatura existirá no documento SEI que encaminha ou aprova este relatório, não neste PDF. | CA46: 2 | CB46: 2 | CC46: 2 | CD46: 2 | CE46: 2 | CF46: 2 | CG46: 2 | CH46: Não | CI46: Não | CJ46: Não | DA46: Essa informação está ausente no documento fornecido. | DC46: 2 | DD46: 2 | DE46: 2 | DF46: 2 | DG46: 2 | DH46: 2 | DI46: 2 | DJ46: Não | DK46: Não | DL46: Não | DO46: Não consta data de assinatura dos membros da comissão no relatório gerado por sistema eletrônico. | DQ46: 2 | DR46: 2 | DS46: 2 | DT46: 2 | DU46: 2 | DV46: 2 | DW46: 2 | DX46: Não | DY46: Não | DZ46: Não
A47: 12 | B47: P11 | C47: {=IFERROR(INDEX(DOCUMENTOS!$E:$E,MATCH($A47,DOCUMENTOS!$A:$A,0)),"")} | D47: {=IFERROR(INDEX('BANCO DE PERGUNTAS'!$D:$D,MATCH($B47,'BANCO DE PERGUNTAS'!$A:$A,0)),"")} -> Extraia os principais dados do documento em formato estruturado. | E47: {=IFERROR(INDEX('BANCO DE PERGUNTAS'!$B:$B,MATCH($B47,'BANCO DE PERGUNTAS'!$A:$A,0)),"")} -> Extração | F47: {=IFERROR(INDEX('BANCO DE PERGUNTAS'!$H:$H,MATCH($B47,'BANCO DE PERGUNTAS'!$A:$A,0)),"")} -> 2 | U47: Documento: Relatório de Cotação EMPRESA PRISMA 2026; identificação no arquivo: 0631080; órgão: UFJ; CNPJ: 35.840.659/0001-30; unidade: Diretoria de Compras e Licitações/Pró-Reitoria de Administração e Finanças; pesquisa: 24/08/2026, 07:41:13–09:00:20; método: média aritmética de três preços selecionados por item, com referências apresentadas como medianas de propostas finais; item 1: 1 m², R$ 4,97; item 2: 1 unidade, R$ 20.231,97; item 3: 1 unidade, R$ 3.463,47; global: R$ 23.700,41; fontes: PNCP e Compras.gov.br; processo da UFJ e total anual: não consta no documento. (PDF, pp. 1–27.) | W47: 2 | X47: 2 | Y47: 2 | Z47: 2 | AA47: 2 | AB47: 2 | AC47: 2 | AD47: Não | AE47: Não | AF47: Não | AI47: Título: Relatório de Cotação “EMPRESA PRISMA 2026”. Órgão: UFJ/PROAD/Diretoria de Compras e Licitações. Pesquisa: 24/08/2026, das 07h41min13s às 09h00min20s. Método: média aritmética dos preços selecionados. Item 1: serviço de limpeza e conservação, R$ 4,97/unidade. Item 2: materiais sob demanda + BDI, R$ 20.231,97/unidade. Item 3: equipamentos + BDI, R$ 3.463,47/unidade. Valor global do resumo: R$ 23.700,41 para quantidade 1 de cada item. | AK47: 2 | AL47: 2 | AM47: 2 | AN47: 2 | AO47: 2 | AP47: 2 | AQ47: 2 | AR47: Não | AS47: Não | AT47: Não | BK47: Órgão: UFJ/Diretoria de Compras e Licitações | Identificação interna: "EMPRESA PRISMA 2026" | Base legal: IN 65/2021 e Lei 14.133/2021 | Método: Média Aritmética | Itens: 3 | Valor Global: R$ 23.700,41 | Cotações por item: mínimo 3 (Art. 5º, Inc. I) | Datas: pesquisa em 24/08/2026 | Extensão: 259 páginas (inclui anexos-fonte de cada cotação). | BM47: 2 | BN47: 2 | BO47: 2 | BP47: 2 | BQ47: 2 | BR47: 2 | BS47: 2 | BT47: Não | BU47: Não | BV47: Não | BY47: Órgão: UFJ/MEC – PROAF/Diretoria de Compras e Licitações, CNPJ 35.840.659/0001-30 | Título da cotação: EMPRESA PRISMA 2026 | Período da pesquisa: 24/08/2026, 07:41:13 a 09:00:20 | Geração: 24/08/2026 09:23:33 (detalhado) e 09:25:10 (resumido) | Fundamento: Lei 14.133/2021 e IN SEGES/ME nº 65/2021, art. 5º, inc. I (contratações públicas similares) | Método: média aritmética dos preços obtidos | Quantidade de preços: 3 por item | ITEM 1 – Prestação de serviço de limpeza e conservação, 1 m², preço estimado R$ 4,97/m², preços-fonte R$ 4,98 (IFPB), R$ 4,93 (IFCE) e R$ 5,00 (SSP/SP) | ITEM 2 – Material sob demanda + BDI, 1 unidade, preço estimado R$ 20.231,97, preços-fonte R$ 17.590,22 (São José do Rio Pardo), R$ 20.773,80 e R$ 22.331,88 (ambos Funasa, Pregão 90009/2026) | ITEM 3 – Equipamentos BDI, 1 unidade, preço estimado R$ 3.463,47, preços-fonte R$ 3.712,00 (Darcinópolis/TO), R$ 3.849,40 (Caldas Novas/GO) e R$ 2.829,00 (CMRJ) | Valor Global: R$ 23.700,41 | Participação: Item 2 = 85,4% e Item 3 = 14,6% | Fontes: Compras.gov.br (acesso 24/08/2026 07:55:09) e PNCP (acesso 24/08/2026 07:54:59) | Anexos: Memorial de Cálculo e 4 Termos de Homologação. | CA47: 2 | CB47: 2 | CC47: 2 | CD47: 2 | CE47: 2 | CF47: 2 | CG47: 2 | CH47: Não | CI47: Não | CJ47: Não | DA47: Órgão: UFJ. Metodologia: Média Aritmética (IN 65/2021). Valor Global Estimado: R$ 23.700,41. Itens Cotados: 1) Limpeza (R$ 4,97/m²), 2) Material/BDI (R$ 20.231,97/un), 3) Equipamentos/BDI (R$ 3.463,47/un). | DC47: 2 | DD47: 2 | DE47: 2 | DF47: 2 | DG47: 2 | DH47: 2 | DI47: 2 | DJ47: Não | DK47: Não | DL47: Não | DO47: Itens cotados: 1) Prestação de Serviço de limpeza e conservação (R$ 4,97 un); 2) Material Sob Demanda BDI (R$ 20.231,97 un); 3) Equipamentos BDI (R$ 3.463,47 un). | DQ47: 2 | DR47: 2 | DS47: 2 | DT47: 2 | DU47: 2 | DV47: 2 | DW47: 2 | DX47: Não | DY47: Não | DZ47: Não
A48: 12 | B48: P12 | C48: {=IFERROR(INDEX(DOCUMENTOS!$E:$E,MATCH($A48,DOCUMENTOS!$A:$A,0)),"")} | D48: {=IFERROR(INDEX('BANCO DE PERGUNTAS'!$D:$D,MATCH($B48,'BANCO DE PERGUNTAS'!$A:$A,0)),"")} -> Liste os valores financeiros presentes no documento. | E48: {=IFERROR(INDEX('BANCO DE PERGUNTAS'!$B:$B,MATCH($B48,'BANCO DE PERGUNTAS'!$A:$A,0)),"")} -> Extração | F48: {=IFERROR(INDEX('BANCO DE PERGUNTAS'!$H:$H,MATCH($B48,'BANCO DE PERGUNTAS'!$A:$A,0)),"")} -> 2 | U48: Valores centrais: limpeza — referências R$ 4,98, R$ 4,93 e R$ 5,00; média R$ 4,97. Material sob demanda + BDI — R$ 17.590,22, R$ 20.773,80 e R$ 22.331,88; média R$ 20.231,97. Equipamentos BDI — R$ 3.712,00, R$ 3.849,40 e R$ 2.829,00; média R$ 3.463,47. Valor global R$ 23.700,41. Há ainda propostas iniciais, finais, lances e totais nos anexos; a aba Valores do PDF lista as ocorrências monetárias explícitas em R$, com página e trecho, preservando repetições. Esses valores não devem ser somados indiscriminadamente. (PDF, pp. 1–259.) | W48: 2 | X48: 2 | Y48: 2 | Z48: 2 | AA48: 2 | AB48: 2 | AC48: 2 | AD48: Não | AE48: Não | AF48: Não | AI48: Valores estimados consolidados: R$ 4,97 (item 1), R$ 20.231,97 (item 2), R$ 3.463,47 (item 3) e R$ 23.700,41 (global para uma unidade de cada item). O detalhamento contém também diversos preços de propostas/fontes, incluindo, por exemplo, R$ 4,98, R$ 4,93 e R$ 5,00 para o item 1; os preços de referência de cada fonte estão discriminados nas páginas dos itens. | AK48: 2 | AL48: 2 | AM48: 2 | AN48: 2 | AO48: 2 | AP48: 2 | AQ48: 2 | AR48: Não | AS48: Não | AT48: Não | BK48: Item 1 (limpeza/conservação): R$ 4,97 — 3 cotações entre R$ 4,93 e R$ 5,00. Item 2 (Material Sob Demanda + BDI): R$ 20.231,97 — 3 cotações entre R$ 17.590,22 e R$ 22.331,88. Item 3 (Equipamentos BDI): R$ 3.463,47 — 3 cotações entre R$ 2.829,00 e R$ 3.849,40. Valor Global do relatório: R$ 23.700,41. | BM48: 2 | BN48: 2 | BO48: 2 | BP48: 2 | BQ48: 2 | BR48: 2 | BS48: 2 | BT48: Não | BU48: Não | BV48: Não | BY48: ITEM 1 – preço estimado R$ 4,97/m²; preços coletados R$ 4,98; R$ 4,93; R$ 5,00 (propostas individuais variando de R$ 3,60 a R$ 5,05, com propostas iniciais de até R$ 50,00 e R$ 1.000,00). ITEM 2 – preço estimado R$ 20.231,97; preços coletados R$ 17.590,22; R$ 20.773,80; R$ 22.331,88 (propostas vencedoras de R$ 20.722,00 e R$ 22.331,00). ITEM 3 – preço estimado R$ 3.463,47; preços coletados R$ 3.712,00; R$ 3.849,40; R$ 2.829,00 (propostas de R$ 2.728,99 a R$ 2.851,99). VALOR GLOBAL: R$ 23.700,41. Percentuais de composição: Item 2 = 85,4%; Item 3 = 14,6%; Item 1 = 0% (arredondamento). Valores citados nos Termos de Homologação anexos, como R$ 4.112,20, R$ 3.584,17 e R$ 2.570,60, referem-se a licitações de terceiros e não integram a estimativa da UFJ. | CA48: 2 | CB48: 2 | CC48: 2 | CD48: 2 | CE48: 2 | CF48: 2 | CG48: 2 | CH48: Não | CI48: Não | CJ48: Não | DA48: Valor global: R$ 23.700,41. Valores estimados por item: Item 1 (R$ 4,97), Item 2 (R$ 20.231,97), Item 3 (R$ 3.463,47). O anexo lista dezenas de lances de pregões, variando de centavos (R$ 0,20) a milhares de reais (R$ 775.000,00). | DC48: 2 | DD48: 1 | DE48: 2 | DF48: 2 | DG48: 2 | DH48: 1 | DI48: 2 | DJ48: Não | DK48: Sim | DL48: Não | DO48: R$ 4,97, R$ 20.231,97, R$ 3.463,47 e Valor Global de R$ 23.700,41 (além de diversas propostas de fornecedores listadas no corpo do documento). | DQ48: 2 | DR48: 1 | DS48: 2 | DT48: 2 | DU48: 2 | DV48: 1 | DW48: 2 | DX48: Não | DY48: Sim | DZ48: Não
A49: 12 | B49: P13 | C49: {=IFERROR(INDEX(DOCUMENTOS!$E:$E,MATCH($A49,DOCUMENTOS!$A:$A,0)),"")} | D49: {=IFERROR(INDEX('BANCO DE PERGUNTAS'!$D:$D,MATCH($B49,'BANCO DE PERGUNTAS'!$A:$A,0)),"")} -> Liste as obrigações ou responsabilidades estabelecidas. | E49: {=IFERROR(INDEX('BANCO DE PERGUNTAS'!$B:$B,MATCH($B49,'BANCO DE PERGUNTAS'!$A:$A,0)),"")} -> Extração | F49: {=IFERROR(INDEX('BANCO DE PERGUNTAS'!$H:$H,MATCH($B49,'BANCO DE PERGUNTAS'!$A:$A,0)),"")} -> 2 | U49: O objeto prevê prestação continuada de limpeza, conservação e asseio, com fornecimento de mão de obra, insumos, máquinas e equipamentos necessários à UFJ. O relatório declara a materialização da pesquisa e a indicação do método matemático, citando a IN 65/2021. Nos anexos, há exigências próprias dos certames de referência, como envio de proposta ajustada e documentos; não estão automaticamente estabelecidas como obrigações da contratação da UFJ. (PDF, pp. 2–3 e 259.) | W49: 2 | X49: 2 | Y49: 2 | Z49: 2 | AA49: 2 | AB49: 2 | AC49: 2 | AD49: Não | AE49: Não | AF49: Não | AI49: O relatório não estabelece obrigações contratuais ou responsabilidades de execução. Registra que a pesquisa foi feita conforme a IN nº 65/2021 e informa o método matemático e as fontes dos preços. | AK49: 2 | AL49: 2 | AM49: 2 | AN49: 2 | AO49: 2 | AP49: 2 | AQ49: 2 | AR49: Não | AS49: Não | AT49: Não | BK49: O relatório não estabelece obrigações ou responsabilidades contratuais — é apenas um levantamento de preços de mercado (fase de planejamento da contratação). Eventuais obrigações das partes constarão do Termo de Referência/Edital/Contrato, documentos distintos deste relatório, não incluídos no arquivo enviado. | BM49: 2 | BN49: 2 | BO49: 2 | BP49: 2 | BQ49: 2 | BR49: 2 | BS49: 2 | BT49: Não | BU49: Não | BV49: Não | BY49: O documento NÃO estabelece obrigações ou responsabilidades contratuais — trata-se de peça instrutória da fase preparatória, sem cláusulas, sem partes contratantes e sem eficácia obrigacional. As únicas exigências presentes são de natureza metodológica e decorrem da norma invocada (Lei 14.133/2021 e IN SEGES/ME nº 65/2021, arts. 3º e 5º): materializar a pesquisa em documento; indicar o método matemático aplicado; caracterizar as fontes; apresentar a série de preços. Observe-se que o próprio relatório não cumpre integralmente os incisos II e VI do art. 3º da IN 65/2021 (ver respostas 19 e 22). | CA49: 2 | CB49: 2 | CC49: 2 | CD49: 2 | CE49: 2 | CF49: 2 | CG49: 2 | CH49: Não | CI49: Não | CJ49: Não | DA49: Fornecimento de mão de obra (com dedicação exclusiva), insumos, máquinas e equipamentos necessários para a limpeza e conservação contínua nas dependências da instituição. | DC49: 2 | DD49: 1 | DE49: 2 | DF49: 2 | DG49: 2 | DH49: 1 | DI49: 2 | DJ49: Não | DK49: Sim | DL49: Não | DO49: Realização de pesquisa de preços em conformidade com a IN nº 65/2021 e Lei nº 14.133/2021 para estimativa de custos. | DQ49: 2 | DR49: 1 | DS49: 2 | DT49: 2 | DU49: 2 | DV49: 1 | DW49: 2 | DX49: Não | DY49: Sim | DZ49: Não
A50: 12 | B50: P14 | C50: {=IFERROR(INDEX(DOCUMENTOS!$E:$E,MATCH($A50,DOCUMENTOS!$A:$A,0)),"")} | D50: {=IFERROR(INDEX('BANCO DE PERGUNTAS'!$D:$D,MATCH($B50,'BANCO DE PERGUNTAS'!$A:$A,0)),"")} -> Explique o significado da cláusula/seção 4.1.4.. | E50: {=IFERROR(INDEX('BANCO DE PERGUNTAS'!$B:$B,MATCH($B50,'BANCO DE PERGUNTAS'!$A:$A,0)),"")} -> Interpretação | F50: {=IFERROR(INDEX('BANCO DE PERGUNTAS'!$H:$H,MATCH($B50,'BANCO DE PERGUNTAS'!$A:$A,0)),"")} -> 3 | U50: não consta no documento o texto da cláusula/seção 4.1.4.; não é possível explicar seu significado com base no arquivo fornecido. | W50: 2 | X50: 2 | Y50: 2 | Z50: 2 | AA50: 2 | AB50: 2 | AC50: 2 | AD50: Não | AE50: Não | AF50: Não | AI50: Não consta cláusula ou seção 4.1.4 no relatório. | AK50: 2 | AL50: 2 | AM50: 2 | AN50: 2 | AO50: 2 | AP50: 2 | AQ50: 2 | AR50: Não | AS50: Não | AT50: Não | BK50: Não aplicável — não existe cláusula ou seção "4.1.4" neste documento. Não há numeração de cláusulas nesse relatório (ele não é um contrato/TR/edital). | BM50: 2 | BN50: 2 | BO50: 2 | BP50: 2 | BQ50: 2 | BR50: 2 | BS50: 2 | BT50: Não | BU50: Não | BV50: Não | BY50: NÃO EXISTE. O documento não possui cláusula, item ou seção 4.1.4 — a numeração em questão não aparece em nenhuma das 259 páginas. A única menção semelhante está em mensagem de chat de licitação de terceiro anexada ao documento (Pregão 90001/2026 – CMRJ), que cita "item 4.1.6 do termo de referência" daquele órgão, sem qualquer relação com a UFJ. A pergunta parece ter sido formulada para outro tipo de documento (Termo de Referência, ETP ou minuta de contrato). | CA50: 2 | CB50: 2 | CC50: 2 | CD50: 2 | CE50: 2 | CF50: 2 | CG50: 2 | CH50: Não | CI50: Não | CJ50: Não | DA50: Cláusula 4.1.4 ausente no documento fornecido. | DC50: 2 | DD50: 2 | DE50: 2 | DF50: 2 | DG50: 2 | DH50: 2 | DI50: 2 | DJ50: Não | DK50: Não | DL50: Não | DO50: Cláusula/seção não aplicável diretamente ao relatório de pesquisa de preços estruturado (trata-se de relatório sistêmico do Banco de Preços). | DQ50: 2 | DR50: 2 | DS50: 2 | DT50: 2 | DU50: 2 | DV50: 2 | DW50: 2 | DX50: Não | DY50: Não | DZ50: Não
A51: 12 | B51: P15 | C51: {=IFERROR(INDEX(DOCUMENTOS!$E:$E,MATCH($A51,DOCUMENTOS!$A:$A,0)),"")} | D51: {=IFERROR(INDEX('BANCO DE PERGUNTAS'!$D:$D,MATCH($B51,'BANCO DE PERGUNTAS'!$A:$A,0)),"")} -> Qual é a finalidade administrativa deste documento? | E51: {=IFERROR(INDEX('BANCO DE PERGUNTAS'!$B:$B,MATCH($B51,'BANCO DE PERGUNTAS'!$A:$A,0)),"")} -> Interpretação | F51: {=IFERROR(INDEX('BANCO DE PERGUNTAS'!$H:$H,MATCH($B51,'BANCO DE PERGUNTAS'!$A:$A,0)),"")} -> 3 | U51: Documentar a pesquisa de preços e apresentar estimativas e referências para subsidiar a contratação de empresa remanescente de limpeza e conservação da UFJ, com método estatístico, fontes e memória de cálculo. (PDF, pp. 1–3 e 21–27.) | W51: 2 | X51: 2 | Y51: 2 | Z51: 2 | AA51: 2 | AB51: 2 | AC51: 2 | AD51: Não | AE51: Não | AF51: Não | AI51: Documentar a pesquisa de preços e fornecer valores de referência para estimar a contratação de serviços de limpeza, materiais e equipamentos. | AK51: 2 | AL51: 2 | AM51: 2 | AN51: 2 | AO51: 2 | AP51: 2 | AQ51: 2 | AR51: Não | AS51: Não | AT51: Não | BK51: Subsidiar, na fase interna do planejamento da contratação, a estimativa/valor de referência dos itens pesquisados pela UFJ, conforme art. 3º, inciso V, da IN SEGES/ME nº 65/2021 (Lei nº 14.133/2021), que exige registro do método matemático aplicado na definição do valor estimado. | BM51: 2 | BN51: 2 | BO51: 2 | BP51: 2 | BQ51: 2 | BR51: 2 | BS51: 2 | BT51: Não | BU51: Não | BV51: Não | BY51: Instruir a fase preparatória da contratação, formando o preço estimado do objeto, nos termos do art. 23 da Lei nº 14.133/2021 e da IN SEGES/ME nº 65/2021. Serve de base para: definição do valor estimado da contratação, juízo de adequação orçamentária, aferição de exequibilidade e de sobrepreço das propostas, e eventual negociação. É documento obrigatório de instrução do processo de contratação. | CA51: 2 | CB51: 2 | CC51: 2 | CD51: 2 | CE51: 2 | CF51: 2 | CG51: 2 | CH51: Não | CI51: Não | CJ51: Não | DA51: Materializar e formalizar a pesquisa de preços de mercado para compor o valor estimado de uma futura contratação pública, cumprindo as exigências da Instrução Normativa Nº 65/2021 e da Lei nº 14.133. | DC51: 2 | DD51: 2 | DE51: 2 | DF51: 2 | DG51: 2 | DH51: 2 | DI51: 2 | DJ51: Não | DK51: Não | DL51: Não | DO51: Materializar a pesquisa de preços para fins de instrução de procedimento licitatório ou contratação direta. | DQ51: 2 | DR51: 2 | DS51: 2 | DT51: 2 | DU51: 2 | DV51: 1 | DW51: 2 | DX51: Não | DY51: Não | DZ51: Não
A52: 12 | B52: P16 | C52: {=IFERROR(INDEX(DOCUMENTOS!$E:$E,MATCH($A52,DOCUMENTOS!$A:$A,0)),"")} | D52: {=IFERROR(INDEX('BANCO DE PERGUNTAS'!$D:$D,MATCH($B52,'BANCO DE PERGUNTAS'!$A:$A,0)),"")} -> Qual consequência decorre da informação estabelecida em 4.11? | E52: {=IFERROR(INDEX('BANCO DE PERGUNTAS'!$B:$B,MATCH($B52,'BANCO DE PERGUNTAS'!$A:$A,0)),"")} -> Interpretação | F52: {=IFERROR(INDEX('BANCO DE PERGUNTAS'!$H:$H,MATCH($B52,'BANCO DE PERGUNTAS'!$A:$A,0)),"")} -> 3 | U52: não consta no documento o texto da seção 4.11; não é possível identificar a consequência solicitada. | W52: 2 | X52: 2 | Y52: 2 | Z52: 2 | AA52: 2 | AB52: 2 | AC52: 2 | AD52: Não | AE52: Não | AF52: Não | AI52: Não consta item ou seção 4.11 no relatório. | AK52: 2 | AL52: 2 | AM52: 2 | AN52: 2 | AO52: 2 | AP52: 2 | AQ52: 2 | AR52: Não | AS52: Não | AT52: Não | BK52: Não aplicável — não existe item "4.11" neste documento. | BM52: 2 | BN52: 2 | BO52: 2 | BP52: 2 | BQ52: 2 | BR52: 2 | BS52: 2 | BT52: Não | BU52: Não | BV52: Não | BY52: NÃO EXISTE. O documento não possui item, cláusula ou seção 4.11, de modo que não há consequência a ser extraída. As ocorrências da sequência "4.11" no arquivo correspondem apenas a fragmentos de valores monetários de licitações anexas (ex.: R$ 4.112,2000). A pergunta parece ter sido formulada para outro documento. | CA52: 2 | CB52: 2 | CC52: 2 | CD52: 2 | CE52: 2 | CF52: 2 | CG52: 2 | CH52: Não | CI52: Não | CJ52: Não | DA52: Cláusula 4.11 ausente no documento fornecido. | DC52: 2 | DD52: 2 | DE52: 2 | DF52: 2 | DG52: 2 | DH52: 2 | DI52: 2 | DJ52: Não | DK52: Não | DL52: Não | DO52: Item não aplicável ou não especificado na estrutura do relatório. | DQ52: 2 | DR52: 2 | DS52: 2 | DT52: 2 | DU52: 2 | DV52: 2 | DW52: 2 | DX52: Não | DY52: Não | DZ52: Não
A53: 12 | B53: P17 | C53: {=IFERROR(INDEX(DOCUMENTOS!$E:$E,MATCH($A53,DOCUMENTOS!$A:$A,0)),"")} | D53: {=IFERROR(INDEX('BANCO DE PERGUNTAS'!$D:$D,MATCH($B53,'BANCO DE PERGUNTAS'!$A:$A,0)),"")} -> Existem informações aparentemente inconsistentes dentro do documento? | E53: {=IFERROR(INDEX('BANCO DE PERGUNTAS'!$B:$B,MATCH($B53,'BANCO DE PERGUNTAS'!$A:$A,0)),"")} -> Identificação de Inconsistências | F53: {=IFERROR(INDEX('BANCO DE PERGUNTAS'!$H:$H,MATCH($B53,'BANCO DE PERGUNTAS'!$A:$A,0)),"")} -> 4 | U53: Sim, há aparentes inconsistências de apresentação a verificar: o critério de preço excessivo é descrito como superior a 30% da média, mas todas as referências são marcadas VÁLIDO; o mapa associa a ROSCH R$ 5,00 e à BRASIDAS R$ 2.829,00, embora suas propostas finais sejam R$ 3,70 e R$ 2.728,99. O memorial mostra que R$ 5,00 e R$ 2.829,00 são medianas, portanto não há erro aritmético demonstrado nessas diferenças. (PDF, pp. 4, 19 e 21–27.) | W53: 2 | X53: 1 | Y53: 1 | Z53: 2 | AA53: 2 | AB53: 1 | AC53: 2 | AD53: Não | AE53: Não | AF53: Não | AI53: Não foi identificada divergência aritmética evidente nos três valores estimados e no valor global. O resumo e o relatório detalhado registram horários de geração diferentes (09h25min10s e 09h23min33s) e códigos de validação distintos; convém confirmar qual versão deve instruir o processo. | AK53: 2 | AL53: 1 | AM53: 1 | AN53: 2 | AO53: 2 | AP53: 1 | AQ53: 2 | AR53: Não | AS53: Não | AT53: Não | BK53: Sim, pelo menos duas: (a) no Item 3 ("Equipamentos BDI"), a 3ª cotação usada tem como Objeto "Aquisição de materiais esportivos" — sem relação aparente com equipamentos de limpeza; (b) a descrição do próprio Item 3 aparece cortada no sistema: "(como lavadoras de alta pressão, aspiradores profissionais etc" — sem fechamento da frase/parênteses. | BM53: 2 | BN53: 2 | BO53: 2 | BP53: 2 | BQ53: 2 | BR53: 2 | BS53: 2 | BT53: Não | BU53: Não | BV53: Não | BY53: SIM. Principais inconsistências: (a) o Item 2 apresenta 3 preços, mas 2 deles vêm do MESMO pregão (Funasa, Pregão 90009/2026, UASG 255000, itens 11 e 12) e têm o MESMO fornecedor vencedor (CNPJ 51.722.124/0001-11), reduzindo a cesta a apenas 2 fontes efetivamente independentes; (b) ainda no Item 2, o primeiro preço (R$ 17.590,22) refere-se a "custos variáveis mensais" com unidade MÊS, enquanto os outros dois se referem a "Conjunto para limpeza" com unidade UNIDADE — grandezas distintas sendo somadas e promediadas; (c) o Item 3 usa como terceiro preço uma enceradeira adquirida em pregão cujo objeto é "Aquisição de materiais esportivos" (CMRJ); (d) o Item 1 mistura preços de áreas internas (IFPB/IFCE) com preço de áreas externas, 12 horas diurnas (SSP/SP); (e) na página resumo, a legenda do gráfico lista os itens em ordem distinta (1-Material, 2-Equipamentos, 3-Prestação) da ordem da tabela (1-Prestação, 2-Material, 3-Equipamentos); (f) o Termo de Homologação do Pregão 90009/2026 (Funasa) está anexado DUAS VEZES, integralmente, com 89 páginas cada. | CA53: 2 | CB53: 2 | CC53: 2 | CD53: 2 | CE53: 2 | CF53: 2 | CG53: 2 | CH53: Não | CI53: Não | CJ53: Não | DA53: Aparentemente não no cálculo principal, pois segue o saneamento estatístico da IN 65/2021. Porém, nota-se imensa discrepância nas licitações de referência, onde fornecedores deram lances irrisórios (R$ 0,20) ou absurdos (R$ 280.000,00) para o mesmo metro quadrado. | DC53: 2 | DD53: 1 | DE53: 1 | DF53: 2 | DG53: 2 | DH53: 1 | DI53: 2 | DJ53: Não | DK53: Não | DL53: Não | DO53: Não foram identificadas inconsistências aparentes nos cálculos apresentados, baseados na média aritmética/mediana conforme metodologia do STJ e IN 65/2021. | DQ53: 1 | DR53: 1 | DS53: 1 | DT53: 2 | DU53: 2 | DV53: 1 | DW53: 2 | DX53: Não | DY53: Não | DZ53: Não
A54: 12 | B54: P18 | C54: {=IFERROR(INDEX(DOCUMENTOS!$E:$E,MATCH($A54,DOCUMENTOS!$A:$A,0)),"")} | D54: {=IFERROR(INDEX('BANCO DE PERGUNTAS'!$D:$D,MATCH($B54,'BANCO DE PERGUNTAS'!$A:$A,0)),"")} -> Existem valores, datas, números ou informações aparentemente incompatíveis? | E54: {=IFERROR(INDEX('BANCO DE PERGUNTAS'!$B:$B,MATCH($B54,'BANCO DE PERGUNTAS'!$A:$A,0)),"")} -> Identificação de Inconsistências | F54: {=IFERROR(INDEX('BANCO DE PERGUNTAS'!$H:$H,MATCH($B54,'BANCO DE PERGUNTAS'!$A:$A,0)),"")} -> 4 | U54: Há aparente incompatibilidade de bases: o item 2 reúne custos variáveis mensais, em MÊS, com conjuntos de limpeza em Unidade; o item 3 reúne lavadora/secadora de pisos e enceradeiras; o item 1 reúne serviços com condições distintas de áreas e produtividade. A soma global combina 1 m² e duas unidades sem demonstrar anualização. As médias dos três itens e a soma R$ 23.700,41 são aritmeticamente coerentes após arredondamento. (PDF, pp. 1, 3–4, 9–10 e 18–22.) | W54: 2 | X54: 2 | Y54: 2 | Z54: 2 | AA54: 2 | AB54: 2 | AC54: 2 | AD54: Não | AE54: Não | AF54: Não | AI54: Não há incompatibilidade numérica demonstrada entre os preços estimados e o total de R$ 23.700,41, que corresponde à soma dos três itens para quantidade 1. O total não equivale ao valor anual do objeto; as quantidades anuais aparecem no mapa comparativo relacionado, não neste relatório. As duas partes do relatório têm horários e códigos de validação diferentes. | AK54: 2 | AL54: 1 | AM54: 1 | AN54: 2 | AO54: 2 | AP54: 1 | AQ54: 2 | AR54: Não | AS54: Não | AT54: Não | BK54: A coluna "Percentual" aparece vazia ("-") nos 3 itens, enquanto a coluna "% Valor Global" está preenchida (0%; 85,4%; 14,6%) — possível campo não utilizado no cadastro. Não foram encontradas inconsistências aritméticas: a soma dos 3 itens (R$ 4,97 + R$ 20.231,97 + R$ 3.463,47) confere exatamente com o Valor Global informado (R$ 23.700,41). | BM54: 2 | BN54: 2 | BO54: 2 | BP54: 2 | BQ54: 2 | BR54: 2 | BS54: 2 | BT54: Não | BU54: Não | BV54: Não | BY54: SIM. (a) Quantidade de 1 (uma) unidade/metro quadrado para todos os itens — não reflete a demanda real da UFJ, o que torna o Valor Global de R$ 23.700,41 uma soma de preços unitários heterogêneos, sem significado econômico; (b) mistura de unidades no Item 2 (MÊS x UNIDADE); (c) propostas iniciais discrepantes na série do Item 1 — R$ 50,00 e R$ 1.000,00 para item cujo valor final é de cerca de R$ 5,00 — sem qualquer justificativa de desconsideração; (d) no 3º preço do Item 1, adotou-se a mediana das propostas finais (R$ 5,00) enquanto o valor do vencedor foi de R$ 3,70, diferença de aproximadamente 35%; (e) os dois relatórios (resumido e detalhado) têm horários de geração diferentes (09:25:10 e 09:23:33) e códigos de validação distintos, embora apresentem os mesmos dados; (f) o Item 1 aparece com participação de 0% no Valor Global, o que é efeito da quantidade fictícia 1. | CA54: 2 | CB54: 2 | CC54: 2 | CD54: 2 | CE54: 2 | CF54: 2 | CG54: 2 | CH54: Não | CI54: Não | CJ54: Não | DA54: Sim, nas transcrições dos pregões de referência, há empresas desclassificadas por apresentarem propostas com preços inexequíveis (ex: R$ 0,20) ou excessivamente altos (R$ 1.000,00 por m²). | DC54: 2 | DD54: 2 | DE54: 2 | DF54: 2 | DG54: 2 | DH54: 2 | DI54: 2 | DJ54: Não | DK54: Não | DL54: Não | DO54: Não detectadas incompatibilidades evidentes entre valores e datas informadas. | DQ54: 2 | DR54: 1 | DS54: 1 | DT54: 2 | DU54: 2 | DV54: 1 | DW54: 2 | DX54: Não | DY54: Não | DZ54: Não
A55: 12 | B55: P19 | C55: {=IFERROR(INDEX(DOCUMENTOS!$E:$E,MATCH($A55,DOCUMENTOS!$A:$A,0)),"")} | D55: {=IFERROR(INDEX('BANCO DE PERGUNTAS'!$D:$D,MATCH($B55,'BANCO DE PERGUNTAS'!$A:$A,0)),"")} -> Existem informações relevantes ausentes? | E55: {=IFERROR(INDEX('BANCO DE PERGUNTAS'!$B:$B,MATCH($B55,'BANCO DE PERGUNTAS'!$A:$A,0)),"")} -> Identificação de Omissões | F55: {=IFERROR(INDEX('BANCO DE PERGUNTAS'!$H:$H,MATCH($B55,'BANCO DE PERGUNTAS'!$A:$A,0)),"")} -> 4 | U55: Sim. No relatório da UFJ, não consta no documento: número de seu processo, identificação e assinatura da equipe responsável, valor anual, dimensionamento total da área e do período de execução, composição/taxa do BDI e justificativa explícita da equivalência das referências heterogêneas. São ausências no arquivo, sem conclusão de que estejam ausentes de todo o processo. | W55: 2 | X55: 2 | Y55: 2 | Z55: 2 | AA55: 2 | AB55: 2 | AC55: 2 | AD55: Não | AE55: Não | AF55: Não | AI55: Não constam neste relatório o número do processo SEI, a quantidade anual prevista de cada item, o valor anual da contratação, a data de assinatura dos responsáveis ou da comissão e uma identificação formal numerada do documento. | AK55: 2 | AL55: 1 | AM55: 1 | AN55: 2 | AO55: 2 | AP55: 1 | AQ55: 2 | AR55: Não | AS55: Não | AT55: Não | BK55: Sim: não há número de processo/protocolo da UFJ vinculado; não há identificação do servidor responsável pela pesquisa (só consta o IP da estação); não há data de validade da pesquisa; e o relatório resumido não detalha se houve exclusão de preços inexequíveis/atípicos, conforme exige a metodologia da IN 65/2021. | BM55: 2 | BN55: 2 | BO55: 2 | BP55: 2 | BQ55: 2 | BR55: 2 | BS55: 2 | BT55: Não | BU55: Não | BV55: Não | BY55: SIM. Ausentes: identificação do agente ou da equipe responsável pela pesquisa (IN 65/2021, art. 3º, II); justificativas para a metodologia adotada e para a desconsideração de valores inexequíveis, inconsistentes ou excessivamente elevados (art. 3º, VI); número do processo administrativo da UFJ; quantitativos reais do objeto (área em m², nº de postos, quantidade de materiais e equipamentos); memória de cálculo do BDI, embora dois dos três itens o mencionem no título; prazo de vigência e data-base dos preços; valor mensal e valor total anual estimados; assinatura e data de aprovação; e análise crítica sobre a compatibilidade dos paradigmas com o objeto da UFJ. | CA55: 2 | CB55: 2 | CC55: 2 | CD55: 2 | CE55: 2 | CF55: 2 | CG55: 2 | CH55: Não | CI55: Não | CJ55: Não | DA55: Sim. Faltam as assinaturas do servidor responsável pela pesquisa e a indicação explícita do Termo de Referência ou número do processo administrativo da UFJ no relatório principal. | DC55: 2 | DD55: 1 | DE55: 2 | DF55: 2 | DG55: 2 | DH55: 1 | DI55: 2 | DJ55: Não | DK55: Não | DL55: Não | DO55: Algumas descrições de fabricantes e marcas constam como 'não informado', padrão para relatórios de cotação pública. | DQ55: 1 | DR55: 1 | DS55: 1 | DT55: 2 | DU55: 2 | DV55: 1 | DW55: 2 | DX55: Não | DY55: Não | DZ55: Não
A56: 12 | B56: P20 | C56: {=IFERROR(INDEX(DOCUMENTOS!$E:$E,MATCH($A56,DOCUMENTOS!$A:$A,0)),"")} | D56: {=IFERROR(INDEX('BANCO DE PERGUNTAS'!$D:$D,MATCH($B56,'BANCO DE PERGUNTAS'!$A:$A,0)),"")} -> Identifique possíveis erros materiais no documento. | E56: {=IFERROR(INDEX('BANCO DE PERGUNTAS'!$B:$B,MATCH($B56,'BANCO DE PERGUNTAS'!$A:$A,0)),"")} -> Detecção de Erros | F56: {=IFERROR(INDEX('BANCO DE PERGUNTAS'!$H:$H,MATCH($B56,'BANCO DE PERGUNTAS'!$A:$A,0)),"")} -> 4 | U56: Possíveis erros materiais: redação do limite de preços excessivos como superiores a 30% da média, a esclarecer; descrição do item 3 iniciada por parêntese e sem fechamento, '(como lavadoras de alta pressão, aspiradores profissionais etc'; uso do código 25194 nos três itens, inclusive materiais e equipamentos, a conferir. A associação de medianas a fornecedores vencedores no mapa também merece ajuste de identificação. Não foi constatado erro nas médias finais ou na soma global. (PDF, pp. 18 e 21–22.) | W56: 2 | X56: 2 | Y56: 2 | Z56: 2 | AA56: 2 | AB56: 2 | AC56: 2 | AD56: Não | AE56: Não | AF56: Não | AI56: Não é possível confirmar erro material apenas com o relatório. Recomenda-se conferir a divergência de horário/código de validação entre o resumo e o relatório detalhado e confirmar a vinculação do arquivo ao processo correto. | AK56: 1 | AL56: 1 | AM56: 1 | AN56: 2 | AO56: 2 | AP56: 1 | AQ56: 2 | AR56: Não | AS56: Não | AT56: Não | BK56: A descrição do Item 3 está truncada ("...aspiradores profissionais etc" sem fechar a frase), sugerindo erro de digitação/corte no cadastro do item no sistema Banco de Preços. | BM56: 2 | BN56: 1 | BO56: 1 | BP56: 2 | BQ56: 2 | BR56: 1 | BS56: 2 | BT56: Não | BU56: Não | BV56: Não | BY56: (a) Descrição do Item 1 truncada, encerrando com "...Universidade Federal de Jataí (UFJ),"; (b) descrição do Item 3 truncada e iniciada por parêntese sem abertura de frase: "(como lavadoras de alta pressão, aspiradores profissionais etc"; (c) descrição do Item 2 lançada de forma informal e com erro de grafia: "Materiais pra limpeza"; (d) erro de grafia "Multifunçional" na descrição CatMat reproduzida; (e) coluna "Observação" em branco nos três itens; (f) inversão da ordem dos itens na legenda do gráfico da página resumo; (g) duplicação integral de 89 páginas do Termo de Homologação do Pregão 90009/2026; (h) o título da cotação identifica uma empresa ("EMPRESA PRISMA 2026"), o que é impróprio para uma pesquisa de preços que deve ser referenciada ao objeto e ao processo. | CA56: 2 | CB56: 2 | CC56: 2 | CD56: 2 | CE56: 2 | CF56: 2 | CG56: 2 | CH56: Não | CI56: Não | CJ56: Não | DA56: Não foram identificados erros matemáticos nos cálculos do relatório, já que as médias e medianas estão detalhadamente justificadas no "Memorial de Cálculo" e mapas comparativos. | DC56: 1 | DD56: 1 | DE56: 1 | DF56: 2 | DG56: 2 | DH56: 1 | DI56: 2 | DJ56: Não | DK56: Não | DL56: Sim | DM56: Omissão | DO56: Nenhum erro material evidente identificado na compilação do relatório. | DQ56: 1 | DR56: 1 | DS56: 1 | DT56: 2 | DU56: 2 | DV56: 1 | DW56: 2 | DX56: Não | DY56: Não | DZ56: Sim | EA56: Omissão
A57: 12 | B57: P21 | C57: {=IFERROR(INDEX(DOCUMENTOS!$E:$E,MATCH($A57,DOCUMENTOS!$A:$A,0)),"")} | D57: {=IFERROR(INDEX('BANCO DE PERGUNTAS'!$D:$D,MATCH($B57,'BANCO DE PERGUNTAS'!$A:$A,0)),"")} -> Existem informações que deveriam ser verificadas por um servidor antes da utilização do documento? | E57: {=IFERROR(INDEX('BANCO DE PERGUNTAS'!$B:$B,MATCH($B57,'BANCO DE PERGUNTAS'!$A:$A,0)),"")} -> Análise de Risco | F57: {=IFERROR(INDEX('BANCO DE PERGUNTAS'!$H:$H,MATCH($B57,'BANCO DE PERGUNTAS'!$A:$A,0)),"")} -> 4 | U57: Sim. Verificar a equivalência de objetos, unidades, periodicidades, áreas e produtividades; distinguir mediana de propostas finais do preço efetivamente vencedor; conferir o critério de 30%, o código 25194, a composição do BDI, o dimensionamento da UFJ e a vinculação ao seu processo. As referências e os cálculos constam nas pp. 3–27. | W57: 2 | X57: 2 | Y57: 2 | Z57: 2 | AA57: 2 | AB57: 2 | AC57: 2 | AD57: Não | AE57: Não | AF57: Não | AI57: Sim. Confirmar a autenticidade/versão pelo código de validação, a vinculação ao processo, a comparabilidade das fontes com o objeto, os valores médios selecionados e a aplicação das quantidades corretas para chegar ao valor anual. | AK57: 2 | AL57: 2 | AM57: 2 | AN57: 2 | AO57: 2 | AP57: 2 | AQ57: 2 | AR57: Não | AS57: Não | AT57: Não | BK57: Sim: (a) confirmar se a cotação do Item 3 originada de "Aquisição de materiais esportivos" é de fato comparável ao equipamento pretendido; (b) confirmar se a cotação 1 do Item 2 (oriunda de contrato de manutenção de velório/cemitério) é um parâmetro válido; (c) confirmar se houve exclusão de preços inexequíveis conforme a IN 65/2021 antes de aceitar a média; (d) validar o Valor Global antes de usá-lo como estimativa oficial. | BM57: 2 | BN57: 2 | BO57: 2 | BP57: 2 | BQ57: 2 | BR57: 2 | BS57: 2 | BT57: Não | BU57: Não | BV57: Não | BY57: SIM. Devem ser verificados por servidor antes do uso: a compatibilidade de cada preço-fonte com o objeto efetivamente pretendido pela UFJ (especialmente o Item 3, oriundo de pregão de materiais esportivos, e o Item 1, que mistura áreas internas e externas); a independência das fontes do Item 2 (dois preços do mesmo pregão e do mesmo fornecedor); a validade e a vigência dos links do PNCP e do Compras.gov.br; a aderência dos quantitativos reais, já que a planilha usa quantidade 1; a composição e o percentual de BDI, não demonstrados; a suficiência da fundamentação exclusivamente no inciso I do art. 5º da IN 65/2021; e a inclusão, no processo, da identificação e da assinatura do agente responsável pela pesquisa. | CA57: 2 | CB57: 2 | CC57: 2 | CD57: 2 | CE57: 2 | CF57: 2 | CG57: 2 | CH57: Não | CI57: Não | CJ57: Não | DA57: Sim. Deve-se verificar se os itens paradigmas encontrados no Banco de Preços (as contratações de outros órgãos) possuem quantitativos, convenções coletivas e exigências técnicas idênticas ao Termo de Referência da UFJ. | DC57: 2 | DD57: 2 | DE57: 2 | DF57: 2 | DG57: 2 | DH57: 2 | DI57: 2 | DJ57: Não | DK57: Não | DL57: Não | DO57: Sim, o servidor deve verificar a validade das atas e a compatibilidade das especificações dos itens com o Termo de Referência da unidade. | DQ57: 2 | DR57: 1 | DS57: 2 | DT57: 1 | DU57: 2 | DV57: 2 | DW57: 2 | DX57: Não | DY57: Não | DZ57: Não
A58: 12 | B58: P22 | C58: {=IFERROR(INDEX(DOCUMENTOS!$E:$E,MATCH($A58,DOCUMENTOS!$A:$A,0)),"")} | D58: {=IFERROR(INDEX('BANCO DE PERGUNTAS'!$D:$D,MATCH($B58,'BANCO DE PERGUNTAS'!$A:$A,0)),"")} -> Existem elementos que indiquem possível desconformidade com os próprios requisitos apresentados no documento? | E58: {=IFERROR(INDEX('BANCO DE PERGUNTAS'!$B:$B,MATCH($B58,'BANCO DE PERGUNTAS'!$A:$A,0)),"")} -> Conformidade Documental | F58: {=IFERROR(INDEX('BANCO DE PERGUNTAS'!$H:$H,MATCH($B58,'BANCO DE PERGUNTAS'!$A:$A,0)),"")} -> 4 | U58: Há indício de desconformidade interna na redação do critério de preços excessivos: a leitura literal de superiores a 30% da média é incompatível com a classificação VÁLIDO de todas as cotações. O limite efetivamente pretendido não está esclarecido. A média aritmética declarada é compatível com os três preços selecionados em cada item; o uso de medianas para formar esses preços está demonstrado no memorial. (PDF, pp. 21–27.) | W58: 2 | X58: 1 | Y58: 1 | Z58: 2 | AA58: 2 | AB58: 1 | AC58: 2 | AD58: Não | AE58: Não | AF58: Não | AI58: O relatório declara conformidade com a IN nº 65/2021 e informa a média aritmética e as fontes consultadas. Não foi identificada, apenas pelo texto, desconformidade inequívoca com esses critérios; a adequação das fontes e da formação do valor deve ser conferida no processo. | AK58: 2 | AL58: 2 | AM58: 2 | AN58: 2 | AO58: 2 | AP58: 2 | AQ58: 2 | AR58: Não | AS58: Não | AT58: Não | BK58: Sim: para os Itens 2 e 3, ao menos uma das três referências de preço usadas no cálculo da média tem objeto de contratação diverso do item pesquisado (ex.: materiais esportivos para "Equipamentos BDI"), o que pode não atender ao requisito de pesquisa ampla e efetivamente comparável exigido pela IN 65/2021/Lei 14.133/2021. | BM58: 2 | BN58: 2 | BO58: 2 | BP58: 2 | BQ58: 2 | BR58: 2 | BS58: 2 | BT58: Não | BU58: Não | BV58: Não | BY58: SIM. O relatório declara conformidade com a IN SEGES/ME nº 65/2021 e com a Lei 14.133/2021, mas: (a) não identifica o agente ou a equipe responsável pela pesquisa, exigência do art. 3º, II; (b) não apresenta justificativas para a metodologia nem para a desconsideração de valores inexequíveis, inconsistentes ou excessivamente elevados, exigência do art. 3º, VI, embora existam na série valores como R$ 50,00 e R$ 1.000,00 para item de aproximadamente R$ 5,00; (c) no Item 2, dois dos três preços vêm do mesmo pregão e do mesmo fornecedor vencedor, o que fragiliza a exigência de cesta de, no mínimo, três preços de fontes idôneas e distintas (art. 6º); (d) o art. 5º condiciona o uso de contratações similares à similaridade do objeto, requisito questionável no Item 3 (enceradeira adquirida em pregão de materiais esportivos) e no Item 1 (áreas externas x internas). | CA58: 2 | CB58: 2 | CC58: 2 | CD58: 2 | CE58: 2 | CF58: 2 | CG58: 2 | CH58: Não | CI58: Não | CJ58: Não | DA58: Não de forma evidente. O sistema aplicou os filtros estatísticos da IN 65/2021, excluindo valores 30% superiores ou 70% inferiores à média. | DC58: 2 | DD58: 1 | DE58: 1 | DF58: 2 | DG58: 2 | DH58: 1 | DI58: 2 | DJ58: Não | DK58: Não | DL58: Não | DO58: Não há elementos de desconformidade com os requisitos da IN 65/2021 declarados no documento. | DQ58: 2 | DR58: 1 | DS58: 1 | DT58: 2 | DU58: 2 | DV58: 1 | DW58: 2 | DX58: Não | DY58: Não | DZ58: Não
A59: 12 | B59: P23 | C59: {=IFERROR(INDEX(DOCUMENTOS!$E:$E,MATCH($A59,DOCUMENTOS!$A:$A,0)),"")} | D59: {=IFERROR(INDEX('BANCO DE PERGUNTAS'!$D:$D,MATCH($B59,'BANCO DE PERGUNTAS'!$A:$A,0)),"")} -> Quais requisitos estão explicitamente presentes? | E59: {=IFERROR(INDEX('BANCO DE PERGUNTAS'!$B:$B,MATCH($B59,'BANCO DE PERGUNTAS'!$A:$A,0)),"")} -> Conformidade Documental | F59: {=IFERROR(INDEX('BANCO DE PERGUNTAS'!$H:$H,MATCH($B59,'BANCO DE PERGUNTAS'!$A:$A,0)),"")} -> 2 | U59: Estão explícitos: serviço continuado de limpeza, conservação e asseio com mão de obra, insumos, máquinas e equipamentos; três referências por item; quantidades de 1 m² para serviços e 1 unidade para cada um dos outros itens; média aritmética; identificação de fontes e datas; referências à IN 65/2021, art. 3º, V, e art. 5º, I; critérios estatísticos de 30% e 70% e classificação de validade. As especificações técnicas detalhadas de equipamentos e exigências das atas referem-se às contratações pesquisadas. (PDF, pp. 1–3, 18 e 21–27.) | W59: 2 | X59: 2 | Y59: 2 | Z59: 2 | AA59: 2 | AB59: 2 | AC59: 2 | AD59: Não | AE59: Não | AF59: Não | AI59: O relatório informa pesquisa realizada entre 24/08/2026 07h41min13s e 09h00min20s, adoção da média aritmética dos preços selecionados, preços de referência por item, fontes/registros consultados e referência à IN nº 65/2021 (arts. 3º, inciso V, e 5º, inciso I). | AK59: 2 | AL59: 1 | AM59: 1 | AN59: 2 | AO59: 2 | AP59: 1 | AQ59: 2 | AR59: Não | AS59: Não | AT59: Não | BK59: Estão explícitos: base legal (IN SEGES/ME nº 65/2021, art. 3º e art. 5º, Inc. I; Lei nº 14.133/2021); método matemático declarado (Média Aritmética); mínimo de 3 preços por item; identificação de cada fonte (CNPJ, órgão, modalidade, data, objeto, fonte/link). | BM59: 2 | BN59: 1 | BO59: 1 | BP59: 2 | BQ59: 2 | BR59: 1 | BS59: 2 | BT59: Não | BU59: Não | BV59: Não | BY59: Explicitamente presentes: (a) declaração de conformidade com a IN nº 65, de 07/07/2021, e com a Lei nº 14.133/2021; (b) indicação do método matemático aplicado — média aritmética dos preços obtidos —, com citação do art. 3º, inc. V, da IN 65/2021; (c) fundamento de cada preço no art. 5º, inc. I, da IN 65/2021 (contratações similares de outros entes públicos), com adoção da mediana das propostas finais; (d) caracterização das fontes consultadas, em "Extrato de fontes utilizadas" — Compras.gov.br e PNCP, com data e hora de acesso; (e) série de preços coletados, com CNPJ, órgão, objeto, modalidade, data de homologação, quantidade, unidade e UF; (f) Anexo 1 – Memorial de Cálculo, demonstrando aritmeticamente cada valor; (g) código de validação eletrônica do relatório; (h) Termos de Homologação das licitações-fonte, como documentação comprobatória. | CA59: 2 | CB59: 2 | CC59: 2 | CD59: 2 | CE59: 2 | CF59: 2 | CG59: 2 | CH59: Não | CI59: Não | CJ59: Não | DA59: Atendimento à Instrução Normativa Nº 65 de 07 de Julho de 2021 (Lei nº 14.133), aplicando o método matemático de Média Aritmética. | DC59: 2 | DD59: 1 | DE59: 1 | DF59: 2 | DG59: 2 | DH59: 1 | DI59: 2 | DJ59: Não | DK59: Sim | DL59: Não | DO59: Observância à Lei nº 14.133/2021, Instrução Normativa nº 65/2021 e aplicação de critérios estatísticos (média/mediana). | DQ59: 2 | DR59: 2 | DS59: 2 | DT59: 2 | DU59: 2 | DV59: 2 | DW59: 2 | DX59: Não | DY59: Não | DZ59: Não
A60: 12 | B60: P24 | C60: {=IFERROR(INDEX(DOCUMENTOS!$E:$E,MATCH($A60,DOCUMENTOS!$A:$A,0)),"")} | D60: {=IFERROR(INDEX('BANCO DE PERGUNTAS'!$D:$D,MATCH($B60,'BANCO DE PERGUNTAS'!$A:$A,0)),"")} -> Quais informações necessárias parecem estar ausentes? | E60: {=IFERROR(INDEX('BANCO DE PERGUNTAS'!$B:$B,MATCH($B60,'BANCO DE PERGUNTAS'!$A:$A,0)),"")} -> Identificação de Omissões | F60: {=IFERROR(INDEX('BANCO DE PERGUNTAS'!$H:$H,MATCH($B60,'BANCO DE PERGUNTAS'!$A:$A,0)),"")} -> 4 | U60: Para transpor os resultados à contratação da UFJ, não consta no documento a demonstração de equivalência técnica e temporal entre as cotações, a composição e taxa do BDI, a área e os quantitativos reais da contratação, a periodicidade dos custos, a memória do valor anual e a identificação/assinatura dos responsáveis pela pesquisa. A necessidade de verificação decorre das diferenças observáveis entre as referências. | W60: 2 | X60: 1 | Y60: 2 | Z60: 2 | AA60: 2 | AB60: 1 | AC60: 2 | AD60: Não | AE60: Não | AF60: Não | AI60: Para apurar o valor total anual a partir deste relatório, faltam nele as quantidades anuais de cada item e a memória de cálculo anual. Também não constam o número SEI do processo, a identificação formal numerada do documento e as assinaturas dos responsáveis. | AK60: 2 | AL60: 2 | AM60: 2 | AN60: 2 | AO60: 2 | AP60: 2 | AQ60: 2 | AR60: Não | AS60: Não | AT60: Não | BK60: As mesmas da pergunta 19: identificação/nº de processo da UFJ, responsável técnico pela pesquisa, data de validade, e evidência de tratamento de preços inexequíveis/discrepantes antes do cálculo da média. | BM60: 2 | BN60: 1 | BO60: 1 | BP60: 2 | BQ60: 2 | BR60: 1 | BS60: 2 | BT60: Não | BU60: Não | BV60: Não | BY60: Identificação e assinatura do agente ou da equipe de planejamento responsável pela pesquisa; justificativa da metodologia e do tratamento dado a valores atípicos; número do processo administrativo da UFJ; quantitativos reais do objeto e a consequente estimativa mensal e anual da contratação; memória de composição do BDI aplicado aos itens 2 e 3; descrições completas e não truncadas dos itens; data-base e prazo de validade dos preços; análise de similaridade entre os paradigmas e o objeto da UFJ; e justificativa para o uso de apenas uma das fontes previstas no art. 5º da IN 65/2021. | CA60: 2 | CB60: 2 | CC60: 2 | CD60: 2 | CE60: 2 | CF60: 2 | CG60: 2 | CH60: Não | CI60: Não | CJ60: Não | DA60: Número do processo administrativo interno da UFJ e assinatura do pesquisador que emitiu o relatório no sistema. | DC60: 2 | DD60: 2 | DE60: 2 | DF60: 2 | DG60: 2 | DH60: 2 | DI60: 2 | DJ60: Não | DK60: Não | DL60: Não | DO60: Detalhamento pormenorizado de todas as propostas individuais de alguns fornecedores cujos links remetem a anexos externos. | DQ60: 2 | DR60: 1 | DS60: 1 | DT60: 2 | DU60: 2 | DV60: 1 | DW60: 2 | DX60: Não | DY60: Sim | DZ60: Não
A61: 12 | B61: P25 | C61: {=IFERROR(INDEX(DOCUMENTOS!$E:$E,MATCH($A61,DOCUMENTOS!$A:$A,0)),"")} | D61: {=IFERROR(INDEX('BANCO DE PERGUNTAS'!$D:$D,MATCH($B61,'BANCO DE PERGUNTAS'!$A:$A,0)),"")} -> Existem informações conflitantes com outro documento relacionado? | E61: {=IFERROR(INDEX('BANCO DE PERGUNTAS'!$B:$B,MATCH($B61,'BANCO DE PERGUNTAS'!$A:$A,0)),"")} -> Comparação | F61: {=IFERROR(INDEX('BANCO DE PERGUNTAS'!$H:$H,MATCH($B61,'BANCO DE PERGUNTAS'!$A:$A,0)),"")} -> 5 | U61: Entre o relatório e as peças anexas, as diferenças de valores identificadas não comprovam conflito: R$ 2.829,00 é a mediana da referência de equipamentos, enquanto R$ 2.728,99 é o valor vencedor da BRASIDAS; o memorial explica a diferença. A apresentação do mapa pode induzir à confusão entre esses conceitos. Conflito com outro documento da contratação da UFJ: não consta no documento, pois esse outro documento não foi fornecido. (PDF, pp. 19, 22, 27 e 254–259.) | W61: 2 | X61: 1 | Y61: 1 | Z61: 2 | AA61: 2 | AB61: 1 | AC61: 2 | AD61: Não | AE61: Não | AF61: Sim | AG61: Erro de interpretação | AI61: Não foi identificado conflito nos preços do Banco de Preços: R$ 4,97, R$ 20.231,97 e R$ 3.463,47 coincidem com o “Preço 02” do mapa comparativo. Os totais diferem porque o relatório soma uma unidade de cada item (R$ 23.700,41), enquanto o mapa aplica quantidades e combina esses preços com valores do contrato vigente para calcular médias e total anual. | AK61: 2 | AL61: 1 | AM61: 1 | AN61: 2 | AO61: 2 | AP61: 1 | AQ61: 2 | AR61: Não | AS61: Não | AT61: Sim | AU61: Erro de interpretação | BK61: Não é possível avaliar — nenhum outro documento foi enviado nesta consulta para comparação. | BM61: 2 | BN61: 2 | BO61: 2 | BP61: 2 | BQ61: 2 | BR61: 2 | BS61: 2 | BT61: Não | BU61: Não | BV61: Não | BY61: NÃO É POSSÍVEL AFIRMAR com base no material disponível: foi fornecido apenas este documento, sem o Estudo Técnico Preliminar, o Termo de Referência, o contrato original ou a planilha de custos da contratação remanescente, que seriam os documentos de cotejo natural. Internamente, há divergências entre as peças que compõem o próprio arquivo: o Relatório Resumido e o Relatório de Cotação foram gerados em horários distintos (09:25:10 e 09:23:33) e possuem códigos de validação diferentes, e há um Termo de Homologação anexado em duplicidade. Recomenda-se confrontar este relatório com o ETP/TR e com a planilha da contratação remanescente antes de qualquer decisão. | CA61: 2 | CB61: 2 | CC61: 2 | CD61: 2 | CE61: 2 | CF61: 2 | CG61: 2 | CH61: Não | CI61: Não | CJ61: Não | DA61: Apenas um documento foi fornecido (o relatório e seus anexos nativos), impossibilitando a comparação externa. | DC61: 2 | DD61: 2 | DE61: 2 | DF61: 2 | DG61: 2 | DH61: 2 | DI61: 2 | DJ61: Não | DK61: Não | DL61: Não | DO61: Não há confronto direto com outros documentos no escopo deste relatório isolado. | DQ61: 2 | DR61: 2 | DS61: 2 | DT61: 2 | DU61: 2 | DV61: 2 | DW61: 2 | DX61: Não | DY61: Não | DZ61: Não
A62: 12 | B62: P26 | C62: {=IFERROR(INDEX(DOCUMENTOS!$E:$E,MATCH($A62,DOCUMENTOS!$A:$A,0)),"")} | D62: {=IFERROR(INDEX('BANCO DE PERGUNTAS'!$D:$D,MATCH($B62,'BANCO DE PERGUNTAS'!$A:$A,0)),"")} -> Quais diferenças existem entre os documentos? | E62: {=IFERROR(INDEX('BANCO DE PERGUNTAS'!$B:$B,MATCH($B62,'BANCO DE PERGUNTAS'!$A:$A,0)),"")} -> Comparação | F62: {=IFERROR(INDEX('BANCO DE PERGUNTAS'!$H:$H,MATCH($B62,'BANCO DE PERGUNTAS'!$A:$A,0)),"")} -> 5 | U62: No próprio PDF, o relatório resumido apresenta três estimativas e o global; o detalhado apresenta fornecedores, fontes e critérios; o memorial demonstra medianas; as atas anexas registram propostas, lances, julgamento e homologação dos certames de referência. O resumido foi gerado às 09:25:10 e o detalhado às 09:23:33 em 24/08/2026. Diferenças com outro documento da contratação da UFJ: não consta no documento. | W62: 2 | X62: 1 | Y62: 1 | Z62: 2 | AA62: 2 | AB62: 1 | AC62: 2 | AD62: Não | AE62: Não | AF62: Sim | AG62: Erro de interpretação | AI62: O relatório detalha a pesquisa no Banco de Preços e os preços unitários estimados. O mapa comparativo adiciona o valor atualizado do contrato nº 113/2024, calcula a média entre esse preço e o preço do Banco de Preços, aplica 434.000 m² e 12 meses aos itens pertinentes e apresenta total anual de R$ 2.350.378,54. | AK62: 2 | AL62: 1 | AM62: 1 | AN62: 2 | AO62: 2 | AP62: 1 | AQ62: 2 | AR62: Não | AS62: Não | AT62: Sim | AU62: Erro de interpretação | BK62: Não aplicável — apenas um documento foi fornecido. | BM62: 2 | BN62: 2 | BO62: 2 | BP62: 2 | BQ62: 2 | BR62: 2 | BS62: 2 | BT62: Não | BU62: Não | BV62: Não | BY62: Entre as peças internas: (a) o Relatório Resumido (1 página) traz apenas o quadro-síntese dos 3 itens, o Valor Global e os gráficos, enquanto o Relatório de Cotação (22 páginas) traz o detalhamento completo de cada preço, com fornecedores, propostas e fontes; (b) diferem em horário de geração e código de validação; (c) a legenda do gráfico do resumo apresenta os itens em ordem invertida em relação à tabela. Entre os anexos: são 4 Termos de Homologação — Pregão 90006/2026 (SSP/SP, 46 páginas), Pregão 90009/2026 (Funasa, 89 páginas), o MESMO Pregão 90009/2026 repetido integralmente (89 páginas) e Pregão 90001/2026 (CMRJ, 8 páginas). A comparação com documentos externos do processo não pôde ser feita, pois não foram fornecidos. | CA62: 2 | CB62: 1 | CC62: 1 | CD62: 2 | CE62: 2 | CF62: 1 | CG62: 2 | CH62: Não | CI62: Não | CJ62: Sim | CK62: Erro de interpretação | DA62: O conjunto contém o relatório final da UFJ e os anexos que são as transcrições das fontes (Pregões da Secretaria de Segurança de SP e da Funasa). A diferença é que os anexos são a matéria-prima utilizada para extrair os preços que embasam o relatório final. | DC62: 2 | DD62: 1 | DE62: 1 | DF62: 2 | DG62: 2 | DH62: 1 | DI62: 2 | DJ62: Não | DK62: Não | DL62: Sim | DM62: Erro de interpretação | DO62: Não aplicável. | DQ62: 2 | DR62: 2 | DS62: 2 | DT62: 2 | DU62: 2 | DV62: 2 | DW62: 2 | DX62: Não | DY62: Não | DZ62: Não
A63: 12 | B63: P27 | C63: {=IFERROR(INDEX(DOCUMENTOS!$E:$E,MATCH($A63,DOCUMENTOS!$A:$A,0)),"")} | D63: {=IFERROR(INDEX('BANCO DE PERGUNTAS'!$D:$D,MATCH($B63,'BANCO DE PERGUNTAS'!$A:$A,0)),"")} -> Quais informações foram alteradas? | E63: {=IFERROR(INDEX('BANCO DE PERGUNTAS'!$B:$B,MATCH($B63,'BANCO DE PERGUNTAS'!$A:$A,0)),"")} -> Análise de Relações entre Informações | F63: {=IFERROR(INDEX('BANCO DE PERGUNTAS'!$H:$H,MATCH($B63,'BANCO DE PERGUNTAS'!$A:$A,0)),"")} -> 5 | U63: Alterações entre versões do relatório da UFJ: não consta no documento, pois não há histórico de versões. Nas propostas dos certames de referência, o memorial registra mudanças entre valores inicial e final: BRASIDAS de R$ 2.848,99 para R$ 2.728,99 e GRM Máquinas e Locações de R$ 2.848,99 para R$ 2.749,99. São alterações nas propostas pesquisadas, não no contrato da UFJ. (PDF, p. 27.) | W63: 2 | X63: 2 | Y63: 2 | Z63: 2 | AA63: 2 | AB63: 2 | AC63: 2 | AD63: Não | AE63: Não | AF63: Não | AI63: Não consta histórico de versões ou registro de alterações. A diferença entre os documentos reflete escopo e cálculo distintos; não permite afirmar que algum preço tenha sido alterado. | AK63: 2 | AL63: 2 | AM63: 2 | AN63: 2 | AO63: 2 | AP63: 2 | AQ63: 2 | AR63: Não | AS63: Não | AT63: Não | BK63: Não aplicável — não há versão anterior deste documento disponível para comparação. | BM63: 2 | BN63: 2 | BO63: 2 | BP63: 2 | BQ63: 2 | BR63: 2 | BS63: 2 | BT63: Não | BU63: Não | BV63: Não | BY63: NÃO É POSSÍVEL IDENTIFICAR ALTERAÇÕES. O documento não possui controle de versão, histórico de revisões, campo de "versão" ou marcas de alteração, e não foi fornecida versão anterior para cotejo. O único indício de retrabalho é a geração de duas peças em horários distintos no mesmo dia (09:23:33 e 09:25:10), com tokens de validação diferentes — o que é comportamento normal da ferramenta ao emitir relatórios distintos, não evidência de alteração de conteúdo. Eventual histórico de alterações deverá ser consultado no SEI. | CA63: 2 | CB63: 2 | CC63: 2 | CD63: 2 | CE63: 2 | CF63: 2 | CG63: 2 | CH63: Não | CI63: Não | CJ63: Não | DA63: Ao longo das transcrições dos pregões, as propostas iniciais de centenas de empresas foram alteradas na etapa de lances sucessivos até chegarem aos valores finais adjudicados. | DC63: 2 | DD63: 1 | DE63: 1 | DF63: 2 | DG63: 2 | DH63: 1 | DI63: 2 | DJ63: Não | DK63: Não | DL63: Sim | DM63: Erro de interpretação | DO63: Nenhuma informação foi alterada no relatório gerado pelo sistema. | DQ63: 2 | DR63: 2 | DS63: 2 | DT63: 2 | DU63: 2 | DV63: 2 | DW63: 2 | DX63: Não | DY63: Não | DZ63: Não
A64: 12 | B64: P28 | C64: {=IFERROR(INDEX(DOCUMENTOS!$E:$E,MATCH($A64,DOCUMENTOS!$A:$A,0)),"")} | D64: {=IFERROR(INDEX('BANCO DE PERGUNTAS'!$D:$D,MATCH($B64,'BANCO DE PERGUNTAS'!$A:$A,0)),"")} -> Identifique possíveis pontos de atenção administrativa. | E64: {=IFERROR(INDEX('BANCO DE PERGUNTAS'!$B:$B,MATCH($B64,'BANCO DE PERGUNTAS'!$A:$A,0)),"")} -> Análise de Risco | F64: {=IFERROR(INDEX('BANCO DE PERGUNTAS'!$H:$H,MATCH($B64,'BANCO DE PERGUNTAS'!$A:$A,0)),"")} -> 4 | U64: Pontos de atenção: comparabilidade de objetos e unidades; duas referências do item 2 provenientes de itens do mesmo Pregão 90009/2026 da Funasa; distinção entre medianas e preços vencedores; redação do limite estatístico; código 25194 nos três itens; ausência de composição do BDI e de dimensionamento anual. O global do relatório não está identificado como valor anual da contratação. (PDF, pp. 1, 9–17 e 21–27.) | W64: 2 | X64: 2 | Y64: 2 | Z64: 2 | AA64: 2 | AB64: 2 | AC64: 2 | AD64: Não | AE64: Não | AF64: Não | AI64: O relatório não informa quantidades anuais nem processo SEI; o valor global de R$ 23.700,41 usa quantidade 1 por item; resumo e relatório detalhado têm códigos de validação e horários de geração diferentes; é necessário confirmar se as fontes são comparáveis ao objeto e à especificação da contratação. | AK64: 2 | AL64: 1 | AM64: 1 | AN64: 2 | AO64: 2 | AP64: 1 | AQ64: 2 | AR64: Não | AS64: Não | AT64: Sim | AU64: Erro de interpretação | BK64: (1) Ausência de nº de processo/protocolo vinculado da UFJ; (2) referências de preço com objeto de contratação distinto do item cotado nos Itens 2 e 3; (3) descrição truncada no Item 3; (4) ausência de identificação do responsável/assinatura; (5) necessidade de checar a exclusão de preços atípicos conforme a metodologia da IN 65/2021. | BM64: 2 | BN64: 2 | BO64: 2 | BP64: 2 | BQ64: 2 | BR64: 2 | BS64: 2 | BT64: Não | BU64: Não | BV64: Não | BY64: (1) O Valor Global de R$ 23.700,41 não é o valor da contratação: resulta de quantidade 1 para cada item e não pode ser usado como estimativa contratual; (2) ausência de identificação e assinatura do responsável pela pesquisa; (3) ausência de justificativas metodológicas e de tratamento de valores atípicos; (4) fragilidade da cesta de preços do Item 2 (duas cotações do mesmo pregão e do mesmo fornecedor); (5) baixa similaridade de alguns paradigmas com o objeto (Item 3 oriundo de pregão de materiais esportivos; Item 1 mesclando áreas internas e externas); (6) BDI mencionado no título dos itens 2 e 3 sem qualquer memória de composição; (7) o título da cotação nomeia uma empresa específica ("EMPRESA PRISMA 2026"), o que pode sugerir direcionamento e deve ser corrigido para referência ao objeto/processo; (8) descrições de itens truncadas e informais; (9) duplicação de 89 páginas de anexo, onerando o processo; (10) uso de fonte única (inciso I do art. 5º), sem justificativa para não ampliação da pesquisa. | CA64: 2 | CB64: 2 | CC64: 2 | CD64: 2 | CE64: 2 | CF64: 2 | CG64: 2 | CH64: Não | CI64: Não | CJ64: Não | DA64: O alto valor do Item 2 (Material Sob Demanda - R$ 20.231,97 por unidade) exige atenção redobrada para certificar que a composição e o quantitativo do kit correspondem exatamente ao exigido pela UFJ. | DC64: 2 | DD64: 1 | DE64: 1 | DF64: 2 | DG64: 2 | DH64: 1 | DI64: 2 | DJ64: Não | DK64: Não | DL64: Sim | DM64: Erro de interpretação | DO64: Atenção à seleção adequada dos preços válidos e desclassificação de propostas inexequíveis ou excessivas conforme parâmetros estatísticos (30% e 70%). | DQ64: 2 | DR64: 1 | DS64: 1 | DT64: 2 | DU64: 2 | DV64: 1 | DW64: 2 | DX64: Não | DY64: Não | DZ64: Sim | EA64: Erro de interpretação
A65: 12 | B65: P29 | C65: {=IFERROR(INDEX(DOCUMENTOS!$E:$E,MATCH($A65,DOCUMENTOS!$A:$A,0)),"")} | D65: {=IFERROR(INDEX('BANCO DE PERGUNTAS'!$D:$D,MATCH($B65,'BANCO DE PERGUNTAS'!$A:$A,0)),"")} -> Quais informações deveriam ser verificadas antes de uma decisão administrativa? | E65: {=IFERROR(INDEX('BANCO DE PERGUNTAS'!$B:$B,MATCH($B65,'BANCO DE PERGUNTAS'!$A:$A,0)),"")} -> Análise de Risco | F65: {=IFERROR(INDEX('BANCO DE PERGUNTAS'!$H:$H,MATCH($B65,'BANCO DE PERGUNTAS'!$A:$A,0)),"")} -> 4 | U65: Antes de decidir, conferir a vinculação da pesquisa ao processo da UFJ, a identificação dos responsáveis, a adequação das especificações e quantidades, a normalização de unidades e períodos, a composição do BDI, a justificativa da seleção das referências e a interpretação dos limites estatísticos. Confirmar que o uso de medianas está compreendido e que R$ 23.700,41 não seja tratado como valor anual sem memória de cálculo. (PDF, pp. 1–27.) | W65: 2 | X65: 1 | Y65: 1 | Z65: 2 | AA65: 2 | AB65: 1 | AC65: 2 | AD65: Não | AE65: Sim | AF65: Não | AI65: Confirmar a versão autêntica do relatório e seu vínculo ao processo; validar as fontes e a comparabilidade dos itens; conferir os preços médios; confirmar quantidades anuais e a memória de cálculo que forma o total anual. | AK65: 2 | AL65: 1 | AM65: 1 | AN65: 2 | AO65: 2 | AP65: 1 | AQ65: 2 | AR65: Não | AS65: Sim | AT65: Não | BK65: Verificar: comparabilidade real das fontes de preço usadas nos Itens 2 e 3; correção do Valor Global antes de vinculá-lo ao processo de contratação; cumprimento do mínimo de 3 cotações válidas (Art. 5º, Inc. I, IN 65/2021); e se este relatório é a versão final ou preliminar a ser anexada ao ETP/Termo de Referência. | BM65: 2 | BN65: 1 | BO65: 1 | BP65: 2 | BQ65: 2 | BR65: 1 | BS65: 2 | BT65: Não | BU65: Não | BV65: Sim | BW65: Erro de interpretação | BY65: O processo administrativo e o ETP/TR a que este relatório se vincula; os quantitativos reais do objeto e a conversão dos preços unitários em valor mensal e anual; a similaridade entre cada preço-fonte e o objeto da UFJ; a independência e a idoneidade das fontes do Item 2; a vigência dos preços (todos de 2026, dentro do prazo de 1 ano do art. 5º, §1º, da IN 65/2021, o que deve ser reconfirmado na data da decisão); a composição do BDI; a existência de justificativa escrita para a metodologia e para a manutenção de valores atípicos na série; a identificação e a assinatura do agente responsável; e a compatibilidade do valor estimado com a disponibilidade orçamentária e com a planilha da contratação remanescente. | CA65: 2 | CB65: 1 | CC65: 1 | CD65: 2 | CE65: 2 | CF65: 1 | CG65: 2 | CH65: Não | CI65: Não | CJ65: Sim | CK65: Erro de interpretação | DA65: A conformidade e equivalência das especificações técnicas dos serviços e produtos cotados em outros órgãos em relação às necessidades reais da Universidade Federal de Jataí. | DC65: 2 | DD65: 1 | DE65: 1 | DF65: 2 | DG65: 2 | DH65: 1 | DI65: 2 | DJ65: Não | DK65: Sim | DL65: Não | DO65: A verificação da conformidade das propostas obtidas nas compras governamentais com a realidade dos serviços pretendidos pela instituição. | DQ65: 2 | DR65: 1 | DS65: 1 | DT65: 2 | DU65: 2 | DV65: 1 | DW65: 2 | DX65: Não | DY65: Sim | DZ65: Não
A66: 12 | B66: P30 | C66: {=IFERROR(INDEX(DOCUMENTOS!$E:$E,MATCH($A66,DOCUMENTOS!$A:$A,0)),"")} | D66: {=IFERROR(INDEX('BANCO DE PERGUNTAS'!$D:$D,MATCH($B66,'BANCO DE PERGUNTAS'!$A:$A,0)),"")} -> Identifique situações que possam representar risco administrativo. | E66: {=IFERROR(INDEX('BANCO DE PERGUNTAS'!$B:$B,MATCH($B66,'BANCO DE PERGUNTAS'!$A:$A,0)),"")} -> Análise de Risco | F66: {=IFERROR(INDEX('BANCO DE PERGUNTAS'!$H:$H,MATCH($B66,'BANCO DE PERGUNTAS'!$A:$A,0)),"")} -> 4 | U66: Riscos administrativos inferidos do conteúdo: estimativa inadequada por combinação de objetos e períodos não equivalentes; uso do global como total anual sem base; atribuição de medianas como se fossem preços vencedores; aplicação equivocada do limite de 30%; possível duplicidade de custos ao combinar serviço com insumos/equipamentos incluídos e itens separados de materiais/equipamentos. São riscos a verificar, não constatações de dano ou irregularidade consumada. (PDF, pp. 1, 3, 9–10 e 18–27.) | W66: 2 | X66: 2 | Y66: 2 | Z66: 2 | AA66: 2 | AB66: 2 | AC66: 2 | AD66: Não | AE66: Não | AF66: Não | AI66: Usar R$ 23.700,41 como se fosse o valor anual, embora seja a soma de uma unidade de cada item; adotar fontes que não sejam comparáveis ao objeto; ou instruir a decisão com versão/código de validação diferente do documento autenticado. São riscos de uso e conferência, não irregularidades comprovadas. | AK66: 2 | AL66: 2 | AM66: 2 | AN66: 2 | AO66: 2 | AP66: 2 | AQ66: 2 | AR66: Não | AS66: Não | AT66: Não | BK66: Risco de questionamento em auditoria (TCU/CGU/Controle Interno) por utilizar, como parâmetro de preço do Item 3 ("Equipamentos BDI"), uma cotação oriunda de processo de "Aquisição de materiais esportivos" — objeto sem relação direta —, o que pode exigir revisão do valor estimado antes do prosseguimento da contratação. | BM66: 2 | BN66: 2 | BO66: 2 | BP66: 2 | BQ66: 2 | BR66: 2 | BS66: 2 | BT66: Não | BU66: Não | BV66: Não | BY66: (a) Risco de estimativa inadequada e de sobrepreço ou de preço inexequível, pela agregação de preços de objetos e unidades não homogêneos e pelo uso de quantidade fictícia 1; (b) risco de nulidade ou de glosa por descumprimento do art. 3º, II e VI, da IN 65/2021 (ausência de identificação do responsável e de justificativas); (c) risco de questionamento por órgãos de controle quanto à cesta de preços do Item 2, com duas cotações do mesmo certame e do mesmo fornecedor; (d) risco de impugnação por direcionamento, dado o título da cotação nomear empresa específica; (e) risco de responsabilização do agente que utilizar o Valor Global como valor da contratação; (f) risco de repactuação ou de aditivo indevido por ausência de memória de BDI; (g) risco de insegurança probatória se os links das fontes deixarem de estar acessíveis, já que não há cópia integral de todos os editais; (h) risco de atraso e retrabalho caso o documento precise ser refeito após a publicação do edital. | CA66: 2 | CB66: 2 | CC66: 2 | CD66: 2 | CE66: 2 | CF66: 2 | CG66: 2 | CH66: Não | CI66: Não | CJ66: Não | DA66: Utilizar como preço base cotações cujos editais originários possuam especificações, produtividade ou regimes de trabalho divergentes dos da UFJ, o que pode levar a um orçamento inexequível ou a sobrepreço. | DC66: 2 | DD66: 1 | DE66: 1 | DF66: 2 | DG66: 2 | DH66: 1 | DI66: 2 | DJ66: Não | DK66: Sim | DL66: Não | DO66: Risco de utilização de preços inexequíveis ou que não reflitam o mercado local da unidade contratante. | DQ66: 2 | DR66: 1 | DS66: 1 | DT66: 2 | DU66: 2 | DV66: 1 | DW66: 2 | DX66: Não | DY66: Sim | DZ66: Não
A67: 12 | B67: P31 | C67: {=IFERROR(INDEX(DOCUMENTOS!$E:$E,MATCH($A67,DOCUMENTOS!$A:$A,0)),"")} | D67: {=IFERROR(INDEX('BANCO DE PERGUNTAS'!$D:$D,MATCH($B67,'BANCO DE PERGUNTAS'!$A:$A,0)),"")} -> Resuma o documento em até cinco pontos objetivos. | E67: {=IFERROR(INDEX('BANCO DE PERGUNTAS'!$B:$B,MATCH($B67,'BANCO DE PERGUNTAS'!$A:$A,0)),"")} -> Síntese | F67: {=IFERROR(INDEX('BANCO DE PERGUNTAS'!$H:$H,MATCH($B67,'BANCO DE PERGUNTAS'!$A:$A,0)),"")} -> 3 | U67: 1) Pesquisa EMPRESA PRISMA 2026 para serviços de limpeza da UFJ, realizada em 24/08/2026. 2) Três itens, com três referências cada, provenientes de PNCP e Compras.gov.br. 3) Médias: R$ 4,97/m², R$ 20.231,97 para materiais e R$ 3.463,47 para equipamentos. 4) Global de R$ 23.700,41, sem qualificação como anual. 5) Arquivo reúne detalhamento, mapa, memorial e atas; equivalência das referências e redação do critério estatístico merecem verificação. | W67: 2 | X67: 2 | Y67: 2 | Z67: 2 | AA67: 2 | AB67: 2 | AC67: 2 | AD67: Não | AE67: Não | AF67: Não | AI67: 1) Pesquisa de preços da UFJ para limpeza, materiais sob demanda e equipamentos. 2) Pesquisa feita em 24/08/2026. 3) Método declarado: média aritmética dos preços selecionados. 4) Estimativas unitárias: R$ 4,97, R$ 20.231,97 e R$ 3.463,47. 5) Total do resumo: R$ 23.700,41 para uma unidade de cada item; não é valor anual. | AK67: 2 | AL67: 2 | AM67: 2 | AN67: 2 | AO67: 2 | AP67: 2 | AQ67: 2 | AR67: Não | AS67: Não | AT67: Não | BK67: (1) Pesquisa de preços da UFJ para 3 itens (limpeza, material sob demanda + BDI, equipamentos BDI); (2) Valor Global de R$ 23.700,41; (3) metodologia: média aritmética de 3 cotações por item, conforme IN 65/2021; (4) documento gerado automaticamente pelo sistema Banco de Preços, sem nº de processo/assinatura; (5) há pelo menos uma referência de preço (Item 3) com objeto de contratação aparentemente não equivalente, que merece verificação. | BM67: 2 | BN67: 2 | BO67: 2 | BP67: 2 | BQ67: 2 | BR67: 2 | BS67: 2 | BT67: Não | BU67: Não | BV67: Não | BY67: (1) É um relatório de pesquisa de preços emitido pelo Banco de Preços em 24/08/2026 para a UFJ (PROAF/Diretoria de Compras e Licitações), sob o título "EMPRESA PRISMA 2026", referente à contratação de empresa remanescente de limpeza, conservação e asseio. (2) Pesquisa fundamentada na Lei 14.133/2021 e na IN 65/2021, art. 5º, inc. I, com 3 preços por item, oriundos de contratações públicas similares (Compras.gov.br e PNCP), e método de média aritmética. (3) Resultados: Item 1 – limpeza e conservação, R$ 4,97/m²; Item 2 – material sob demanda + BDI, R$ 20.231,97; Item 3 – equipamentos + BDI, R$ 3.463,47; Valor Global de R$ 23.700,41, calculado sobre quantidade 1 de cada item. (4) Acompanham memorial de cálculo e Termos de Homologação das licitações-fonte, totalizando 259 páginas, com um termo repetido. (5) O documento não identifica o responsável pela pesquisa, não apresenta justificativas metodológicas e não contém assinaturas, exigindo complementação antes do uso. | CA67: 2 | CB67: 2 | CC67: 2 | CD67: 2 | CE67: 2 | CF67: 2 | CG67: 2 | CH67: Não | CI67: Não | CJ67: Não | DA67: 1. É um Relatório de Cotação da UFJ. 2. Estima preços para limpeza, materiais e equipamentos. 3. O Valor Global é de R$ 23.700,41. 4. Utilizou o Banco de Preços e média aritmética (IN 65/2021). 5. Documenta fontes e lances extraídos do Compras.gov.br e PNCP. | DC67: 2 | DD67: 2 | DE67: 2 | DF67: 2 | DG67: 2 | DH67: 2 | DI67: 2 | DJ67: Não | DK67: Não | DL67: Não | DO67: 1. Fundamentação na IN nº 65/2021 e Lei nº 14.133/2021; 2. Apresentação de 3 itens principais (Limpeza, Material e Equipamentos); 3. Valor global estimado em R$ 23.700,41; 4. Utilização de média aritmética e mediana como métodos matemáticos; 5. Geração via sistema Banco de Preços em 24/08/2026. | DQ67: 2 | DR67: 2 | DS67: 2 | DT67: 2 | DU67: 2 | DV67: 2 | DW67: 2 | DX67: Não | DY67: Não | DZ67: Não
A68: 12 | B68: P32 | C68: {=IFERROR(INDEX(DOCUMENTOS!$E:$E,MATCH($A68,DOCUMENTOS!$A:$A,0)),"")} | D68: {=IFERROR(INDEX('BANCO DE PERGUNTAS'!$D:$D,MATCH($B68,'BANCO DE PERGUNTAS'!$A:$A,0)),"")} -> Qual é a principal finalidade do documento? | E68: {=IFERROR(INDEX('BANCO DE PERGUNTAS'!$B:$B,MATCH($B68,'BANCO DE PERGUNTAS'!$A:$A,0)),"")} -> Síntese | F68: {=IFERROR(INDEX('BANCO DE PERGUNTAS'!$H:$H,MATCH($B68,'BANCO DE PERGUNTAS'!$A:$A,0)),"")} -> 2 | U68: Subsidiar a estimativa de preços e a análise administrativa da contratação de empresa remanescente para serviços continuados de limpeza, conservação e asseio da UFJ, documentando fontes, preços e método de cálculo. (PDF, pp. 1–3 e 21–27.) | W68: 2 | X68: 2 | Y68: 2 | Z68: 2 | AA68: 2 | AB68: 2 | AC68: 2 | AD68: Não | AE68: Não | AF68: Não | AI68: Registrar a pesquisa de mercado e os preços de referência usados para subsidiar a estimativa administrativa da contratação. | AK68: 2 | AL68: 2 | AM68: 2 | AN68: 2 | AO68: 2 | AP68: 2 | AQ68: 2 | AR68: Não | AS68: Não | AT68: Não | BK68: Servir de base para a estimativa de valor de uma futura contratação de serviços de limpeza/conservação (incluindo material sob demanda e equipamentos) pela UFJ, na fase de planejamento, em cumprimento à exigência legal de pesquisa de preços fundamentada (IN 65/2021, Lei 14.133/2021). | BM68: 2 | BN68: 2 | BO68: 2 | BP68: 2 | BQ68: 2 | BR68: 2 | BS68: 2 | BT68: Não | BU68: Não | BV68: Não | BY68: Servir de base técnica para a definição do valor estimado da contratação, instruindo obrigatoriamente a fase preparatória do processo de contratação da UFJ, nos termos do art. 23 da Lei nº 14.133/2021 e da IN SEGES/ME nº 65/2021. | CA68: 2 | CB68: 2 | CC68: 2 | CD68: 2 | CE68: 2 | CF68: 2 | CG68: 2 | CH68: Não | CI68: Não | CJ68: Não | DA68: Fundamentar a estimativa de preços de mercado que servirá de baliza (valor de referência) para o procedimento licitatório da Universidade. | DC68: 2 | DD68: 2 | DE68: 2 | DF68: 2 | DG68: 2 | DH68: 2 | DI68: 2 | DJ68: Não | DK68: Não | DL68: Não | DO68: Servir de suporte documental para a estimativa de despesas em processo de contratação pública. | DQ68: 2 | DR68: 2 | DS68: 2 | DT68: 2 | DU68: 2 | DV68: 2 | DW68: 2 | DX68: Não | DY68: Não | DZ68: Não
A69: 12 | B69: P33 | C69: {=IFERROR(INDEX(DOCUMENTOS!$E:$E,MATCH($A69,DOCUMENTOS!$A:$A,0)),"")} | D69: {=IFERROR(INDEX('BANCO DE PERGUNTAS'!$D:$D,MATCH($B69,'BANCO DE PERGUNTAS'!$A:$A,0)),"")} -> Quais são as três informações mais importantes para um servidor responsável pela análise? | E69: {=IFERROR(INDEX('BANCO DE PERGUNTAS'!$B:$B,MATCH($B69,'BANCO DE PERGUNTAS'!$A:$A,0)),"")} -> Síntese | F69: {=IFERROR(INDEX('BANCO DE PERGUNTAS'!$H:$H,MATCH($B69,'BANCO DE PERGUNTAS'!$A:$A,0)),"")} -> 3 | U69: 1) Objeto e alcance: limpeza continuada da UFJ com mão de obra, insumos, máquinas e equipamentos. 2) Referências financeiras: R$ 4,97/m², R$ 20.231,97 para materiais e R$ 3.463,47 para equipamentos; global R$ 23.700,41 sem indicação anual. 3) Base e limitações: pesquisa de 24/08/2026, três preços por item, média de referências apresentadas como medianas, exigindo conferência da comparabilidade das unidades/especificações e do critério de 30%. (PDF, pp. 1–3 e 21–27.) | W69: 2 | X69: 2 | Y69: 2 | Z69: 2 | AA69: 2 | AB69: 2 | AC69: 2 | AD69: Não | AE69: Não | AF69: Não | AI69: 1) Os preços unitários estimados são R$ 4,97, R$ 20.231,97 e R$ 3.463,47. 2) O total global de R$ 23.700,41 considera quantidade 1 de cada item, não o custo anual. 3) Antes de decidir, validar a autenticidade/versão, a comparabilidade das fontes e as quantidades/memória de cálculo no processo. | AK69: 2 | AL69: 2 | AM69: 2 | AN69: 2 | AO69: 2 | AP69: 2 | AQ69: 2 | AR69: Não | AS69: Não | AT69: Não | BK69: (1) Valor Global estimado: R$ 23.700,41, distribuído em 3 itens; (2) metodologia declarada: média aritmética de no mínimo 3 cotações por item; (3) necessidade de verificar a comparabilidade das fontes de preço dos Itens 2 e 3 (uma delas com objeto aparentemente não relacionado) antes de validar o valor como estimativa oficial. | BM69: 2 | BN69: 2 | BO69: 2 | BP69: 2 | BQ69: 2 | BR69: 2 | BS69: 2 | BT69: Não | BU69: Não | BV69: Não | BY69: (1) O Valor Global de R$ 23.700,41 é soma de preços unitários apurados com quantidade 1 por item e NÃO corresponde ao valor mensal nem ao valor anual da contratação — usá-lo como valor estimado é o erro mais grave possível neste documento. (2) A composição da cesta de preços é frágil em pontos específicos: no Item 2, dois dos três preços vêm do mesmo pregão (Funasa 90009/2026) e do mesmo fornecedor vencedor (CNPJ 51.722.124/0001-11), e no Item 3 um dos preços vem de pregão cujo objeto é "aquisição de materiais esportivos". (3) O relatório não atende integralmente ao art. 3º da IN 65/2021: faltam a identificação do agente responsável pela pesquisa (inciso II) e as justificativas da metodologia e do tratamento de valores atípicos (inciso VI), o que deve ser suprido por documento complementar assinado antes de qualquer decisão. | CA69: 2 | CB69: 2 | CC69: 2 | CD69: 2 | CE69: 2 | CF69: 2 | CG69: 2 | CH69: Não | CI69: Não | CJ69: Não | DA69: 1) O Valor Global Estimado (R$ 23.700,41). 2) A correta aplicação do método matemático legal (Média Aritmética). 3) A equivalência das descrições dos serviços cotados nas fontes externas com o Termo de Referência interno. | DC69: 2 | DD69: 2 | DE69: 2 | DF69: 2 | DG69: 2 | DH69: 2 | DI69: 2 | DJ69: Não | DK69: Não | DL69: Não | DO69: 1. Objeto e quantificação dos itens; 2. Valor estimado (unitário e global); 3. Fontes e parâmetros das cotações governamentais utilizadas. | DQ69: 2 | DR69: 2 | DS69: 2 | DT69: 2 | DU69: 2 | DV69: 2 | DW69: 2 | DX69: Não | DY69: Não | DZ69: Não
A70: 13 | B70: P01 | C70: {=IFERROR(INDEX(DOCUMENTOS!$E:$E,MATCH($A70,DOCUMENTOS!$A:$A,0)),"")} | D70: {=IFERROR(INDEX('BANCO DE PERGUNTAS'!$D:$D,MATCH($B70,'BANCO DE PERGUNTAS'!$A:$A,0)),"")} -> Qual é o objeto principal deste documento? | E70: {=IFERROR(INDEX('BANCO DE PERGUNTAS'!$B:$B,MATCH($B70,'BANCO DE PERGUNTAS'!$A:$A,0)),"")} -> Identificação | F70: {=IFERROR(INDEX('BANCO DE PERGUNTAS'!$H:$H,MATCH($B70,'BANCO DE PERGUNTAS'!$A:$A,0)),"")} -> 1 | U70: Registrar as ordens de serviço de coleta de resíduos da Universidade Federal de Jataí no período de 01/03/2026 a 31/03/2026, com quantidades por ponto e tipo de resíduo e total financeiro. | W70: 2 | X70: 2 | Y70: 2 | Z70: 2 | AA70: 2 | AB70: 2 | AC70: 2 | AD70: Não | AE70: Não | AF70: Não | AI70: Registro da coleta de resíduos da Universidade Federal de Jataí, por ponto de coleta e tipo de resíduo, no período de 01/03/2026 a 31/03/2026, com apuração do excedente e do valor correspondente. | AK70: 2 | AL70: 2 | AM70: 2 | AN70: 2 | AO70: 2 | AP70: 2 | AQ70: 2 | AR70: Não | AS70: Não | AT70: Não | BK70: O documento é o "Boletim/Impressão de Ordem de Serviço de Resíduos" da empresa Bio Resíduos, que registra e totaliza os resíduos coletados na Universidade Federal de Jataí (UFJ) no período de 01/03/2026 a 31/03/2026, para fins de medição e cobrança do serviço de coleta. | BM70: 2 | BN70: 2 | BO70: 2 | BP70: 2 | BQ70: 2 | BR70: 2 | BS70: 2 | BT70: Não | BU70: Não | BV70: Não | BY70: Relatório mensal de coleta de resíduos emitido pela empresa Bio Resíduos (Soluções Ambientais) para a UNIVERSIDADE FEDERAL DE JATAÍ (cliente 13838), intitulado 'IMPRESSÃO ORDEM DE SERVIÇO RESÍDUOS', referente ao período de 01/03/2026 a 31/03/2026. Consolida as ordens de serviço de coleta executadas em 10 pontos do campus, as quantidades por tipo de resíduo e a apuração do valor a pagar (R$ 2.861,34). Pelo nome do arquivo, está sendo utilizado como boletim de medição mensal do contrato. | CA70: 2 | CB70: 2 | CC70: 2 | CD70: 2 | CE70: 2 | CF70: 2 | CG70: 2 | CH70: Não | CI70: Não | CJ70: Não | DA70: Boletim de medição / Impressão de Ordem de Serviço de coleta de resíduos. | DC70: 2 | DD70: 2 | DE70: 2 | DF70: 2 | DG70: 2 | DH70: 2 | DI70: 2 | DJ70: Não | DK70: Não | DL70: Não | DO70: Boletim de medição e ordem de serviço de coleta e destinação de resíduos perigosos/especiais (período de 01/03/2026 a 31/03/2026). | DQ70: 2 | DR70: 2 | DS70: 2 | DT70: 2 | DU70: 2 | DV70: 2 | DW70: 2 | DX70: Não | DY70: Não | DZ70: Não
A71: 13 | B71: P02 | C71: {=IFERROR(INDEX(DOCUMENTOS!$E:$E,MATCH($A71,DOCUMENTOS!$A:$A,0)),"")} | D71: {=IFERROR(INDEX('BANCO DE PERGUNTAS'!$D:$D,MATCH($B71,'BANCO DE PERGUNTAS'!$A:$A,0)),"")} -> Qual é o número ou identificação do documento? | E71: {=IFERROR(INDEX('BANCO DE PERGUNTAS'!$B:$B,MATCH($B71,'BANCO DE PERGUNTAS'!$A:$A,0)),"")} -> Identificação | F71: {=IFERROR(INDEX('BANCO DE PERGUNTAS'!$H:$H,MATCH($B71,'BANCO DE PERGUNTAS'!$A:$A,0)),"")} -> 1 | U71: Título: IMPRESSÃO ORDEM DE SERVICO RESÍDUOS. Constam as O.S. 367.341 a 367.350 e o código de cliente 13838. O identificador 0572838 aparece no nome do arquivo; número único do boletim no corpo: não consta no documento. | W71: 2 | X71: 2 | Y71: 2 | Z71: 2 | AA71: 2 | AB71: 2 | AC71: 2 | AD71: Não | AE71: Não | AF71: Não | AI71: “Impressão Ordem de Serviço Resíduos”; não há número único do relatório. Constam as O.S. 367.341 a 367.350. | AK71: 2 | AL71: 2 | AM71: 2 | AN71: 2 | AO71: 2 | AP71: 2 | AQ71: 2 | AR71: Não | AS71: Não | AT71: Não | BK71: O documento não traz um número de boletim próprio. Constam apenas os números individuais das Ordens de Serviço (O.S.): 367.341, 367.342, 367.343, 367.344, 367.345, 367.346, 367.347, 367.348, 367.349 e 367.350. | BM71: 2 | BN71: 1 | BO71: 1 | BP71: 2 | BQ71: 2 | BR71: 1 | BS71: 2 | BT71: Não | BU71: Sim | BV71: Não | BY71: O documento NÃO possui número próprio de boletim ou de relatório. Identifica-se por: cliente 13838 (UFJ); período 01/03/2026 a 31/03/2026; data/hora de emissão 01/04/2026 16:48:37; e pelas 10 Ordens de Serviço O.S. 367.341 a 367.350. O número 0572838, presente no nome do arquivo (Boletim_medição_(0572838)), aparenta ser o número do documento no sistema SEI da UFJ — deve ser confirmado no processo, pois não consta no corpo do PDF. | CA71: 2 | CB71: 2 | CC71: 2 | CD71: 2 | CE71: 2 | CF71: 2 | CG71: 2 | CH71: Não | CI71: Não | CJ71: Não | DA71: O.S 367.341, 367.343, 367.344, 367.345, 367.346, 367.347, 367.348, 367.349, 367.350 e 367.342. | DC71: 2 | DD71: 1 | DE71: 1 | DF71: 2 | DG71: 2 | DH71: 1 | DI71: 2 | DJ71: Não | DK71: Sim | DL71: Não | DO71: Documento ID 0572838 / Relatório de Medição de Resíduos. | DQ71: 2 | DR71: 1 | DS71: 1 | DT71: 2 | DU71: 2 | DV71: 1 | DW71: 2 | DX71: Não | DY71: Sim | DZ71: Não
A72: 13 | B72: P03 | C72: {=IFERROR(INDEX(DOCUMENTOS!$E:$E,MATCH($A72,DOCUMENTOS!$A:$A,0)),"")} | D72: {=IFERROR(INDEX('BANCO DE PERGUNTAS'!$D:$D,MATCH($B72,'BANCO DE PERGUNTAS'!$A:$A,0)),"")} -> Qual é o número do processo relacionado? | E72: {=IFERROR(INDEX('BANCO DE PERGUNTAS'!$B:$B,MATCH($B72,'BANCO DE PERGUNTAS'!$A:$A,0)),"")} -> Identificação | F72: {=IFERROR(INDEX('BANCO DE PERGUNTAS'!$H:$H,MATCH($B72,'BANCO DE PERGUNTAS'!$A:$A,0)),"")} -> 1 | U72: não consta no documento | W72: 2 | X72: 2 | Y72: 2 | Z72: 2 | AA72: 2 | AB72: 2 | AC72: 2 | AD72: Não | AE72: Não | AF72: Não | AI72: não consta no documento. | AK72: 2 | AL72: 2 | AM72: 2 | AN72: 2 | AO72: 2 | AP72: 2 | AQ72: 2 | AR72: Não | AS72: Não | AT72: Não | BK72: Não consta número de processo administrativo ou licitatório em nenhuma parte do documento. | BM72: 2 | BN72: 2 | BO72: 2 | BP72: 2 | BQ72: 2 | BR72: 2 | BS72: 2 | BT72: Não | BU72: Não | BV72: Não | BY72: NÃO CONSTA. O documento não menciona número de processo administrativo (SEI), número de contrato, termo de referência, nota de empenho nem número de nota fiscal. Essa vinculação precisa ser obtida no processo de contratação. | CA72: 2 | CB72: 2 | CC72: 2 | CD72: 2 | CE72: 2 | CF72: 2 | CG72: 2 | CH72: Não | CI72: Não | CJ72: Não | DA72: A informação não consta no documento. | DC72: 2 | DD72: 2 | DE72: 2 | DF72: 2 | DG72: 2 | DH72: 2 | DI72: 2 | DJ72: Não | DK72: Não | DL72: Não | DO72: Não consta explicitamente no documento analisado. | DQ72: 2 | DR72: 2 | DS72: 2 | DT72: 2 | DU72: 2 | DV72: 2 | DW72: 2 | DX72: Não | DY72: Não | DZ72: Não
